Workbook

Sheet 填写说明
A1: 经销商生意健康度诊断 - 定量指标填写指南
A2: 致各位合作伙伴： 为确保本次生意健康度诊断的公平、公正与准确，请您在填写各项数据时，严格参考以下指标的统计口径、单位与说明
A3: 维度 | B3: 指标名称 | C3: 单位 | D3: 计算公式 / 统计口径 | E3: 填写须知
A4: 业绩 | B4: 合同达成率 | C4: % | D4: 合同达成率=本年度实际销售额 ÷ 本年度合同任务额 | E4: 按百分比填写，保留1位小数。
B5: 销售增长率 | C5: % | D5: 销售增长率 =（本年度实际销售额 − 上年度实际销售额）÷ 上年度实际销售额 | E5: 同上。
A6: 分销 | B6: 网点数量 | C6: 个 | D6: 过去12个月内，与贵公司有过至少一次交易记录的下游门店、分销商总数 | E6: 填整数，单位个。
B7: 核心店占比 | C7: % | D7: 核心店占比=核心门店数 ÷ 网点数量 × 100% | E7: 核心店包括核心形象店和核心分销店 请填写最终比例值，填写范围0～1，按百分比填写，保留1位小数。
B8: 单店产出 | C8: 万元 | D8: 单店产出=全年雨虹分销渠道总销售额 ÷ 网点数量 | E8: 销售额按雨虹业务口径。保留1位小数。
B9: 有效门店占比 | C9: % | D9: 有效门店占比=(有效门店数 ÷ 网点数量) × 100% | E9: 有效门店：指三个月内存在拜访记录，陈列合格上报的门店 请填写最终比例值，填写范围0～1，按百分比填写，保留1位小数。
B10: 人均服务网点数 | C10: 个/人 | D10: 人均服务网点数=网点数量 ÷ (自有销售人员数量 × 雨虹销售额占比 + 虹销员数量) | E10: 自有销售人员数量需按雨虹销售额占比折算（参见自有人员数量指标说明）；虹销员不需折算。
B11: 自有人员数量 | C11: 人 | D11: 由贵公司全职聘用、发放薪酬，且主要职责为销售的人员数量。若同时经营多品牌，后续指标计算时将按雨虹销售额占比折算 | E11: 不包括仓管、物流等非销售岗。虹销员不计入此项。 多品牌经营者：请如实填写自有销售人员总数，指标计算时将以「雨虹业务销售额 ÷ 总销售额」占比进行折算，消除多品牌经营导致的评分偏差。
B12: 人效 | C12: 万元/人 | D12: 人效=全年雨虹业务总销售额 ÷ (自有销售人员数量 × 雨虹销售额占比 + 虹销员数量) | E12: 分子：全年雨虹业务总销售额（非总销售额），按雨虹口径。 分母：自有销售人员数量需按雨虹销售额占比折算；虹销员不需折算。保留1位小数。
B13: 乡镇覆盖率 | C13: % | D13: 乡镇覆盖率=(已覆盖的乡镇/街道数量 ÷ 授权区域内乡镇/街道总数)× 100% | E13: 按百分比填写，保留1位小数。
A14: 零售 | B14: 会员数量 | C14: 人 | D14: 在会员系统正式注册的工长/师傅数量 | E14: /
B15: 会员人均产出 | C15: 万元/人 | D15: 会员人均产出=全年雨虹零售渠道总销售额 ÷ 会员数量 | E15: 销售额按雨虹零售渠道口径。保留2位小数。
A16: 渠道结构 | B16: 渠道均衡发展 | C16: 个 | D16: 贵公司目前重点经营的渠道数量 | E16: 例如，同时经营分销、零售、家装，则填写“3”。
A17: 品类结构 | B17: 品类均衡发展 | C17: 个 | D17: 贵公司目前稳定经营的雨虹品类数量 | E17: 品类包括防水、砂浆、美缝、胶业、卷材、辅材。
A18: 公司运营 | B18: 坪效 | C18: 万元/平方米 | D18: 坪效=全年雨虹业务总销售额 ÷ 仓库中专门用于存储雨虹产品的面积 | E18: 仓库面积严格按雨虹产品实际存储面积计算，不含其他品牌产品存放区域。若仓库为多品牌共用，请按雨虹产品实际占用面积填写。保留2位小数。
B19: 分销会次数 | C19: 次 | D19: 过去12个月内，由贵公司主导组织的面向下游分销商的会议总次数 | E19: /
B20: 专业人士会议次数 | C20: 次 | D20: 过去12个月内，由贵公司主导组织的面向工长/设计师等专业人士的会议总次数 | E20: 例如瓦工会、油工会、设计师沙龙等。
B21: 数字化水平 | C21: 等级（a/b/c/d) | D21: 请根据标准，选择最符合贵公司现状的等级 | E21: a.仅拥有进销存数字化系统水平； b.能够进行数据分析水平； c.具有数字化指标洞察水平； d.尚未采用数字化系统
A22: 意愿度 | B22: 活动参与度 | C22: 等级（a/b/c) | D22: 请根据标准，选择最符合贵公司现状的等级 | E22: a：积极参与品牌方（YH）日常会议、培训、活动，并表现突出 b：参与品牌方（YH）日常会议、培训、活动，较少存在请假、早退等情况 c：基本不参与品牌方（YH）日常会议、培训、活动
B23: 经营意愿 | D23: 请根据标准，选择最符合贵公司现状的等级 | E23: a：对于YH品牌存在巨大经营信心，积极与品牌方（YH）互动沟通，每周不少于1次同品牌方（YH）开展经营沟通，愿意配合品牌方（YH）积极开展市场活动，并投入人力物力等资源开展经营 b：对于YH品牌存在经营信心，较为配合执行品牌方（YH）市场活动政策 c：计划放弃经营YH品牌（指经销商解约），不配合品牌方（YH）日常管理，不协助品牌方（YH）执行市场活动政策
B24: 文化认知度 | D24: 请根据标准，选择最符合贵公司现状的等级 | E24: a：对于东方雨虹企业文化存在清晰认知，认同东方雨虹企业文化，并在日常市场经营活动中积极践行 b：清楚了解东方雨虹企业文化，对于东方雨虹企业文化存在认同 c：不清楚东方雨虹企业文化，不认同东方雨虹企业文化
A26: 附加分指标计算口径说明
A27: 维度 | B27: 指标名称 | C27: 单位 | D27: 计算公式 / 统计口径 | E27: 填写须知
A28: 分销 | B28: 网点覆盖率 | C28: % | D28: 网点覆盖率 = 实际覆盖网点数 ÷ 区域内目标网点总数 | E28: 填小数，如覆盖率90%填 0.9，无需保留小数
B29: 网点活跃度 | C29: % | D29: 网点活跃度 = 近3个月内有进货记录的网点数 ÷ 网点总数 | E29: 填小数，如活跃度45%填 0.45，无需保留小数
A30: 零售 | B30: 会员活跃率 | C30: % | D30: 会员活跃率 = 近3个月内有消费记录的会员数 ÷ 会员总数 | E30: 填小数，如活跃率30%填 0.3，无需保留小数
A31: 家装 | B31: 家装销售占比 | C31: % | D31: 家装销售占比 = 全年家装渠道总销售额 ÷ 全年所有渠道总销售额 | E31: 填小数，如占比2.70%填 0.027，保留2位小数
B32: 月均家装订单数 | C32: 户 | D32: 月均家装订单数 = 全年家装渠道订单总数 ÷ 12 | E32: 填整数，计算结果有小数四舍五入
B33: 家装公司产出/月 | C33: 元 | D33: 单家家装公司月均产出 = 全年家装渠道总销售额 ÷ 合作家装公司总数 ÷ 12 | E33: 填整数，单位为元
A34: 服务 | B34: 工单转化率 | C34: 单 | D34: 工单转化率 = 已转化工单数 ÷ 总工单数 × 100% | E34: 填小数，如转化率45%填 0.45，无需保留小数
B35: 月均工单数量 | C35: 单 | D35: 月均工单数量 = 全年服务业务总工单数 ÷ 12 | E35: 填整数，计算结果有小数四舍五入
A36: 公司维度 | B36: 人效 | C36: 万/人 | D36: 人效 = 全年总销售额 ÷（自有销售人员数量 + 虹销员数量） | E36: 填数值，单位万元/人，保留2位小数
A39: 区域外部市场分析指标填写说明
A40: 维度 | B40: 指标名称 | C40: 单位 | D40: 计算公式 / 统计口径 | E40: 填写须知
A41: 区域市场竞争格局诊断 | B41: 雨虹年度销售额 | C41: 万元 | D41: 本区域雨虹品牌全渠道全年实际销售额 | E41: 填整数，单位万元
B42: 各竞品年度销售额 | C42: 万元 | D42: 德高、立邦及其他主要竞品在本区域的年度预估销售额 | E42: 填整数，单位万元，不清楚可填估算值，无竞品留空即可
B43: 我方市占率 | C43: % | D43: 我方市占率 = 雨虹年度销售额 ÷ 所有品牌销售额合计 × 100% | E43: 自动计算，无需填写，请勿修改此单元格
B44: 最大竞品市占率 | C44: % | D44: 最大竞品市占率 = 竞品中最高销售额 ÷ 所有品牌销售额合计 × 100% | E44: 自动计算，无需填写，请勿修改此单元格
B45: 我方vs最大竞品倍率 | C45: 倍 | D45: 我方vs最大竞品倍率 = 雨虹年度销售额 ÷ 最大竞品年度销售额 | E45: 自动计算，无需填写，请勿修改此单元格
A46: 市场容量与份额分析 | B46: 城区人口 | C46: 万人 | D46: 经销商授权经营区域的城区常住人口数量 | E46: 可从当地统计局公开数据获取，或由区域经理填写。填整数，单位万人。
B47: 户均居住面积 | C47: m²/户 | D47: 经销商所在城市/区域的户均住房建筑面积 | E47: 可从当地住建部门公开数据获取，或使用默认值90m²。填整数。
B48: 户均人口 | C48: 人/户 | D48: 经销商所在城市/区域的户均人口数 | E48: 可从当地统计局公开数据获取，或使用默认值3.0。保留1位小数。
B49: 品类单价 | C49: 元/m² | D49: 该品类在所在区域市场的每平方材料单价。 总体单价 = 防水+砂浆+美缝+卷材+墙辅+胶业+管业各品类单价的加总。 | E49: 建议根据所在区域实际情况，结合该品类适用的房屋面积比重，综合测算品类单价后填写。
B50: 雨虹实际销售额 | C50: 万元 | D50: 经销商在该品类在年度实际销售额（雨虹口径）。 | E50: 由经销商/区域经理根据实际销售数据填写。保留1位小数。
B51: 市场容量 | C51: 万元 | D51: 市场容量 = 人口(万) ÷ 户均人口 × 户均居住面积(m²) × 品类单价(元/m²) × 5% | E51: 自动计算，无需填写，请勿修改此单元格
B52: 市场份额 | C52: % | D52: 市场份额 = 雨虹实际销售额 ÷ 市场容量 × 100% | E52: 自动计算，无需填写，请勿修改此单元格

Sheet 动态诊断表
B1: 经销商生意诊断表
B2: 城市等级 | D2: 三四级 | G2: 商体量 | H2: 1000W-2000W | J2: 说明：通过筛选城市等级/商体量，调用对应数据；红色指标为重要性指标；白色为填写区。
A3: 定量指标参考值 | P3: 附加分指标参考值 | Y3: 区域外部市场分析
A5: 维度 | D5: 指标 | E5: 权重 | F5: 函数项 | G5: 实际值 | H5: 得分 | I5: 优秀值 | J5: 指标 | K5: 权重 | L5: 函数项 | M5: 实际值 | N5: 得分 | O5: 优秀值 | P5: 渠道维度 | Q5: 指标 | S5: 权重 | T5: 函数项 | U5: 实际值 | W5: 得分 | X5: 优秀值 | Y5: 1. 市场容量与份额分析
A6: 增长层 | B6: 渠道维度 | C6: 生意总体 | D6: 合同达成率（%） | E6: =INDEX(数据底稿1!$G:$G,MATCH($D$2&"|"&$H$2&"|合同达成率",数据底稿1!$Z:$Z,0)) -> 0.1 | F6: =IF(G6<=INDEX(数据底稿1!$I:$I,MATCH($D$2&"|"&$H$2&"|合同达成率",数据底稿1!$Z:$Z,0)),G6*INDEX(数据底稿1!$J:$J,MATCH($D$2&"|"&$H$2&"|合同达成率",数据底稿1!$Z:$Z,0)),IF(G6<=INDEX(数据底稿1!$M:$M,MATCH($D$2&"|"&$H$2&"|合同达成率",数据底稿1!$Z:$Z,0)),G6*INDEX(数据底稿1!$N:$N,MATCH($D$2&"|"&$H$2&"|合同达成率",数据底稿1!$Z:$Z,0)),IF(G6<=INDEX(数据底稿1!$Q:$Q,MATCH($D$2&"|"&$H$2&"|合同达成率",数据底稿1!$Z:$Z,0)),G6*INDEX(数据底稿1!$R:$R,MATCH($D$2&"|"&$H$2&"|合同达成率",数据底稿1!$Z:$Z,0)),INDEX(数据底稿1!$V:$V,MATCH($D$2&"|"&$H$2&"|合同达成率",数据底稿1!$Z:$Z,0))))) -> 0.144 | G6: 1 | H6: =IF(ISBLANK(G6),"",F6*100) -> 14.4 | I6: =IFERROR(TEXT(INDEX(数据底稿1!$H:$H,MATCH($D$2&"|"&$H$2&"|合同达成率",数据底稿1!$Z:$Z,0)),"0.0%"),INDEX(数据底稿1!$H:$H,MATCH($D$2&"|"&$H$2&"|合同达成率",数据底稿1!$Z:$Z,0))) -> 100.0% | J6: 销售增长率（%） | K6: =INDEX(数据底稿1!$G:$G,MATCH($D$2&"|"&$H$2&"|销售增长率",数据底稿1!$Z:$Z,0)) -> 0.1 | L6: =IF(M6<INDEX(数据底稿1!$I:$I,MATCH($D$2&"|"&$H$2&"|销售增长率",数据底稿1!$Z:$Z,0)),INDEX(数据底稿1!$J:$J,MATCH($D$2&"|"&$H$2&"|销售增长率",数据底稿1!$Z:$Z,0)),IF(M6<INDEX(数据底稿1!$M:$M,MATCH($D$2&"|"&$H$2&"|销售增长率",数据底稿1!$Z:$Z,0)),INDEX(数据底稿1!$N:$N,MATCH($D$2&"|"&$H$2&"|销售增长率",数据底稿1!$Z:$Z,0)),IF(M6<INDEX(数据底稿1!$Q:$Q,MATCH($D$2&"|"&$H$2&"|销售增长率",数据底稿1!$Z:$Z,0)),INDEX(数据底稿1!$R:$R,MATCH($D$2&"|"&$H$2&"|销售增长率",数据底稿1!$Z:$Z,0)),INDEX(数据底稿1!$V:$V,MATCH($D$2&"|"&$H$2&"|销售增长率",数据底稿1!$Z:$Z,0))))) -> 0.1 | M6: 0.3 | N6: =IF(ISBLANK(M6),"",L6*100) -> 10 | O6: =IFERROR(TEXT(INDEX(数据底稿1!$H:$H,MATCH($D$2&"|"&$H$2&"|销售增长率",数据底稿1!$Z:$Z,0)),"0.0%"),INDEX(数据底稿1!$H:$H,MATCH($D$2&"|"&$H$2&"|销售增长率",数据底稿1!$Z:$Z,0))) -> 15.1% | P6: 零售 | Q6: 会员活跃率 | S6: 0.25 | T6: =IF(U6="","",IF(U6>=INDEX(数据底稿2!C4:K4,1,MATCH($D$2&$H$2,数据底稿2!$C$3:$K$3,0)),90,IF(U6>=INDEX(数据底稿2!C5:K5,1,MATCH($D$2&$H$2,数据底稿2!$C$3:$K$3,0)),70,IF(U6>=INDEX(数据底稿2!C6:K6,1,MATCH($D$2&$H$2,数据底稿2!$C$3:$K$3,0)),50,30)))) -> 70 | U6: 0.1 | W6: =IF(U6="","",T6*S6) -> 17.5 | X6: =INDEX(数据底稿2!C4:K4,1,MATCH($D$2&$H$2,数据底稿2!$C$3:$K$3,0)) -> 0.1318 | Y6: 选择品类 | AA6: 防水
C7: 分销 | D7: 网点数量（个） | E7: =INDEX(数据底稿1!$G:$G,MATCH($D$2&"|"&$H$2&"|网点数量",数据底稿1!$Z:$Z,0)) -> 0.041 | F7: =IF(G7<INDEX(数据底稿1!$I:$I,MATCH($D$2&"|"&$H$2&"|网点数量",数据底稿1!$Z:$Z,0)),INDEX(数据底稿1!$J:$J,MATCH($D$2&"|"&$H$2&"|网点数量",数据底稿1!$Z:$Z,0)),IF(G7<INDEX(数据底稿1!$M:$M,MATCH($D$2&"|"&$H$2&"|网点数量",数据底稿1!$Z:$Z,0)),INDEX(数据底稿1!$N:$N,MATCH($D$2&"|"&$H$2&"|网点数量",数据底稿1!$Z:$Z,0)),IF(INDEX(数据底稿1!$Q:$Q,MATCH($D$2&"|"&$H$2&"|网点数量",数据底稿1!$Z:$Z,0))="",INDEX(数据底稿1!$R:$R,MATCH($D$2&"|"&$H$2&"|网点数量",数据底稿1!$Z:$Z,0)),IF(G7<INDEX(数据底稿1!$Q:$Q,MATCH($D$2&"|"&$H$2&"|网点数量",数据底稿1!$Z:$Z,0)),INDEX(数据底稿1!$R:$R,MATCH($D$2&"|"&$H$2&"|网点数量",数据底稿1!$Z:$Z,0)),IF(INDEX(数据底稿1!$V:$V,MATCH($D$2&"|"&$H$2&"|网点数量",数据底稿1!$Z:$Z,0))="",INDEX(数据底稿1!$R:$R,MATCH($D$2&"|"&$H$2&"|网点数量",数据底稿1!$Z:$Z,0)),INDEX(数据底稿1!$V:$V,MATCH($D$2&"|"&$H$2&"|网点数量",数据底稿1!$Z:$Z,0))))))) -> 90 | G7: 1000 | H7: =IF(ISBLANK(G7),"",F7*E7) -> 3.69 | I7: =INDEX(数据底稿1!$H:$H,MATCH($D$2&"|"&$H$2&"|网点数量",数据底稿1!$Z:$Z,0)) -> 380个 | J7: 单店产出（万元） | K7: =INDEX(数据底稿1!$G:$G,MATCH($D$2&"|"&$H$2&"|单店产出",数据底稿1!$Z:$Z,0)) -> 0.109 | L7: =IF(M7<INDEX(数据底稿1!$I:$I,MATCH($D$2&"|"&$H$2&"|单店产出",数据底稿1!$Z:$Z,0)),INDEX(数据底稿1!$J:$J,MATCH($D$2&"|"&$H$2&"|单店产出",数据底稿1!$Z:$Z,0)),IF(M7<INDEX(数据底稿1!$M:$M,MATCH($D$2&"|"&$H$2&"|单店产出",数据底稿1!$Z:$Z,0)),INDEX(数据底稿1!$N:$N,MATCH($D$2&"|"&$H$2&"|单店产出",数据底稿1!$Z:$Z,0)),IF(INDEX(数据底稿1!$Q:$Q,MATCH($D$2&"|"&$H$2&"|单店产出",数据底稿1!$Z:$Z,0))="",INDEX(数据底稿1!$R:$R,MATCH($D$2&"|"&$H$2&"|单店产出",数据底稿1!$Z:$Z,0)),IF(M7<INDEX(数据底稿1!$Q:$Q,MATCH($D$2&"|"&$H$2&"|单店产出",数据底稿1!$Z:$Z,0)),INDEX(数据底稿1!$R:$R,MATCH($D$2&"|"&$H$2&"|单店产出",数据底稿1!$Z:$Z,0)),IF(INDEX(数据底稿1!$V:$V,MATCH($D$2&"|"&$H$2&"|单店产出",数据底稿1!$Z:$Z,0))="",INDEX(数据底稿1!$R:$R,MATCH($D$2&"|"&$H$2&"|单店产出",数据底稿1!$Z:$Z,0)),INDEX(数据底稿1!$V:$V,MATCH($D$2&"|"&$H$2&"|单店产出",数据底稿1!$Z:$Z,0))))))) -> 90 | M7: 10 | N7: =IF(ISBLANK(M7),"",L7*K7) -> 9.81 | O7: =INDEX(数据底稿1!$H:$H,MATCH($D$2&"|"&$H$2&"|单店产出",数据底稿1!$Z:$Z,0)) -> 4.4万 | Y7: 数据输入
D8: 核心店占比（%） | E8: =INDEX(数据底稿1!$G:$G,MATCH($D$2&"|"&$H$2&"|核心店数量占比",数据底稿1!$Z:$Z,0)) -> 0.041 | F8: =IF(G8<INDEX(数据底稿1!$I:$I,MATCH($D$2&"|"&$H$2&"|核心店数量占比",数据底稿1!$Z:$Z,0)),INDEX(数据底稿1!$J:$J,MATCH($D$2&"|"&$H$2&"|核心店数量占比",数据底稿1!$Z:$Z,0)),IF(G8<INDEX(数据底稿1!$M:$M,MATCH($D$2&"|"&$H$2&"|核心店数量占比",数据底稿1!$Z:$Z,0)),INDEX(数据底稿1!$N:$N,MATCH($D$2&"|"&$H$2&"|核心店数量占比",数据底稿1!$Z:$Z,0)),IF(INDEX(数据底稿1!$Q:$Q,MATCH($D$2&"|"&$H$2&"|核心店数量占比",数据底稿1!$Z:$Z,0))="",INDEX(数据底稿1!$R:$R,MATCH($D$2&"|"&$H$2&"|核心店数量占比",数据底稿1!$Z:$Z,0)),IF(G8<INDEX(数据底稿1!$Q:$Q,MATCH($D$2&"|"&$H$2&"|核心店数量占比",数据底稿1!$Z:$Z,0)),INDEX(数据底稿1!$R:$R,MATCH($D$2&"|"&$H$2&"|核心店数量占比",数据底稿1!$Z:$Z,0)),IF(INDEX(数据底稿1!$V:$V,MATCH($D$2&"|"&$H$2&"|核心店数量占比",数据底稿1!$Z:$Z,0))="",INDEX(数据底稿1!$R:$R,MATCH($D$2&"|"&$H$2&"|核心店数量占比",数据底稿1!$Z:$Z,0)),INDEX(数据底稿1!$V:$V,MATCH($D$2&"|"&$H$2&"|核心店数量占比",数据底稿1!$Z:$Z,0))))))) -> 90 | G8: 0.35 | H8: =IF(ISBLANK(G8),"",F8*E8) -> 3.69 | I8: =IFERROR(TEXT(INDEX(数据底稿1!$H:$H,MATCH($D$2&"|"&$H$2&"|核心店数量占比",数据底稿1!$Z:$Z,0)),"0.0%"),INDEX(数据底稿1!$H:$H,MATCH($D$2&"|"&$H$2&"|核心店数量占比",数据底稿1!$Z:$Z,0))) -> 17.5% | J8: 有效门店占比（%） | K8: =INDEX(数据底稿1!$G:$G,MATCH($D$2&"|"&$H$2&"|有效门店占比",数据底稿1!$Z:$Z,0)) -> 0.09 | L8: =IF(M8<INDEX(数据底稿1!$I:$I,MATCH($D$2&"|"&$H$2&"|有效门店占比",数据底稿1!$Z:$Z,0)),INDEX(数据底稿1!$J:$J,MATCH($D$2&"|"&$H$2&"|有效门店占比",数据底稿1!$Z:$Z,0)),IF(M8<INDEX(数据底稿1!$M:$M,MATCH($D$2&"|"&$H$2&"|有效门店占比",数据底稿1!$Z:$Z,0)),INDEX(数据底稿1!$N:$N,MATCH($D$2&"|"&$H$2&"|有效门店占比",数据底稿1!$Z:$Z,0)),IF(INDEX(数据底稿1!$Q:$Q,MATCH($D$2&"|"&$H$2&"|有效门店占比",数据底稿1!$Z:$Z,0))="",INDEX(数据底稿1!$R:$R,MATCH($D$2&"|"&$H$2&"|有效门店占比",数据底稿1!$Z:$Z,0)),IF(M8<INDEX(数据底稿1!$Q:$Q,MATCH($D$2&"|"&$H$2&"|有效门店占比",数据底稿1!$Z:$Z,0)),INDEX(数据底稿1!$R:$R,MATCH($D$2&"|"&$H$2&"|有效门店占比",数据底稿1!$Z:$Z,0)),IF(INDEX(数据底稿1!$V:$V,MATCH($D$2&"|"&$H$2&"|有效门店占比",数据底稿1!$Z:$Z,0))="",INDEX(数据底稿1!$R:$R,MATCH($D$2&"|"&$H$2&"|有效门店占比",数据底稿1!$Z:$Z,0)),INDEX(数据底稿1!$V:$V,MATCH($D$2&"|"&$H$2&"|有效门店占比",数据底稿1!$Z:$Z,0))))))) -> 90 | M8: 1 | N8: =IF(ISBLANK(M8),"",L8*K8) -> 8.1 | O8: =IFERROR(TEXT(INDEX(数据底稿1!$H:$H,MATCH($D$2&"|"&$H$2&"|有效门店占比",数据底稿1!$Z:$Z,0)),"0.0%"),INDEX(数据底稿1!$H:$H,MATCH($D$2&"|"&$H$2&"|有效门店占比",数据底稿1!$Z:$Z,0))) -> 94.1% | P8: 家装 | Q8: 家装销售占比 | S8: 0.18 | T8: =IF(U8="","",IF(U8>=INDEX(数据底稿2!C7:K7,1,MATCH($D$2&$H$2,数据底稿2!$C$3:$K$3,0)),90,IF(U8>=INDEX(数据底稿2!C8:K8,1,MATCH($D$2&$H$2,数据底稿2!$C$3:$K$3,0)),70,IF(U8>=INDEX(数据底稿2!C9:K9,1,MATCH($D$2&$H$2,数据底稿2!$C$3:$K$3,0)),50,30)))) -> 30 | U8: 0.013 | W8: =IF(U8="","",T8*S8) -> 5.4 | X8: =INDEX(数据底稿2!C7:K7,1,MATCH($D$2&$H$2,数据底稿2!$C$3:$K$3,0)) -> 0.038 | Y8: 城区人口 | Z8: 万人 | AA8: 279
D9: 人均服务网点数（个） | E9: =INDEX(数据底稿1!$G:$G,MATCH($D$2&"|"&$H$2&"|人均服务网点数",数据底稿1!$Z:$Z,0)) -> 0.045 | F9: =IF(G9<INDEX(数据底稿1!$I:$I,MATCH($D$2&"|"&$H$2&"|人均服务网点数",数据底稿1!$Z:$Z,0)),INDEX(数据底稿1!$J:$J,MATCH($D$2&"|"&$H$2&"|人均服务网点数",数据底稿1!$Z:$Z,0)),IF(G9<INDEX(数据底稿1!$M:$M,MATCH($D$2&"|"&$H$2&"|人均服务网点数",数据底稿1!$Z:$Z,0)),INDEX(数据底稿1!$N:$N,MATCH($D$2&"|"&$H$2&"|人均服务网点数",数据底稿1!$Z:$Z,0)),IF(INDEX(数据底稿1!$Q:$Q,MATCH($D$2&"|"&$H$2&"|人均服务网点数",数据底稿1!$Z:$Z,0))="",INDEX(数据底稿1!$R:$R,MATCH($D$2&"|"&$H$2&"|人均服务网点数",数据底稿1!$Z:$Z,0)),IF(G9<INDEX(数据底稿1!$Q:$Q,MATCH($D$2&"|"&$H$2&"|人均服务网点数",数据底稿1!$Z:$Z,0)),INDEX(数据底稿1!$R:$R,MATCH($D$2&"|"&$H$2&"|人均服务网点数",数据底稿1!$Z:$Z,0)),IF(INDEX(数据底稿1!$V:$V,MATCH($D$2&"|"&$H$2&"|人均服务网点数",数据底稿1!$Z:$Z,0))="",INDEX(数据底稿1!$R:$R,MATCH($D$2&"|"&$H$2&"|人均服务网点数",数据底稿1!$Z:$Z,0)),INDEX(数据底稿1!$V:$V,MATCH($D$2&"|"&$H$2&"|人均服务网点数",数据底稿1!$Z:$Z,0))))))) -> 90 | G9: 150 | H9: =IF(ISBLANK(G9),"",F9*E9) -> 4.05 | I9: =IFERROR(TEXT(ROUND(VALUE(SUBSTITUTE(INDEX(数据底稿1!$H:$H,MATCH($D$2&"|"&$H$2&"|人均服务网点数",数据底稿1!$Z:$Z,0)),"个","")),0),"0")&"个",INDEX(数据底稿1!$H:$H,MATCH($D$2&"|"&$H$2&"|人均服务网点数",数据底稿1!$Z:$Z,0))) -> 78个 | J9: 自有人员数量（人） | K9: =INDEX(数据底稿1!$G:$G,MATCH($D$2&"|"&$H$2&"|自有人员数量",数据底稿1!$Z:$Z,0)) -> 0.023 | L9: =IF(M9<INDEX(数据底稿1!$I:$I,MATCH($D$2&"|"&$H$2&"|自有人员数量",数据底稿1!$Z:$Z,0)),INDEX(数据底稿1!$J:$J,MATCH($D$2&"|"&$H$2&"|自有人员数量",数据底稿1!$Z:$Z,0)),IF(M9<INDEX(数据底稿1!$M:$M,MATCH($D$2&"|"&$H$2&"|自有人员数量",数据底稿1!$Z:$Z,0)),INDEX(数据底稿1!$N:$N,MATCH($D$2&"|"&$H$2&"|自有人员数量",数据底稿1!$Z:$Z,0)),IF(INDEX(数据底稿1!$Q:$Q,MATCH($D$2&"|"&$H$2&"|自有人员数量",数据底稿1!$Z:$Z,0))="",INDEX(数据底稿1!$R:$R,MATCH($D$2&"|"&$H$2&"|自有人员数量",数据底稿1!$Z:$Z,0)),IF(M9<INDEX(数据底稿1!$Q:$Q,MATCH($D$2&"|"&$H$2&"|自有人员数量",数据底稿1!$Z:$Z,0)),INDEX(数据底稿1!$R:$R,MATCH($D$2&"|"&$H$2&"|自有人员数量",数据底稿1!$Z:$Z,0)),IF(INDEX(数据底稿1!$V:$V,MATCH($D$2&"|"&$H$2&"|自有人员数量",数据底稿1!$Z:$Z,0))="",INDEX(数据底稿1!$R:$R,MATCH($D$2&"|"&$H$2&"|自有人员数量",数据底稿1!$Z:$Z,0)),INDEX(数据底稿1!$V:$V,MATCH($D$2&"|"&$H$2&"|自有人员数量",数据底稿1!$Z:$Z,0))))))) -> 90 | M9: 6 | N9: =IF(ISBLANK(M9),"",L9*K9) -> 2.07 | O9: =INDEX(数据底稿1!$H:$H,MATCH($D$2&"|"&$H$2&"|自有人员数量",数据底稿1!$Z:$Z,0)) -> 4人
D10: 人效（万元/人） | E10: =INDEX(数据底稿1!$G:$G,MATCH($D$2&"|"&$H$2&"|人效",数据底稿1!$Z:$Z,0)) -> 0.086 | F10: =IF(G10<INDEX(数据底稿1!$I:$I,MATCH($D$2&"|"&$H$2&"|人效",数据底稿1!$Z:$Z,0)),INDEX(数据底稿1!$J:$J,MATCH($D$2&"|"&$H$2&"|人效",数据底稿1!$Z:$Z,0)),IF(G10<INDEX(数据底稿1!$M:$M,MATCH($D$2&"|"&$H$2&"|人效",数据底稿1!$Z:$Z,0)),INDEX(数据底稿1!$N:$N,MATCH($D$2&"|"&$H$2&"|人效",数据底稿1!$Z:$Z,0)),IF(INDEX(数据底稿1!$Q:$Q,MATCH($D$2&"|"&$H$2&"|人效",数据底稿1!$Z:$Z,0))="",INDEX(数据底稿1!$R:$R,MATCH($D$2&"|"&$H$2&"|人效",数据底稿1!$Z:$Z,0)),IF(G10<INDEX(数据底稿1!$Q:$Q,MATCH($D$2&"|"&$H$2&"|人效",数据底稿1!$Z:$Z,0)),INDEX(数据底稿1!$R:$R,MATCH($D$2&"|"&$H$2&"|人效",数据底稿1!$Z:$Z,0)),IF(INDEX(数据底稿1!$V:$V,MATCH($D$2&"|"&$H$2&"|人效",数据底稿1!$Z:$Z,0))="",INDEX(数据底稿1!$R:$R,MATCH($D$2&"|"&$H$2&"|人效",数据底稿1!$Z:$Z,0)),INDEX(数据底稿1!$V:$V,MATCH($D$2&"|"&$H$2&"|人效",数据底稿1!$Z:$Z,0))))))) -> 90 | G10: 1000 | H10: =IF(ISBLANK(G10),"",F10*E10) -> 7.74 | I10: =INDEX(数据底稿1!$H:$H,MATCH($D$2&"|"&$H$2&"|人效",数据底稿1!$Z:$Z,0)) -> 490.9万/人 | J10: 乡镇覆盖率（%） | K10: =INDEX(数据底稿1!$G:$G,MATCH($D$2&"|"&$H$2&"|乡镇覆盖率",数据底稿1!$Z:$Z,0)) -> 0.014 | L10: =IF(M10<INDEX(数据底稿1!$I:$I,MATCH($D$2&"|"&$H$2&"|乡镇覆盖率",数据底稿1!$Z:$Z,0)),INDEX(数据底稿1!$J:$J,MATCH($D$2&"|"&$H$2&"|乡镇覆盖率",数据底稿1!$Z:$Z,0)),IF(M10<INDEX(数据底稿1!$M:$M,MATCH($D$2&"|"&$H$2&"|乡镇覆盖率",数据底稿1!$Z:$Z,0)),INDEX(数据底稿1!$N:$N,MATCH($D$2&"|"&$H$2&"|乡镇覆盖率",数据底稿1!$Z:$Z,0)),IF(INDEX(数据底稿1!$Q:$Q,MATCH($D$2&"|"&$H$2&"|乡镇覆盖率",数据底稿1!$Z:$Z,0))="",INDEX(数据底稿1!$R:$R,MATCH($D$2&"|"&$H$2&"|乡镇覆盖率",数据底稿1!$Z:$Z,0)),IF(M10<INDEX(数据底稿1!$Q:$Q,MATCH($D$2&"|"&$H$2&"|乡镇覆盖率",数据底稿1!$Z:$Z,0)),INDEX(数据底稿1!$R:$R,MATCH($D$2&"|"&$H$2&"|乡镇覆盖率",数据底稿1!$Z:$Z,0)),IF(INDEX(数据底稿1!$V:$V,MATCH($D$2&"|"&$H$2&"|乡镇覆盖率",数据底稿1!$Z:$Z,0))="",INDEX(数据底稿1!$R:$R,MATCH($D$2&"|"&$H$2&"|乡镇覆盖率",数据底稿1!$Z:$Z,0)),INDEX(数据底稿1!$V:$V,MATCH($D$2&"|"&$H$2&"|乡镇覆盖率",数据底稿1!$Z:$Z,0))))))) -> 70 | M10: 1 | N10: =IF(ISBLANK(M10),"",L10*K10) -> 0.98 | O10: =IFERROR(TEXT(INDEX(数据底稿1!$H:$H,MATCH($D$2&"|"&$H$2&"|乡镇覆盖率",数据底稿1!$Z:$Z,0)),"0.0%"),INDEX(数据底稿1!$H:$H,MATCH($D$2&"|"&$H$2&"|乡镇覆盖率",数据底稿1!$Z:$Z,0))) -> 100.0% | Q10: 家装公司产出/月（元） | S10: 0.17 | T10: =IF(U10="","",IF(U10>=INDEX(数据底稿2!C10:K10,1,MATCH($D$2&$H$2,数据底稿2!$C$3:$K$3,0)),90,IF(U10>=INDEX(数据底稿2!C11:K11,1,MATCH($D$2&$H$2,数据底稿2!$C$3:$K$3,0)),70,IF(U10>=INDEX(数据底稿2!C12:K12,1,MATCH($D$2&$H$2,数据底稿2!$C$3:$K$3,0)),50,30)))) -> 70 | U10: 2000 | W10: =IF(U10="","",T10*S10) -> 11.9 | X10: =INDEX(数据底稿2!C10:K10,1,MATCH($D$2&$H$2,数据底稿2!$C$3:$K$3,0)) -> 2864 | Y10: 户均居住面积 | Z10: m²/户 | AA10: 90
C11: 零售 | D11: 会员数量（人） | E11: =INDEX(数据底稿1!$G:$G,MATCH($D$2&"|"&$H$2&"|会员数量",数据底稿1!$Z:$Z,0)) -> 0.025 | F11: =IF(G11<INDEX(数据底稿1!$I:$I,MATCH($D$2&"|"&$H$2&"|会员数量",数据底稿1!$Z:$Z,0)),INDEX(数据底稿1!$J:$J,MATCH($D$2&"|"&$H$2&"|会员数量",数据底稿1!$Z:$Z,0)),IF(G11<INDEX(数据底稿1!$M:$M,MATCH($D$2&"|"&$H$2&"|会员数量",数据底稿1!$Z:$Z,0)),INDEX(数据底稿1!$N:$N,MATCH($D$2&"|"&$H$2&"|会员数量",数据底稿1!$Z:$Z,0)),IF(INDEX(数据底稿1!$Q:$Q,MATCH($D$2&"|"&$H$2&"|会员数量",数据底稿1!$Z:$Z,0))="",INDEX(数据底稿1!$R:$R,MATCH($D$2&"|"&$H$2&"|会员数量",数据底稿1!$Z:$Z,0)),IF(G11<INDEX(数据底稿1!$Q:$Q,MATCH($D$2&"|"&$H$2&"|会员数量",数据底稿1!$Z:$Z,0)),INDEX(数据底稿1!$R:$R,MATCH($D$2&"|"&$H$2&"|会员数量",数据底稿1!$Z:$Z,0)),IF(INDEX(数据底稿1!$V:$V,MATCH($D$2&"|"&$H$2&"|会员数量",数据底稿1!$Z:$Z,0))="",INDEX(数据底稿1!$R:$R,MATCH($D$2&"|"&$H$2&"|会员数量",数据底稿1!$Z:$Z,0)),INDEX(数据底稿1!$V:$V,MATCH($D$2&"|"&$H$2&"|会员数量",数据底稿1!$Z:$Z,0))))))) -> 90 | G11: 200 | H11: =IF(ISBLANK(G11),"",F11*E11) -> 2.25 | I11: =INDEX(数据底稿1!$H:$H,MATCH($D$2&"|"&$H$2&"|会员数量",数据底稿1!$Z:$Z,0)) -> 127人 | J11: 会员人均产出（万元/人） | K11: =INDEX(数据底稿1!$G:$G,MATCH($D$2&"|"&$H$2&"|会员人均产出",数据底稿1!$Z:$Z,0)) -> 0.025 | L11: =IF(M11<INDEX(数据底稿1!$I:$I,MATCH($D$2&"|"&$H$2&"|会员人均产出",数据底稿1!$Z:$Z,0)),INDEX(数据底稿1!$J:$J,MATCH($D$2&"|"&$H$2&"|会员人均产出",数据底稿1!$Z:$Z,0)),IF(M11<INDEX(数据底稿1!$M:$M,MATCH($D$2&"|"&$H$2&"|会员人均产出",数据底稿1!$Z:$Z,0)),INDEX(数据底稿1!$N:$N,MATCH($D$2&"|"&$H$2&"|会员人均产出",数据底稿1!$Z:$Z,0)),IF(INDEX(数据底稿1!$Q:$Q,MATCH($D$2&"|"&$H$2&"|会员人均产出",数据底稿1!$Z:$Z,0))="",INDEX(数据底稿1!$R:$R,MATCH($D$2&"|"&$H$2&"|会员人均产出",数据底稿1!$Z:$Z,0)),IF(M11<INDEX(数据底稿1!$Q:$Q,MATCH($D$2&"|"&$H$2&"|会员人均产出",数据底稿1!$Z:$Z,0)),INDEX(数据底稿1!$R:$R,MATCH($D$2&"|"&$H$2&"|会员人均产出",数据底稿1!$Z:$Z,0)),IF(INDEX(数据底稿1!$V:$V,MATCH($D$2&"|"&$H$2&"|会员人均产出",数据底稿1!$Z:$Z,0))="",INDEX(数据底稿1!$R:$R,MATCH($D$2&"|"&$H$2&"|会员人均产出",数据底稿1!$Z:$Z,0)),INDEX(数据底稿1!$V:$V,MATCH($D$2&"|"&$H$2&"|会员人均产出",数据底稿1!$Z:$Z,0))))))) -> 90 | M11: 2 | N11: =IF(ISBLANK(M11),"",L11*K11) -> 2.25 | O11: =IFERROR(TEXT(VALUE(SUBSTITUTE(SUBSTITUTE(INDEX(数据底稿1!$H:$H,MATCH($D$2&"|"&$H$2&"|会员人均产出",数据底稿1!$Z:$Z,0)),"万/人",""),"万","")),"0.00")&"万/人",INDEX(数据底稿1!$H:$H,MATCH($D$2&"|"&$H$2&"|会员人均产出",数据底稿1!$Z:$Z,0))) -> 1.01万/人
C12: 渠道均衡发展 | D12: 渠道数量 | E12: =INDEX(数据底稿1!$G:$G,MATCH($D$2&"|"&$H$2&"|渠道数量",数据底稿1!$Z:$Z,0)) -> 0.06 | F12: =IF(G12<INDEX(数据底稿1!$I:$I,MATCH($D$2&"|"&$H$2&"|渠道数量",数据底稿1!$Z:$Z,0)),INDEX(数据底稿1!$J:$J,MATCH($D$2&"|"&$H$2&"|渠道数量",数据底稿1!$Z:$Z,0)),IF(G12<INDEX(数据底稿1!$M:$M,MATCH($D$2&"|"&$H$2&"|渠道数量",数据底稿1!$Z:$Z,0)),INDEX(数据底稿1!$N:$N,MATCH($D$2&"|"&$H$2&"|渠道数量",数据底稿1!$Z:$Z,0)),IF(OR(INDEX(数据底稿1!$Q:$Q,MATCH($D$2&"|"&$H$2&"|渠道数量",数据底稿1!$Z:$Z,0))="",G12<INDEX(数据底稿1!$Q:$Q,MATCH($D$2&"|"&$H$2&"|渠道数量",数据底稿1!$Z:$Z,0))),INDEX(数据底稿1!$R:$R,MATCH($D$2&"|"&$H$2&"|渠道数量",数据底稿1!$Z:$Z,0)),INDEX(数据底稿1!$V:$V,MATCH($D$2&"|"&$H$2&"|渠道数量",数据底稿1!$Z:$Z,0))))) -> 90 | G12: 4 | H12: =IF(ISBLANK(G12),"",F12*E12) -> 5.4 | I12: =INDEX(数据底稿1!$H:$H,MATCH($D$2&"|"&$H$2&"|渠道数量",数据底稿1!$Z:$Z,0)) -> 4个 | Y12: 户均人口 | Z12: 人/户 | AA12: 2.6
B13: 品类维度 | C13: 品类均衡发展 | D13: 品类数量 | E13: =INDEX(数据底稿1!$G:$G,MATCH($D$2&"|"&$H$2&"|品类数量",数据底稿1!$Z:$Z,0)) -> 0.06 | F13: =IF(G13<INDEX(数据底稿1!$I:$I,MATCH($D$2&"|"&$H$2&"|品类数量",数据底稿1!$Z:$Z,0)),INDEX(数据底稿1!$J:$J,MATCH($D$2&"|"&$H$2&"|品类数量",数据底稿1!$Z:$Z,0)),IF(G13<INDEX(数据底稿1!$M:$M,MATCH($D$2&"|"&$H$2&"|品类数量",数据底稿1!$Z:$Z,0)),INDEX(数据底稿1!$N:$N,MATCH($D$2&"|"&$H$2&"|品类数量",数据底稿1!$Z:$Z,0)),IF(OR(INDEX(数据底稿1!$Q:$Q,MATCH($D$2&"|"&$H$2&"|品类数量",数据底稿1!$Z:$Z,0))="",G13<INDEX(数据底稿1!$Q:$Q,MATCH($D$2&"|"&$H$2&"|品类数量",数据底稿1!$Z:$Z,0))),INDEX(数据底稿1!$R:$R,MATCH($D$2&"|"&$H$2&"|品类数量",数据底稿1!$Z:$Z,0)),INDEX(数据底稿1!$V:$V,MATCH($D$2&"|"&$H$2&"|品类数量",数据底稿1!$Z:$Z,0))))) -> 90 | G13: 5 | H13: =IF(ISBLANK(G13),"",F13*E13) -> 5.4 | I13: =INDEX(数据底稿1!$H:$H,MATCH($D$2&"|"&$H$2&"|品类数量",数据底稿1!$Z:$Z,0)) -> 5个 | P13: 服务 | Q13: 工单转化率 | S13: 0.24 | T13: =IF(U13="","",IF(U13>=INDEX(数据底稿2!C16:K16,1,MATCH($D$2&$H$2,数据底稿2!$C$3:$K$3,0)),90,IF(U13>=INDEX(数据底稿2!C17:K17,1,MATCH($D$2&$H$2,数据底稿2!$C$3:$K$3,0)),70,IF(U13>=INDEX(数据底稿2!C18:K18,1,MATCH($D$2&$H$2,数据底稿2!$C$3:$K$3,0)),50,30)))) -> 90 | U13: 0.28 | W13: =IF(U13="","",T13*S13) -> 21.6 | X13: =INDEX(数据底稿2!C16:K16,1,MATCH($D$2&$H$2,数据底稿2!$C$3:$K$3,0)) -> 0.274 | Y13: =IF(AA6="总体","雨虹产品总体单价",AA6&"品类单价") -> 防水品类单价 | Z13: 元/m² | AA13: 30
A14: 支撑层 | B14: 公司维度 | C14: 会议场次 | D14: 分销会次数（次） | E14: =INDEX(数据底稿1!$G:$G,MATCH($D$2&"|"&$H$2&"|分销会次数",数据底稿1!$Z:$Z,0)) -> 0.03 | F14: =IF(G14<INDEX(数据底稿1!$I:$I,MATCH($D$2&"|"&$H$2&"|分销会次数",数据底稿1!$Z:$Z,0)),INDEX(数据底稿1!$J:$J,MATCH($D$2&"|"&$H$2&"|分销会次数",数据底稿1!$Z:$Z,0)),IF(G14<INDEX(数据底稿1!$M:$M,MATCH($D$2&"|"&$H$2&"|分销会次数",数据底稿1!$Z:$Z,0)),INDEX(数据底稿1!$N:$N,MATCH($D$2&"|"&$H$2&"|分销会次数",数据底稿1!$Z:$Z,0)),IF(INDEX(数据底稿1!$Q:$Q,MATCH($D$2&"|"&$H$2&"|分销会次数",数据底稿1!$Z:$Z,0))="",INDEX(数据底稿1!$R:$R,MATCH($D$2&"|"&$H$2&"|分销会次数",数据底稿1!$Z:$Z,0)),IF(G14<INDEX(数据底稿1!$Q:$Q,MATCH($D$2&"|"&$H$2&"|分销会次数",数据底稿1!$Z:$Z,0)),INDEX(数据底稿1!$R:$R,MATCH($D$2&"|"&$H$2&"|分销会次数",数据底稿1!$Z:$Z,0)),IF(INDEX(数据底稿1!$V:$V,MATCH($D$2&"|"&$H$2&"|分销会次数",数据底稿1!$Z:$Z,0))="",INDEX(数据底稿1!$R:$R,MATCH($D$2&"|"&$H$2&"|分销会次数",数据底稿1!$Z:$Z,0)),INDEX(数据底稿1!$V:$V,MATCH($D$2&"|"&$H$2&"|分销会次数",数据底稿1!$Z:$Z,0))))))) -> 90 | G14: 8 | H14: =IF(ISBLANK(G14),"",F14*E14) -> 2.7 | I14: =INDEX(数据底稿1!$H:$H,MATCH($D$2&"|"&$H$2&"|分销会次数",数据底稿1!$Z:$Z,0)) -> 5次 | J14: 专业人士会议次数（次） | K14: =INDEX(数据底稿1!$G:$G,MATCH($D$2&"|"&$H$2&"|专业人士会议次数",数据底稿1!$Z:$Z,0)) -> 0.029 | L14: =IF(M14<INDEX(数据底稿1!$I:$I,MATCH($D$2&"|"&$H$2&"|专业人士会议次数",数据底稿1!$Z:$Z,0)),INDEX(数据底稿1!$J:$J,MATCH($D$2&"|"&$H$2&"|专业人士会议次数",数据底稿1!$Z:$Z,0)),IF(M14<INDEX(数据底稿1!$M:$M,MATCH($D$2&"|"&$H$2&"|专业人士会议次数",数据底稿1!$Z:$Z,0)),INDEX(数据底稿1!$N:$N,MATCH($D$2&"|"&$H$2&"|专业人士会议次数",数据底稿1!$Z:$Z,0)),IF(M14<INDEX(数据底稿1!$Q:$Q,MATCH($D$2&"|"&$H$2&"|专业人士会议次数",数据底稿1!$Z:$Z,0)),INDEX(数据底稿1!$R:$R,MATCH($D$2&"|"&$H$2&"|专业人士会议次数",数据底稿1!$Z:$Z,0)),IF(M14<=40,INDEX(数据底稿1!$V:$V,MATCH($D$2&"|"&$H$2&"|专业人士会议次数",数据底稿1!$Z:$Z,0)),50)))) -> 90 | M14: 38 | N14: =IF(ISBLANK(M14),"",L14*K14) -> 2.61 | O14: =INDEX(数据底稿1!$H:$H,MATCH($D$2&"|"&$H$2&"|专业人士会议次数",数据底稿1!$Z:$Z,0)) -> 28次 | Y14: ="品类单价填写提示：建议根据所在区域实际情况，结合该品类适用的房屋面积比重，综合测算品类单价后填写。"&IF(AA6="总体","总体单价为所有品类单价的加总。","") -> 品类单价填写提示：建议根据所在区域实际情况，结合该品类适用的房屋面积比重，综合测算品类单价后填写。
C15: 仓储效率 | D15: 坪效（万元/平方米） | E15: =INDEX(数据底稿1!$G:$G,MATCH($D$2&"|"&$H$2&"|坪效",数据底稿1!$Z:$Z,0)) -> 0.039 | F15: =IF(G15<INDEX(数据底稿1!$I:$I,MATCH($D$2&"|"&$H$2&"|坪效",数据底稿1!$Z:$Z,0)),INDEX(数据底稿1!$J:$J,MATCH($D$2&"|"&$H$2&"|坪效",数据底稿1!$Z:$Z,0)),IF(G15<INDEX(数据底稿1!$M:$M,MATCH($D$2&"|"&$H$2&"|坪效",数据底稿1!$Z:$Z,0)),INDEX(数据底稿1!$N:$N,MATCH($D$2&"|"&$H$2&"|坪效",数据底稿1!$Z:$Z,0)),IF(INDEX(数据底稿1!$Q:$Q,MATCH($D$2&"|"&$H$2&"|坪效",数据底稿1!$Z:$Z,0))="",INDEX(数据底稿1!$R:$R,MATCH($D$2&"|"&$H$2&"|坪效",数据底稿1!$Z:$Z,0)),IF(G15<INDEX(数据底稿1!$Q:$Q,MATCH($D$2&"|"&$H$2&"|坪效",数据底稿1!$Z:$Z,0)),INDEX(数据底稿1!$R:$R,MATCH($D$2&"|"&$H$2&"|坪效",数据底稿1!$Z:$Z,0)),IF(INDEX(数据底稿1!$V:$V,MATCH($D$2&"|"&$H$2&"|坪效",数据底稿1!$Z:$Z,0))="",INDEX(数据底稿1!$R:$R,MATCH($D$2&"|"&$H$2&"|坪效",数据底稿1!$Z:$Z,0)),INDEX(数据底稿1!$V:$V,MATCH($D$2&"|"&$H$2&"|坪效",数据底稿1!$Z:$Z,0))))))) -> 90 | G15: 3 | H15: =IF(ISBLANK(G15),"",F15*E15) -> 3.51 | I15: =IFERROR(TEXT(VALUE(SUBSTITUTE(INDEX(数据底稿1!$H:$H,MATCH($D$2&"|"&$H$2&"|坪效",数据底稿1!$Z:$Z,0)),"万/平方米","")),"0.00")&"万/平方米",INDEX(数据底稿1!$H:$H,MATCH($D$2&"|"&$H$2&"|坪效",数据底稿1!$Z:$Z,0))) -> 1.38万/平方米 | Q15: 月均工单数量（单） | S15: 0.16 | T15: =IF(U15="","",IF(U15>=INDEX(数据底稿2!C13:K13,1,MATCH($D$2&$H$2,数据底稿2!$C$3:$K$3,0)),90,IF(U15>=INDEX(数据底稿2!C14:K14,1,MATCH($D$2&$H$2,数据底稿2!$C$3:$K$3,0)),70,IF(U15>=INDEX(数据底稿2!C15:K15,1,MATCH($D$2&$H$2,数据底稿2!$C$3:$K$3,0)),50,30)))) -> 70 | U15: 20 | W15: =IF(U15="","",T15*S15) -> 11.2 | X15: =INDEX(数据底稿2!C13:K13,1,MATCH($D$2&$H$2,数据底稿2!$C$3:$K$3,0)) -> 38
C16: 数字化水平 （a/b/c/d） | E16: =INDEX(数据底稿1!$G:$G,MATCH($D$2&"|"&$H$2&"|数字化水平",数据底稿1!$Z:$Z,0)) -> 0.033 | F16: =IF(G16=INDEX(数据底稿1!$I:$I,MATCH($D$2&"|"&$H$2&"|数字化水平",数据底稿1!$Z:$Z,0)),INDEX(数据底稿1!$J:$J,MATCH($D$2&"|"&$H$2&"|数字化水平",数据底稿1!$Z:$Z,0)),IF(G16=INDEX(数据底稿1!$M:$M,MATCH($D$2&"|"&$H$2&"|数字化水平",数据底稿1!$Z:$Z,0)),INDEX(数据底稿1!$N:$N,MATCH($D$2&"|"&$H$2&"|数字化水平",数据底稿1!$Z:$Z,0)),IF(G16=INDEX(数据底稿1!$Q:$Q,MATCH($D$2&"|"&$H$2&"|数字化水平",数据底稿1!$Z:$Z,0)),INDEX(数据底稿1!$R:$R,MATCH($D$2&"|"&$H$2&"|数字化水平",数据底稿1!$Z:$Z,0)),IF(G16=INDEX(数据底稿1!$U:$U,MATCH($D$2&"|"&$H$2&"|数字化水平",数据底稿1!$Z:$Z,0)),INDEX(数据底稿1!$V:$V,MATCH($D$2&"|"&$H$2&"|数字化水平",数据底稿1!$Z:$Z,0)),0)))) -> 90 | G16: c | H16: =IF(ISBLANK(G16),"",F16*E16) -> 2.97 | I16: a. 仅拥有进销存数字化系统水平 b. 能够进行数据分析水平 c. 具有数字化指标洞察水平 d. 尚未采用数字化系统 | Y16: 雨虹实际销售额 | Z16: 万元 | AA16: 3000.1
A18: 意愿层 | B18: 意愿维度 | C18: 活动参与度 （a/b/c） | E18: =INDEX(数据底稿1!$G:$G,MATCH($D$2&"|"&$H$2&"|活动参与度",数据底稿1!$Z:$Z,0)) -> 0.015 | F18: =IF(G18=INDEX(数据底稿1!$I:$I,MATCH($D$2&"|"&$H$2&"|活动参与度",数据底稿1!$Z:$Z,0)),INDEX(数据底稿1!$J:$J,MATCH($D$2&"|"&$H$2&"|活动参与度",数据底稿1!$Z:$Z,0)),IF(G18=INDEX(数据底稿1!$M:$M,MATCH($D$2&"|"&$H$2&"|活动参与度",数据底稿1!$Z:$Z,0)),INDEX(数据底稿1!$N:$N,MATCH($D$2&"|"&$H$2&"|活动参与度",数据底稿1!$Z:$Z,0)),IF(G18=INDEX(数据底稿1!$Q:$Q,MATCH($D$2&"|"&$H$2&"|活动参与度",数据底稿1!$Z:$Z,0)),INDEX(数据底稿1!$R:$R,MATCH($D$2&"|"&$H$2&"|活动参与度",数据底稿1!$Z:$Z,0)),IF(G18=INDEX(数据底稿1!$U:$U,MATCH($D$2&"|"&$H$2&"|活动参与度",数据底稿1!$Z:$Z,0)),INDEX(数据底稿1!$V:$V,MATCH($D$2&"|"&$H$2&"|活动参与度",数据底稿1!$Z:$Z,0)),0)))) -> 90 | G18: a | H18: =IF(ISBLANK(G18),"",F18*E18) -> 1.35 | I18: a. 积极参与品牌方（YH）日常会议、培训、活动，并表现突出 b. 参与品牌方（YH）日常会议、培训、活动，较少存在请假、早退等情况 c. 基本不参与品牌方（YH）日常会议、培训、活动 | P18: 品类及渠道参考值 | Y18: 计算输出
Q19: 防水 | R19: 砂浆 | U19: 美缝 | W19: 卷材 | Y19: ="市场容量（"&AA6&"品类）" -> 市场容量（防水品类） | Z19: 万元 | AA19: =AA8/AA12*AA10*AA13*5% -> 14486.538
C20: 经营意愿 （a/b/c） | E20: =INDEX(数据底稿1!$G:$G,MATCH($D$2&"|"&$H$2&"|经营意愿",数据底稿1!$Z:$Z,0)) -> 0.02 | F20: =IF(G20=INDEX(数据底稿1!$I:$I,MATCH($D$2&"|"&$H$2&"|经营意愿",数据底稿1!$Z:$Z,0)),INDEX(数据底稿1!$J:$J,MATCH($D$2&"|"&$H$2&"|经营意愿",数据底稿1!$Z:$Z,0)),IF(G20=INDEX(数据底稿1!$M:$M,MATCH($D$2&"|"&$H$2&"|经营意愿",数据底稿1!$Z:$Z,0)),INDEX(数据底稿1!$N:$N,MATCH($D$2&"|"&$H$2&"|经营意愿",数据底稿1!$Z:$Z,0)),IF(G20=INDEX(数据底稿1!$Q:$Q,MATCH($D$2&"|"&$H$2&"|经营意愿",数据底稿1!$Z:$Z,0)),INDEX(数据底稿1!$R:$R,MATCH($D$2&"|"&$H$2&"|经营意愿",数据底稿1!$Z:$Z,0)),IF(G20=INDEX(数据底稿1!$U:$U,MATCH($D$2&"|"&$H$2&"|经营意愿",数据底稿1!$Z:$Z,0)),INDEX(数据底稿1!$V:$V,MATCH($D$2&"|"&$H$2&"|经营意愿",数据底稿1!$Z:$Z,0)),0)))) -> 90 | G20: a | H20: =IF(ISBLANK(G20),"",F20*E20) -> 1.8 | I20: a. 对于YH品牌存在巨大经营信心，积极与品牌方（YH）互动沟通，每周不少于1次同品牌方（YH）开展经营沟通，愿意配合品牌方（YH）积极开展市场活动，并投入人力物力等资源开展经营 b. 对于YH品牌存在经营信心，较为配合执行品牌方（YH）市场活动政策 c. 计划放弃经营YH品牌（指经销商解约），不配合品牌方（YH）日常管理，不协助品牌方（YH）执行市场活动政策
P21: 优秀值 | Q21: =IFERROR(INDEX(数据底稿2!$A$50:$N$59,MATCH($D$2&$H$2,数据底稿2!$A$50:$A$59,0),2),"/") -> 458.8万 | R21: =IFERROR(INDEX(数据底稿2!$A$50:$N$59,MATCH($D$2&$H$2,数据底稿2!$A$50:$A$59,0),3),"/") -> 754.2万 | U21: =IFERROR(INDEX(数据底稿2!$A$50:$N$59,MATCH($D$2&$H$2,数据底稿2!$A$50:$A$59,0),4),"/") -> 112.7万 | W21: =IFERROR(INDEX(数据底稿2!$A$50:$N$59,MATCH($D$2&$H$2,数据底稿2!$A$50:$A$59,0),5),"/") -> 189.2万 | Y21: ="市场份额（"&AA6&"品类）" -> 市场份额（防水品类） | Z21: / | AA21: =IF(AA19=0,"-",AA16/AA19) -> 0.20709571
C22: 文化认知度 （a/b/c） | E22: =INDEX(数据底稿1!$G:$G,MATCH($D$2&"|"&$H$2&"|文化认知度",数据底稿1!$Z:$Z,0)) -> 0.015 | F22: =IF(G22=INDEX(数据底稿1!$I:$I,MATCH($D$2&"|"&$H$2&"|文化认知度",数据底稿1!$Z:$Z,0)),INDEX(数据底稿1!$J:$J,MATCH($D$2&"|"&$H$2&"|文化认知度",数据底稿1!$Z:$Z,0)),IF(G22=INDEX(数据底稿1!$M:$M,MATCH($D$2&"|"&$H$2&"|文化认知度",数据底稿1!$Z:$Z,0)),INDEX(数据底稿1!$N:$N,MATCH($D$2&"|"&$H$2&"|文化认知度",数据底稿1!$Z:$Z,0)),IF(G22=INDEX(数据底稿1!$Q:$Q,MATCH($D$2&"|"&$H$2&"|文化认知度",数据底稿1!$Z:$Z,0)),INDEX(数据底稿1!$R:$R,MATCH($D$2&"|"&$H$2&"|文化认知度",数据底稿1!$Z:$Z,0)),IF(G22=INDEX(数据底稿1!$U:$U,MATCH($D$2&"|"&$H$2&"|文化认知度",数据底稿1!$Z:$Z,0)),INDEX(数据底稿1!$V:$V,MATCH($D$2&"|"&$H$2&"|文化认知度",数据底稿1!$Z:$Z,0)),0)))) -> 90 | G22: a | H22: =IF(ISBLANK(G22),"",F22*E22) -> 1.35 | I22: a. 对于东方雨虹企业文化存在清晰认知，认同东方雨虹企业文化，并在日常市场经营活动中积极践行 b. 清楚了解东方雨虹企业文化，对于东方雨虹企业文化存在认同 c. 不清楚东方雨虹企业文化，不认同东方雨虹企业文化 | Y22: 公式：市场容量 = 人口(万) ÷ 户均人口 × 户均居住面积(m²) × 品类单价(元/m²) × 5%。 市场份额 = 雨虹实际销售额 ÷ 市场容量。注：5%系数按房屋20年翻新一次估算。
Q23: 墙辅 | R23: 胶业 | U23: 管业 | Y23: 2. 区域市场竞争格局诊断
A24: 最终得分 | C24: =SUM(H6:H23,N6:N11,N14)*数据底稿3!B3+SUM(W6,W8,W10,W13,W15)*数据底稿3!B4 -> 90.416
P25: 优秀值 | Q25: =IFERROR(INDEX(数据底稿2!$A$50:$N$59,MATCH($D$2&$H$2,数据底稿2!$A$50:$A$59,0),6),"/") -> 52.7万 | R25: =IFERROR(INDEX(数据底稿2!$A$50:$N$59,MATCH($D$2&$H$2,数据底稿2!$A$50:$A$59,0),7),"/") -> 20.2万 | U25: =IFERROR(INDEX(数据底稿2!$A$50:$N$59,MATCH($D$2&$H$2,数据底稿2!$A$50:$A$59,0),8),"/") -> 21.3万 | Y25: 数据输入
A26: 评语 | C26: 结果性评价 | D26: 合同达成率 | G26: =IF(OR(G6="",ISERROR(G6)),"",IFERROR(IF(G6<=INDEX(数据底稿1!$I:$I,MATCH($D$2&"|"&$H$2&"|合同达成率",数据底稿1!$Z:$Z,0)),INDEX(数据底稿1!$L:$L,MATCH($D$2&"|"&$H$2&"|合同达成率",数据底稿1!$Z:$Z,0)),IF(G6<=INDEX(数据底稿1!$M:$M,MATCH($D$2&"|"&$H$2&"|合同达成率",数据底稿1!$Z:$Z,0)),INDEX(数据底稿1!$P:$P,MATCH($D$2&"|"&$H$2&"|合同达成率",数据底稿1!$Z:$Z,0)),IF(OR(INDEX(数据底稿1!$Q:$Q,MATCH($D$2&"|"&$H$2&"|合同达成率",数据底稿1!$Z:$Z,0))="",G6<=INDEX(数据底稿1!$Q:$Q,MATCH($D$2&"|"&$H$2&"|合同达成率",数据底稿1!$Z:$Z,0))),INDEX(数据底稿1!$T:$T,MATCH($D$2&"|"&$H$2&"|合同达成率",数据底稿1!$Z:$Z,0)),IFERROR(IF(INDEX(数据底稿1!$X:$X,MATCH($D$2&"|"&$H$2&"|合同达成率",数据底稿1!$Z:$Z,0))="","",INDEX(数据底稿1!$X:$X,MATCH($D$2&"|"&$H$2&"|合同达成率",数据底稿1!$Z:$Z,0))),"")))),"")) -> 全年合同达百，整体表现优异。建议深入分析单份合同达成差异，防范个别合同达成不力带来的风险。 | Y26: 品牌 | AA26: 年度预估销售(万元)
D27: 销售增长率 | G27: =IF(OR(M6="",ISERROR(M6)),"",IFERROR(IF(M6<=INDEX(数据底稿1!$I:$I,MATCH($D$2&"|"&$H$2&"|销售增长率",数据底稿1!$Z:$Z,0)),INDEX(数据底稿1!$L:$L,MATCH($D$2&"|"&$H$2&"|销售增长率",数据底稿1!$Z:$Z,0)),IF(M6<=INDEX(数据底稿1!$M:$M,MATCH($D$2&"|"&$H$2&"|销售增长率",数据底稿1!$Z:$Z,0)),INDEX(数据底稿1!$P:$P,MATCH($D$2&"|"&$H$2&"|销售增长率",数据底稿1!$Z:$Z,0)),IF(OR(INDEX(数据底稿1!$Q:$Q,MATCH($D$2&"|"&$H$2&"|销售增长率",数据底稿1!$Z:$Z,0))="",M6<=INDEX(数据底稿1!$Q:$Q,MATCH($D$2&"|"&$H$2&"|销售增长率",数据底稿1!$Z:$Z,0))),INDEX(数据底稿1!$T:$T,MATCH($D$2&"|"&$H$2&"|销售增长率",数据底稿1!$Z:$Z,0)),IFERROR(IF(INDEX(数据底稿1!$X:$X,MATCH($D$2&"|"&$H$2&"|销售增长率",数据底稿1!$Z:$Z,0))="","",INDEX(数据底稿1!$X:$X,MATCH($D$2&"|"&$H$2&"|销售增长率",数据底稿1!$Z:$Z,0))),"")))),"")) -> 销售增长率处于同类经销商中的领先水平，增长动力强劲。建议关注各品类的增长表现，识别增长引擎品类，制定可持续增长策略，避免短期波动影响长期发展。 | Q27: 分销 | R27: 零售 | U27: 家装 | W27: 服务 | Y27: 雨虹 | AA27: 100
C28: 渠道维度 | D28: 网点数量 | G28: =IF(OR(C26=FALSE,C26="",ISERROR(C26)),"",IF(OR(G7="",ISERROR(G7)),"",IFERROR(IF(G7<=INDEX(数据底稿1!$I:$I,MATCH($D$2&"|"&$H$2&"|网点数量",数据底稿1!$Z:$Z,0)),INDEX(数据底稿1!$L:$L,MATCH($D$2&"|"&$H$2&"|网点数量",数据底稿1!$Z:$Z,0)),IF(G7<=INDEX(数据底稿1!$M:$M,MATCH($D$2&"|"&$H$2&"|网点数量",数据底稿1!$Z:$Z,0)),INDEX(数据底稿1!$P:$P,MATCH($D$2&"|"&$H$2&"|网点数量",数据底稿1!$Z:$Z,0)),IF(OR(INDEX(数据底稿1!$Q:$Q,MATCH($D$2&"|"&$H$2&"|网点数量",数据底稿1!$Z:$Z,0))="",G7<=INDEX(数据底稿1!$Q:$Q,MATCH($D$2&"|"&$H$2&"|网点数量",数据底稿1!$Z:$Z,0))),INDEX(数据底稿1!$T:$T,MATCH($D$2&"|"&$H$2&"|网点数量",数据底稿1!$Z:$Z,0)),IFERROR(IF(INDEX(数据底稿1!$X:$X,MATCH($D$2&"|"&$H$2&"|网点数量",数据底稿1!$Z:$Z,0))="","",INDEX(数据底稿1!$X:$X,MATCH($D$2&"|"&$H$2&"|网点数量",数据底稿1!$Z:$Z,0))),"")))),""))) -> 网点数量处于同类经销商中的领先水平，网点覆盖广泛，网络基础扎实。建议重点提升单店产值和核心店占比，优化网点质量；同时建立网点分级管理体系，提高网点运营效率。 | Y28: 德高 | AA28: 80
D29: 核心店数量占比 | G29: =IF(OR(C26=FALSE,C26="",ISERROR(C26)),"",IF(OR(G8="",ISERROR(G8)),"",IFERROR(IF(G8<=INDEX(数据底稿1!$I:$I,MATCH($D$2&"|"&$H$2&"|核心店数量占比",数据底稿1!$Z:$Z,0)),INDEX(数据底稿1!$L:$L,MATCH($D$2&"|"&$H$2&"|核心店数量占比",数据底稿1!$Z:$Z,0)),IF(G8<=INDEX(数据底稿1!$M:$M,MATCH($D$2&"|"&$H$2&"|核心店数量占比",数据底稿1!$Z:$Z,0)),INDEX(数据底稿1!$P:$P,MATCH($D$2&"|"&$H$2&"|核心店数量占比",数据底稿1!$Z:$Z,0)),IF(OR(INDEX(数据底稿1!$Q:$Q,MATCH($D$2&"|"&$H$2&"|核心店数量占比",数据底稿1!$Z:$Z,0))="",G8<=INDEX(数据底稿1!$Q:$Q,MATCH($D$2&"|"&$H$2&"|核心店数量占比",数据底稿1!$Z:$Z,0))),INDEX(数据底稿1!$T:$T,MATCH($D$2&"|"&$H$2&"|核心店数量占比",数据底稿1!$Z:$Z,0)),IFERROR(IF(INDEX(数据底稿1!$X:$X,MATCH($D$2&"|"&$H$2&"|核心店数量占比",数据底稿1!$Z:$Z,0))="","",INDEX(数据底稿1!$X:$X,MATCH($D$2&"|"&$H$2&"|核心店数量占比",数据底稿1!$Z:$Z,0))),"")))),""))) -> 核心店数量占比处于同类经销商中的领先水平，核心资源集中，分销渠道增长由核心店驱动，市场竞争力强。建议持续关注核心店达成情况，保持增长动力。 | P29: 优秀值 | Q29: =IFERROR(INDEX(数据底稿2!$A$50:$N$59,MATCH($D$2&$H$2,数据底稿2!$A$50:$A$59,0),9),"/") -> 1250.5万 | R29: =IFERROR(INDEX(数据底稿2!$A$50:$N$59,MATCH($D$2&$H$2,数据底稿2!$A$50:$A$59,0),10),"/") -> 71.3万 | U29: =IFERROR(INDEX(数据底稿2!$A$50:$N$59,MATCH($D$2&$H$2,数据底稿2!$A$50:$A$59,0),11),"/") -> 28.7万 | W29: =IFERROR(INDEX(数据底稿2!$A$50:$N$59,MATCH($D$2&$H$2,数据底稿2!$A$50:$A$59,0),12),"/") -> 3.9万 | Y29: 立邦 | AA29: 95
D30: 人均服务网点数 | G30: =IF(OR(C26=FALSE,C26="",ISERROR(C26)),"",IF(OR(G9="",ISERROR(G9)),"",IFERROR(IF(G9<=INDEX(数据底稿1!$I:$I,MATCH($D$2&"|"&$H$2&"|人均服务网点数",数据底稿1!$Z:$Z,0)),INDEX(数据底稿1!$L:$L,MATCH($D$2&"|"&$H$2&"|人均服务网点数",数据底稿1!$Z:$Z,0)),IF(G9<=INDEX(数据底稿1!$M:$M,MATCH($D$2&"|"&$H$2&"|人均服务网点数",数据底稿1!$Z:$Z,0)),INDEX(数据底稿1!$P:$P,MATCH($D$2&"|"&$H$2&"|人均服务网点数",数据底稿1!$Z:$Z,0)),IF(OR(INDEX(数据底稿1!$Q:$Q,MATCH($D$2&"|"&$H$2&"|人均服务网点数",数据底稿1!$Z:$Z,0))="",G9<=INDEX(数据底稿1!$Q:$Q,MATCH($D$2&"|"&$H$2&"|人均服务网点数",数据底稿1!$Z:$Z,0))),INDEX(数据底稿1!$T:$T,MATCH($D$2&"|"&$H$2&"|人均服务网点数",数据底稿1!$Z:$Z,0)),IFERROR(IF(INDEX(数据底稿1!$X:$X,MATCH($D$2&"|"&$H$2&"|人均服务网点数",数据底稿1!$Z:$Z,0))="","",INDEX(数据底稿1!$X:$X,MATCH($D$2&"|"&$H$2&"|人均服务网点数",数据底稿1!$Z:$Z,0))),"")))),""))) -> 人均服务网点数处于同类经销商中的领先水平，单兵服务密度极高，人员负荷处于满载状态。建议关注人效，防止服务质量下降。 | Y30: 其他主要竞品1 | AA30: 20
D31: 人效 | G31: =IF(OR(C26=FALSE,C26="",ISERROR(C26)),"",IF(OR(G10="",ISERROR(G10)),"",IFERROR(IF(G10<=INDEX(数据底稿1!$I:$I,MATCH($D$2&"|"&$H$2&"|人效",数据底稿1!$Z:$Z,0)),INDEX(数据底稿1!$L:$L,MATCH($D$2&"|"&$H$2&"|人效",数据底稿1!$Z:$Z,0)),IF(G10<=INDEX(数据底稿1!$M:$M,MATCH($D$2&"|"&$H$2&"|人效",数据底稿1!$Z:$Z,0)),INDEX(数据底稿1!$P:$P,MATCH($D$2&"|"&$H$2&"|人效",数据底稿1!$Z:$Z,0)),IF(OR(INDEX(数据底稿1!$Q:$Q,MATCH($D$2&"|"&$H$2&"|人效",数据底稿1!$Z:$Z,0))="",G10<=INDEX(数据底稿1!$Q:$Q,MATCH($D$2&"|"&$H$2&"|人效",数据底稿1!$Z:$Z,0))),INDEX(数据底稿1!$T:$T,MATCH($D$2&"|"&$H$2&"|人效",数据底稿1!$Z:$Z,0)),IFERROR(IF(INDEX(数据底稿1!$X:$X,MATCH($D$2&"|"&$H$2&"|人效",数据底稿1!$Z:$Z,0))="","",INDEX(数据底稿1!$X:$X,MATCH($D$2&"|"&$H$2&"|人效",数据底稿1!$Z:$Z,0))),"")))),""))) -> 人效处于同类经销商中的领先水平，人力资源利用充分，人均创造价值高。建议关注销售额整体构成，提升净利润水平。 | P31: 品类结构 （防水：砂浆：美缝：卷材：墙辅：胶业+管业） | U31: 渠道结构 （分销：零售：家装+工装） | Y31: 其他主要竞品2 | AA31: 70
D32: 乡镇覆盖率 | G32: =IF(OR(C26=FALSE,C26="",ISERROR(C26)),"",IF(OR(M10="",ISERROR(M10)),"",IFERROR(IF(M10<=INDEX(数据底稿1!$I:$I,MATCH($D$2&"|"&$H$2&"|乡镇覆盖率",数据底稿1!$Z:$Z,0)),INDEX(数据底稿1!$L:$L,MATCH($D$2&"|"&$H$2&"|乡镇覆盖率",数据底稿1!$Z:$Z,0)),IF(M10<=INDEX(数据底稿1!$M:$M,MATCH($D$2&"|"&$H$2&"|乡镇覆盖率",数据底稿1!$Z:$Z,0)),INDEX(数据底稿1!$P:$P,MATCH($D$2&"|"&$H$2&"|乡镇覆盖率",数据底稿1!$Z:$Z,0)),IF(OR(INDEX(数据底稿1!$Q:$Q,MATCH($D$2&"|"&$H$2&"|乡镇覆盖率",数据底稿1!$Z:$Z,0))="",M10<=INDEX(数据底稿1!$Q:$Q,MATCH($D$2&"|"&$H$2&"|乡镇覆盖率",数据底稿1!$Z:$Z,0))),INDEX(数据底稿1!$T:$T,MATCH($D$2&"|"&$H$2&"|乡镇覆盖率",数据底稿1!$Z:$Z,0)),IFERROR(IF(INDEX(数据底稿1!$X:$X,MATCH($D$2&"|"&$H$2&"|乡镇覆盖率",数据底稿1!$Z:$Z,0))="","",INDEX(数据底稿1!$X:$X,MATCH($D$2&"|"&$H$2&"|乡镇覆盖率",数据底稿1!$Z:$Z,0))),"")))),""))) -> 乡镇覆盖率处于同类经销商中的领先水平，乡镇市场渗透充分。建议关注乡镇网点的产值表现，制定差异化运营方案，优化产品和服务策略。 | P32: 优秀值 | Q32: =IFERROR(INDEX(数据底稿2!$A$50:$N$59,MATCH($D$2&$H$2,数据底稿2!$A$50:$A$59,0),13),"/") -> 33 : 44 : 7 : 10 : 2 : 4 | U32: 优秀值 | V32: =IFERROR(INDEX(数据底稿2!$A$50:$N$59,MATCH($D$2&$H$2,数据底稿2!$A$50:$A$59,0),14),"/") -> 93：04：03 | Y32: ……
D33: 单店产出 | G33: =IF(OR(C26=FALSE,C26="",ISERROR(C26)),"",IF(OR(M7="",ISERROR(M7)),"",IFERROR(IF(M7<=INDEX(数据底稿1!$I:$I,MATCH($D$2&"|"&$H$2&"|单店产出",数据底稿1!$Z:$Z,0)),INDEX(数据底稿1!$L:$L,MATCH($D$2&"|"&$H$2&"|单店产出",数据底稿1!$Z:$Z,0)),IF(M7<=INDEX(数据底稿1!$M:$M,MATCH($D$2&"|"&$H$2&"|单店产出",数据底稿1!$Z:$Z,0)),INDEX(数据底稿1!$P:$P,MATCH($D$2&"|"&$H$2&"|单店产出",数据底稿1!$Z:$Z,0)),IF(OR(INDEX(数据底稿1!$Q:$Q,MATCH($D$2&"|"&$H$2&"|单店产出",数据底稿1!$Z:$Z,0))="",M7<=INDEX(数据底稿1!$Q:$Q,MATCH($D$2&"|"&$H$2&"|单店产出",数据底稿1!$Z:$Z,0))),INDEX(数据底稿1!$T:$T,MATCH($D$2&"|"&$H$2&"|单店产出",数据底稿1!$Z:$Z,0)),IFERROR(IF(INDEX(数据底稿1!$X:$X,MATCH($D$2&"|"&$H$2&"|单店产出",数据底稿1!$Z:$Z,0))="","",INDEX(数据底稿1!$X:$X,MATCH($D$2&"|"&$H$2&"|单店产出",数据底稿1!$Z:$Z,0))),"")))),""))) -> 单店产值处于同类经销商中的领先水平，头部门店表现突出。建议分析头部门店成功经验，复制推广至其他门店，防范因过度依赖少数头部门店而导致的结构性风险。 | P33: 附加分指标评语 | Y33: ……
D34: 有效门店占比 | G34: =IF(OR(C26=FALSE,C26="",ISERROR(C26)),"",IF(OR(M8="",ISERROR(M8)),"",IFERROR(IF(M8<=INDEX(数据底稿1!$I:$I,MATCH($D$2&"|"&$H$2&"|有效门店占比",数据底稿1!$Z:$Z,0)),INDEX(数据底稿1!$L:$L,MATCH($D$2&"|"&$H$2&"|有效门店占比",数据底稿1!$Z:$Z,0)),IF(M8<=INDEX(数据底稿1!$M:$M,MATCH($D$2&"|"&$H$2&"|有效门店占比",数据底稿1!$Z:$Z,0)),INDEX(数据底稿1!$P:$P,MATCH($D$2&"|"&$H$2&"|有效门店占比",数据底稿1!$Z:$Z,0)),IF(OR(INDEX(数据底稿1!$Q:$Q,MATCH($D$2&"|"&$H$2&"|有效门店占比",数据底稿1!$Z:$Z,0))="",M8<=INDEX(数据底稿1!$Q:$Q,MATCH($D$2&"|"&$H$2&"|有效门店占比",数据底稿1!$Z:$Z,0))),INDEX(数据底稿1!$T:$T,MATCH($D$2&"|"&$H$2&"|有效门店占比",数据底稿1!$Z:$Z,0)),IFERROR(IF(INDEX(数据底稿1!$X:$X,MATCH($D$2&"|"&$H$2&"|有效门店占比",数据底稿1!$Z:$Z,0))="","",INDEX(数据底稿1!$X:$X,MATCH($D$2&"|"&$H$2&"|有效门店占比",数据底稿1!$Z:$Z,0))),"")))),""))) -> 有效门店占比处于同类经销商中的领先水平，网点拜访率及陈列合格率高，资源利用效率高。建议关注高拜访率门店的产值表现。 | P34: 会员活跃率 | R34: =IF(U6="","",IF(U6>=INDEX(数据底稿2!C4:K4,1,MATCH($D$2&$H$2,数据底稿2!$C$3:$K$3,0)),数据底稿2!$B$22,IF(U6>=INDEX(数据底稿2!C5:K5,1,MATCH($D$2&$H$2,数据底稿2!$C$3:$K$3,0)),数据底稿2!$C$22,IF(U6>=INDEX(数据底稿2!C6:K6,1,MATCH($D$2&$H$2,数据底稿2!$C$3:$K$3,0)),数据底稿2!$D$22,数据底稿2!$E$22)))) -> 会员活跃率接近参考值，仍有提升空间 | Y34: 计算输出
D35: 自有人员数量 | G35: =IF(OR(C26=FALSE,C26="",ISERROR(C26)),"",IF(OR(M9="",ISERROR(M9)),"",IFERROR(IF(M9<=INDEX(数据底稿1!$I:$I,MATCH($D$2&"|"&$H$2&"|自有人员数量",数据底稿1!$Z:$Z,0)),INDEX(数据底稿1!$L:$L,MATCH($D$2&"|"&$H$2&"|自有人员数量",数据底稿1!$Z:$Z,0)),IF(M9<=INDEX(数据底稿1!$M:$M,MATCH($D$2&"|"&$H$2&"|自有人员数量",数据底稿1!$Z:$Z,0)),INDEX(数据底稿1!$P:$P,MATCH($D$2&"|"&$H$2&"|自有人员数量",数据底稿1!$Z:$Z,0)),IF(OR(INDEX(数据底稿1!$Q:$Q,MATCH($D$2&"|"&$H$2&"|自有人员数量",数据底稿1!$Z:$Z,0))="",M9<=INDEX(数据底稿1!$Q:$Q,MATCH($D$2&"|"&$H$2&"|自有人员数量",数据底稿1!$Z:$Z,0))),INDEX(数据底稿1!$T:$T,MATCH($D$2&"|"&$H$2&"|自有人员数量",数据底稿1!$Z:$Z,0)),IFERROR(IF(INDEX(数据底稿1!$X:$X,MATCH($D$2&"|"&$H$2&"|自有人员数量",数据底稿1!$Z:$Z,0))="","",INDEX(数据底稿1!$X:$X,MATCH($D$2&"|"&$H$2&"|自有人员数量",数据底稿1!$Z:$Z,0))),"")))),""))) -> 自有人员数量处于同类经销商中的领先水平，具备深耕市场的团队基础。建议结合渠道发展合理分工，加强人员专业技能培训，提升团队整体素质；建立人员梯队建设计划，保障团队可持续发展。 | Y35: 我方市占率（vs竞品合计） | AA35: =AA27/SUM(AA27:AA33) -> 0.2739726
D36: 会员数量 | G36: =IF(OR(C26=FALSE,C26="",ISERROR(C26)),"",IF(OR(G11="",ISERROR(G11)),"",IFERROR(IF(G11<=INDEX(数据底稿1!$I:$I,MATCH($D$2&"|"&$H$2&"|会员数量",数据底稿1!$Z:$Z,0)),INDEX(数据底稿1!$L:$L,MATCH($D$2&"|"&$H$2&"|会员数量",数据底稿1!$Z:$Z,0)),IF(G11<=INDEX(数据底稿1!$M:$M,MATCH($D$2&"|"&$H$2&"|会员数量",数据底稿1!$Z:$Z,0)),INDEX(数据底稿1!$P:$P,MATCH($D$2&"|"&$H$2&"|会员数量",数据底稿1!$Z:$Z,0)),IF(OR(INDEX(数据底稿1!$Q:$Q,MATCH($D$2&"|"&$H$2&"|会员数量",数据底稿1!$Z:$Z,0))="",G11<=INDEX(数据底稿1!$Q:$Q,MATCH($D$2&"|"&$H$2&"|会员数量",数据底稿1!$Z:$Z,0))),INDEX(数据底稿1!$T:$T,MATCH($D$2&"|"&$H$2&"|会员数量",数据底稿1!$Z:$Z,0)),IFERROR(IF(INDEX(数据底稿1!$X:$X,MATCH($D$2&"|"&$H$2&"|会员数量",数据底稿1!$Z:$Z,0))="","",INDEX(数据底稿1!$X:$X,MATCH($D$2&"|"&$H$2&"|会员数量",数据底稿1!$Z:$Z,0))),"")))),""))) -> 会员数量处于同类经销商中的领先水平，市场影响力强，客户资源丰富。建议建立会员分级管理体系，提升高价值会员服务质量；制定会员活跃度提升计划，增强会员粘性。 | P36: 家装销售占比 | R36: =IF(U8="","",IF(U8>=INDEX(数据底稿2!C7:K7,1,MATCH($D$2&$H$2,数据底稿2!$C$3:$K$3,0)),数据底稿2!$B$23,IF(U8>=INDEX(数据底稿2!C8:K8,1,MATCH($D$2&$H$2,数据底稿2!$C$3:$K$3,0)),数据底稿2!$C$23,IF(U8>=INDEX(数据底稿2!C9:K9,1,MATCH($D$2&$H$2,数据底稿2!$C$3:$K$3,0)),数据底稿2!$D$23,数据底稿2!$E$23)))) -> 家装销售占比显著偏低，亟需开发家装渠道，如油工、设计带动等 | Y36: 最大竞品市占率 | AA36: =MAX(AA28:AA33)/SUM(AA27:AA33) -> 0.26027397
D37: 会员人均产值 | G37: =IF(OR(C26=FALSE,C26="",ISERROR(C26)),"",IF(OR(M11="",ISERROR(M11)),"",IFERROR(IF(M11<=INDEX(数据底稿1!$I:$I,MATCH($D$2&"|"&$H$2&"|会员人均产出",数据底稿1!$Z:$Z,0)),INDEX(数据底稿1!$L:$L,MATCH($D$2&"|"&$H$2&"|会员人均产出",数据底稿1!$Z:$Z,0)),IF(M11<=INDEX(数据底稿1!$M:$M,MATCH($D$2&"|"&$H$2&"|会员人均产出",数据底稿1!$Z:$Z,0)),INDEX(数据底稿1!$P:$P,MATCH($D$2&"|"&$H$2&"|会员人均产出",数据底稿1!$Z:$Z,0)),IF(OR(INDEX(数据底稿1!$Q:$Q,MATCH($D$2&"|"&$H$2&"|会员人均产出",数据底稿1!$Z:$Z,0))="",M11<=INDEX(数据底稿1!$Q:$Q,MATCH($D$2&"|"&$H$2&"|会员人均产出",数据底稿1!$Z:$Z,0))),INDEX(数据底稿1!$T:$T,MATCH($D$2&"|"&$H$2&"|会员人均产出",数据底稿1!$Z:$Z,0)),IFERROR(IF(INDEX(数据底稿1!$X:$X,MATCH($D$2&"|"&$H$2&"|会员人均产出",数据底稿1!$Z:$Z,0))="","",INDEX(数据底稿1!$X:$X,MATCH($D$2&"|"&$H$2&"|会员人均产出",数据底稿1!$Z:$Z,0))),"")))),""))) -> 会员人均产出处于同类经销商中的领先水平，核心会员粘性强、贡献大。建议与核心会员签订协议，建立长期合作关系，保证稳定性。 | Y37: 我方 vs 最大竞品倍率 | AA37: =IF(MAX(AA28:AA33)=0,"-",AA27/MAX(AA28:AA33)) -> 1.0526316
D38: 渠道数量 | G38: =IF(OR(C26=FALSE,C26="",ISERROR(C26)),"",IF(OR(G12="",ISERROR(G12)),"",IFERROR(IF(G12<INDEX(数据底稿1!$I:$I,MATCH($D$2&"|"&$H$2&"|渠道数量",数据底稿1!$Z:$Z,0)),INDEX(数据底稿1!$L:$L,MATCH($D$2&"|"&$H$2&"|渠道数量",数据底稿1!$Z:$Z,0)),IF(G12<INDEX(数据底稿1!$M:$M,MATCH($D$2&"|"&$H$2&"|渠道数量",数据底稿1!$Z:$Z,0)),INDEX(数据底稿1!$P:$P,MATCH($D$2&"|"&$H$2&"|渠道数量",数据底稿1!$Z:$Z,0)),IF(OR(INDEX(数据底稿1!$Q:$Q,MATCH($D$2&"|"&$H$2&"|渠道数量",数据底稿1!$Z:$Z,0))="",G12<INDEX(数据底稿1!$Q:$Q,MATCH($D$2&"|"&$H$2&"|渠道数量",数据底稿1!$Z:$Z,0))),INDEX(数据底稿1!$T:$T,MATCH($D$2&"|"&$H$2&"|渠道数量",数据底稿1!$Z:$Z,0)),IFERROR(IF(INDEX(数据底稿1!$X:$X,MATCH($D$2&"|"&$H$2&"|渠道数量",数据底稿1!$Z:$Z,0))="","",INDEX(数据底稿1!$X:$X,MATCH($D$2&"|"&$H$2&"|渠道数量",数据底稿1!$Z:$Z,0))),"")))),""))) -> 渠道数量处于同类经销商中的领先水平，业务结构健康多元，具备一定盈利能力和发展潜力，抗风险能力强。建议针对低产出渠道进行资源倾斜。 | P38: 家装公司产出/月 | R38: =IF(U10="","",IF(U10>=INDEX(数据底稿2!C10:K10,1,MATCH($D$2&$H$2,数据底稿2!$C$3:$K$3,0)),数据底稿2!$B$24,IF(U10>=INDEX(数据底稿2!C11:K11,1,MATCH($D$2&$H$2,数据底稿2!$C$3:$K$3,0)),数据底稿2!$C$24,IF(U10>=INDEX(数据底稿2!C12:K12,1,MATCH($D$2&$H$2,数据底稿2!$C$3:$K$3,0)),数据底稿2!$D$24,数据底稿2!$E$24)))) -> 单家装公司产出接近参考值，可持续挖掘单客价值 | Y38: 竞争格局评语
C39: 品类维度 | D39: 品类数量 | G39: =IF(OR(C26=FALSE,C26="",ISERROR(C26)),"",IF(OR(G13="",ISERROR(G13)),"",IFERROR(IF(G13<INDEX(数据底稿1!$I:$I,MATCH($D$2&"|"&$H$2&"|品类数量",数据底稿1!$Z:$Z,0)),INDEX(数据底稿1!$L:$L,MATCH($D$2&"|"&$H$2&"|品类数量",数据底稿1!$Z:$Z,0)),IF(G13<INDEX(数据底稿1!$M:$M,MATCH($D$2&"|"&$H$2&"|品类数量",数据底稿1!$Z:$Z,0)),INDEX(数据底稿1!$P:$P,MATCH($D$2&"|"&$H$2&"|品类数量",数据底稿1!$Z:$Z,0)),IF(OR(INDEX(数据底稿1!$Q:$Q,MATCH($D$2&"|"&$H$2&"|品类数量",数据底稿1!$Z:$Z,0))="",G13<INDEX(数据底稿1!$Q:$Q,MATCH($D$2&"|"&$H$2&"|品类数量",数据底稿1!$Z:$Z,0))),INDEX(数据底稿1!$T:$T,MATCH($D$2&"|"&$H$2&"|品类数量",数据底稿1!$Z:$Z,0)),IFERROR(IF(INDEX(数据底稿1!$X:$X,MATCH($D$2&"|"&$H$2&"|品类数量",数据底稿1!$Z:$Z,0))="","",INDEX(数据底稿1!$X:$X,MATCH($D$2&"|"&$H$2&"|品类数量",数据底稿1!$Z:$Z,0))),"")))),""))) -> 品类数量处于同类经销商中的领先水平，品类结构丰富，具备一站式综合服务基础，市场竞争力强。建议分级管理品类，明确利润品与销量品，保持品类活力。
C40: 公司维度 | D40: 坪效 | G40: =IF(OR(C26=FALSE,C26="",ISERROR(C26)),"",IF(OR(G15="",ISERROR(G15)),"",IFERROR(IF(G15<=INDEX(数据底稿1!$I:$I,MATCH($D$2&"|"&$H$2&"|坪效",数据底稿1!$Z:$Z,0)),INDEX(数据底稿1!$L:$L,MATCH($D$2&"|"&$H$2&"|坪效",数据底稿1!$Z:$Z,0)),IF(G15<=INDEX(数据底稿1!$M:$M,MATCH($D$2&"|"&$H$2&"|坪效",数据底稿1!$Z:$Z,0)),INDEX(数据底稿1!$P:$P,MATCH($D$2&"|"&$H$2&"|坪效",数据底稿1!$Z:$Z,0)),IF(OR(INDEX(数据底稿1!$Q:$Q,MATCH($D$2&"|"&$H$2&"|坪效",数据底稿1!$Z:$Z,0))="",G15<=INDEX(数据底稿1!$Q:$Q,MATCH($D$2&"|"&$H$2&"|坪效",数据底稿1!$Z:$Z,0))),INDEX(数据底稿1!$T:$T,MATCH($D$2&"|"&$H$2&"|坪效",数据底稿1!$Z:$Z,0)),IFERROR(IF(INDEX(数据底稿1!$X:$X,MATCH($D$2&"|"&$H$2&"|坪效",数据底稿1!$Z:$Z,0))="","",INDEX(数据底稿1!$X:$X,MATCH($D$2&"|"&$H$2&"|坪效",数据底稿1!$Z:$Z,0))),"")))),""))) -> 坪效处于同类经销商中的领先水平，仓储运营的精细化管理程度高，成本控制好。建议根据毛利润调整产品组合，持续优化。 | P40: 工单转化率 | R40: =IF(U13="","",IF(U13>=INDEX(数据底稿2!C16:K16,1,MATCH($D$2&$H$2,数据底稿2!$C$3:$K$3,0)),数据底稿2!$B$25,IF(U13>=INDEX(数据底稿2!C17:K17,1,MATCH($D$2&$H$2,数据底稿2!$C$3:$K$3,0)),数据底稿2!$C$25,IF(U13>=INDEX(数据底稿2!C18:K18,1,MATCH($D$2&$H$2,数据底稿2!$C$3:$K$3,0)),数据底稿2!$D$25,数据底稿2!$E$25)))) -> 工单转化率已达参考值，在维持转化率的同时关注工单质量 | Y40: =IF(AA37="","",IF(AA37>1.5,[1]数据底稿2!$B$30,IF(AND(AA37>=0.8,AA37<=1.5),[1]数据底稿2!$B$31,IF(AND(AA37>=0.5,AA37<0.8),[1]数据底稿2!$B$32,IF(AA37<0.5,[1]数据底稿2!$B$33,""))))) -> 竞争格局：势均力敌，激烈胶着
D41: 分销会次数 | G41: =IF(OR(C26=FALSE,C26="",ISERROR(C26)),"",IF(OR(G14="",ISERROR(G14)),"",IFERROR(IF(G14<=INDEX(数据底稿1!$I:$I,MATCH($D$2&"|"&$H$2&"|分销会次数",数据底稿1!$Z:$Z,0)),INDEX(数据底稿1!$L:$L,MATCH($D$2&"|"&$H$2&"|分销会次数",数据底稿1!$Z:$Z,0)),IF(G14<=INDEX(数据底稿1!$M:$M,MATCH($D$2&"|"&$H$2&"|分销会次数",数据底稿1!$Z:$Z,0)),INDEX(数据底稿1!$P:$P,MATCH($D$2&"|"&$H$2&"|分销会次数",数据底稿1!$Z:$Z,0)),IF(OR(INDEX(数据底稿1!$Q:$Q,MATCH($D$2&"|"&$H$2&"|分销会次数",数据底稿1!$Z:$Z,0))="",G14<=INDEX(数据底稿1!$Q:$Q,MATCH($D$2&"|"&$H$2&"|分销会次数",数据底稿1!$Z:$Z,0))),INDEX(数据底稿1!$T:$T,MATCH($D$2&"|"&$H$2&"|分销会次数",数据底稿1!$Z:$Z,0)),IFERROR(IF(INDEX(数据底稿1!$X:$X,MATCH($D$2&"|"&$H$2&"|分销会次数",数据底稿1!$Z:$Z,0))="","",INDEX(数据底稿1!$X:$X,MATCH($D$2&"|"&$H$2&"|分销会次数",数据底稿1!$Z:$Z,0))),"")))),""))) -> 分销会场次处于同类经销商中的领先水平，在激活分销网络上具备主动性，渠道维护积极。建议提升会议质量和针对性，增强会议效果，关注分销单店产值。
D42: 专业人士会议次数 | G42: =IF(OR(C26=FALSE,C26="",ISERROR(C26)),"",IF(OR(M14="",ISERROR(M14)),"",IFERROR(IF(M14<=INDEX(数据底稿1!$I:$I,MATCH($D$2&"|"&$H$2&"|专业人士会议次数",数据底稿1!$Z:$Z,0)),INDEX(数据底稿1!$L:$L,MATCH($D$2&"|"&$H$2&"|专业人士会议次数",数据底稿1!$Z:$Z,0)),IF(M14<=INDEX(数据底稿1!$M:$M,MATCH($D$2&"|"&$H$2&"|专业人士会议次数",数据底稿1!$Z:$Z,0)),INDEX(数据底稿1!$P:$P,MATCH($D$2&"|"&$H$2&"|专业人士会议次数",数据底稿1!$Z:$Z,0)),IF(OR(INDEX(数据底稿1!$Q:$Q,MATCH($D$2&"|"&$H$2&"|专业人士会议次数",数据底稿1!$Z:$Z,0))="",M14<=INDEX(数据底稿1!$Q:$Q,MATCH($D$2&"|"&$H$2&"|专业人士会议次数",数据底稿1!$Z:$Z,0))),INDEX(数据底稿1!$T:$T,MATCH($D$2&"|"&$H$2&"|专业人士会议次数",数据底稿1!$Z:$Z,0)),IFERROR(IF(INDEX(数据底稿1!$X:$X,MATCH($D$2&"|"&$H$2&"|专业人士会议次数",数据底稿1!$Z:$Z,0))="","",INDEX(数据底稿1!$X:$X,MATCH($D$2&"|"&$H$2&"|专业人士会议次数",数据底稿1!$Z:$Z,0))),"")))),""))) -> 专业人士会议场次处于同类经销商中的领先水平，会议开展积极，客情维护到位。 建议关注会员人均产出，防范资源浪费。 | P42: 月均工单数量 | R42: =IF(U15="","",IF(U15>=INDEX(数据底稿2!C13:K13,1,MATCH($D$2&$H$2,数据底稿2!$C$3:$K$3,0)),数据底稿2!$B$26,IF(U15>=INDEX(数据底稿2!C14:K14,1,MATCH($D$2&$H$2,数据底稿2!$C$3:$K$3,0)),数据底稿2!$C$26,IF(U15>=INDEX(数据底稿2!C15:K15,1,MATCH($D$2&$H$2,数据底稿2!$C$3:$K$3,0)),数据底稿2!$D$26,数据底稿2!$E$26)))) -> 月均工单数量接近参考值，可进一步优化服务流程
D43: 数字化水平 | G43: =IF(OR(C26=FALSE,C26="",ISERROR(C26)),"",IF(OR(G16="",ISERROR(G16)),"",IFERROR(IF(LOWER(G16)=INDEX(数据底稿1!$I:$I,MATCH($D$2&"|"&$H$2&"|数字化水平",数据底稿1!$Z:$Z,0)),INDEX(数据底稿1!$L:$L,MATCH($D$2&"|"&$H$2&"|数字化水平",数据底稿1!$Z:$Z,0)),IF(LOWER(G16)=INDEX(数据底稿1!$M:$M,MATCH($D$2&"|"&$H$2&"|数字化水平",数据底稿1!$Z:$Z,0)),INDEX(数据底稿1!$P:$P,MATCH($D$2&"|"&$H$2&"|数字化水平",数据底稿1!$Z:$Z,0)),IF(LOWER(G16)=INDEX(数据底稿1!$Q:$Q,MATCH($D$2&"|"&$H$2&"|数字化水平",数据底稿1!$Z:$Z,0)),INDEX(数据底稿1!$T:$T,MATCH($D$2&"|"&$H$2&"|数字化水平",数据底稿1!$Z:$Z,0)),INDEX(数据底稿1!$X:$X,MATCH($D$2&"|"&$H$2&"|数字化水平",数据底稿1!$Z:$Z,0))))),""))) -> 数字化水平处于同类经销商中的领先水平，具备数据驱动决策能力。建议加强数据分析能力建设，用数据指导经营，提升决策效率。

Sheet 数据底稿1
A1: 东方雨虹经销商定量诊断评分 · 数据底稿总表
A2: 使用说明：本表所有指标的区间取值、得分及评语，均可被9张诊断表通过 INDEX/MATCH 公式直接引用。修改本表数据后，诊断表自动同步。区间①~③的"上限值"即为临界值（实际值 < 上限值时适用该区间）；区间④为最高档无上限。
A3: 基本信息 | I3: 区间 ①（实际值 ≤ 区间①上限） | M3: 区间 ②（区间①上限 < 实际值 ≤ 区间②上限） | Q3: 区间 ③（区间②上限 < 实际值 ≤ 区间③上限） | U3: 区间 ④（> 区间③上限，最高档） | Y3: 其他
A4: 城市等级 | B4: 坎级 | C4: 层级 | D4: 子维度 | E4: 指标名称 | F4: 单位 | G4: 权重 | H4: 优秀值 （P70） | I4: 区间① 上限值 | J4: 区间① 系数/得分 | K4: 区间① 计分说明 | L4: 区间① 评语 | M4: 区间② 上限值 | N4: 区间② 系数/得分 | O4: 区间② 计分说明 | P4: 区间② 评语 | Q4: 区间③ 上限值 | R4: 区间③ 系数/得分 | S4: 区间③ 计分说明 | T4: 区间③ 评语 | U4: 区间④ 档位/上限值 | V4: 区间④ 系数/得分 | W4: 区间④ 计分说明 | X4: 区间④ 评语 | Y4: 特殊规则/备注 | Z4: 复合键 （查询用）
A5: 超特 | B5: 300W-1000W | C5: 增长层 | D5: 生意总体 | E5: 合同达成率 | F5: % | G5: 0.1 | H5: 1 | I5: 0.85 | J5: 0.1 | K5: 实际值×0.1（得分随实际值浮动） | L5: 合同达成率低于85%，履约情况需重点改善，严重影响合作稳定性。建议深入复盘分析未达成原因，制定详细改进计划并跟踪落实，确保合同履约执行到位。 | M5: 0.9 | N5: 0.11 | O5: 实际值×0.11 | P5: 合同达成率低于90%，合同履约不足，存在较大改善空间。建议重点关注低达成率品类，分析原因并制定改善计划。 | Q5: 1 | R5: 0.12 | S5: 实际值×0.12 | T5: 全年合同尚未达百，但整体达成情况较好，可能存在部分合同履约不足。建议关注单份合同达成差异，制定针对性改进措施。 | U5: — | V5: 0.144 | W5: 固定封顶，最高14.4分 | X5: 全年合同达百，整体表现优异。建议深入分析单份合同达成差异，防范个别合同达成不力带来的风险。 | Y5: 比例计分，区间上限即为各档临界值 | Z5: 超特|300W-1000W|合同达成率
A6: 超特 | B6: 300W-1000W | C6: 增长层 | D6: 生意总体 | E6: 销售增长率 | F6: % | G6: 0.1 | H6: 0.34 | I6: -1e-17 | J6: 0 | K6: 负增长超过阈值，得0分 | L6: 销售呈现负增长，市场竞争力弱。建议深入分析市场环境和竞争态势，制定针对性营销策略，同时对负增长品类进行专项评估，调整产品结构。 | M6: 0.15 | N6: 0.04 | O6: 固定系数，×100得4分 | P6: 销售增长率处于同类经销商中的中等偏下水平，增长动力有待加强。建议聚焦低增长品类，分析原因并制定提升策略。 | Q6: 0.34 | R6: 0.07 | S6: 固定系数，×100得7分 | T6: 销售增长率处于同类经销商中的中等偏上水平，增长态势良好。建议持续关注品类增长，挖掘潜力品类，提升增长空间。 | U6: — | V6: 0.1 | W6: 固定系数，×100得10分 | X6: 销售增长率处于同类经销商中的领先水平，增长动力强劲。建议关注各品类的增长表现，识别增长引擎品类，制定可持续增长策略，避免短期波动影响长期发展。 | Z6: 超特|300W-1000W|销售增长率
A7: 超特 | B7: 300W-1000W | C7: 增长层 | D7: 分销 | E7: 网点数量 | F7: 个 | G7: 0.058 | H7: 208个 | I7: 36.5 | J7: 30 | K7: 固定30分 | L7: 网点数量处于同类经销商中的末位水平，网点数量严重不足，网络基础薄弱。建议快速制定网点开发计划，加快拓展步伐，优先覆盖重点区域，并建立网点建设进度跟踪机制，确保计划落地。 | M7: 114 | N7: 50 | O7: 固定50分 | P7: 网点数量处于同类经销商中的中等偏下水平，网点数量少，网络覆盖不足。建议制定网点拓展计划，持续推进网点开发，填补空白区域，逐步完善网络布局。 | Q7: 208.3 | R7: 70 | S7: 固定70分 | T7: 网点数量处于同类经销商中的中等偏上水平，网络布局合理。建议在稳定数量的同时提升网点质量，聚焦单店产值和有效门店占比提升，优化网点结构。 | U7: ≥208.3 | V7: 90 | W7: 固定90分（满分） | X7: 网点数量处于同类经销商中的领先水平，网点覆盖广泛，网络基础扎实。建议重点提升单店产值和核心店占比，优化网点质量；同时建立网点分级管理体系，提高网点运营效率。 | Z7: 超特|300W-1000W|网点数量
A8: 超特 | B8: 300W-1000W | C8: 增长层 | D8: 分销 | E8: 核心店数量占比 | F8: % | G8: 0.043 | H8: 0.214 | I8: 0.066 | J8: 30 | K8: 固定30分 | L8: 核心店数量占比处于同类经销商中的末位水平，分销渠道结构极不稳定，核心网点建设严重不足，增长依赖低产值网点。建议分级管理，紧急选拔有潜力门店进行重点培育，打造核心店；学习优秀经销商核心店建设经验，快速复制；建立核心店建设专项考核机制，确保建设效果。 | M8: 0.148 | N8: 50 | O8: 固定50分 | P8: 核心店数量占比处于同类经销商中的中等偏下水平，分销渠道结构不稳定，核心网点建设不足，市场支撑能力弱。建议持续提升网点质量，建立核心店运营标准，培育更多核心店。 | Q8: 0.214 | R8: 70 | S8: 固定70分 | T8: 核心店数量占比处于同类经销商中的中等偏上水平，分销渠道结构稳定，核心店占比相对健康。建议关注核心店达成，建立核心店培育与退出机制，持续提升核心店质量，稳定增长基础。 | U8: ≥21.4% | V8: 90 | W8: 固定90分（满分） | X8: 核心店数量占比处于同类经销商中的领先水平，核心资源集中，分销渠道增长由核心店驱动，市场竞争力强。建议持续关注核心店达成情况，保持增长动力。 | Z8: 超特|300W-1000W|核心店数量占比
A9: 超特 | B9: 300W-1000W | C9: 增长层 | D9: 分销 | E9: 有效门店占比 | F9: % | G9: 0.13 | H9: 0.946 | I9: 0.762 | J9: 30 | K9: 固定30分 | L9: 有效门店占比处于同类经销商中的末位水平，建议安排专人定时进行拜访，完善分销管理流程；对低效门店进行全面评估，制定关停并转计划，集中资源提升保留门店的运营效率。 | M9: 0.918 | N9: 50 | O9: 固定50分 | P9: 有效门店占比处于同类经销商中的中等偏下水平，存在部分“沉睡”门店。建议提升拜访率，激活沉睡门店，避免分销资源浪费；同时对低效门店进行评估，制定整改或淘汰计划。 | Q9: 0.946 | R9: 70 | S9: 固定70分 | T9: 有效门店占比处于同类经销商中的中等偏上水平，网点拜访率及陈列合格率较高，大部分门店运营有效，存在少量低效门店。建议对低效门店进行整改或优化，提升整体有效性。 | U9: ≥94.6% | V9: 90 | W9: 固定90分（满分） | X9: 有效门店占比处于同类经销商中的领先水平，网点拜访率及陈列合格率高，资源利用效率高。建议关注高拜访率门店的产值表现。 | Z9: 超特|300W-1000W|有效门店占比
A10: 超特 | B10: 300W-1000W | C10: 增长层 | D10: 分销 | E10: 人均服务网点数 | F10: 个 | G10: 0.048 | H10: 76.6个 | I10: 33.2 | J10: 30 | K10: 固定30分 | L10: 人均服务网点数处于同类经销商中的末位水平，人员服务密度严重不足，单点人力服务成本高。建议重新设定人员服务网点考核指标，提升人员利用效率。 | M10: 59.3 | N10: 50 | O10: 固定50分 | P10: 人均服务网点数处于同类经销商中的中等偏下水平，单兵服务半径较小，人力资源利用不充分。建议提升网点数量，释放人员效能。 | Q10: 76.6 | R10: 70 | S10: 固定70分 | T10: 人均服务网点数处于同类经销商中的中等偏上水平，管理半径相对合理。建议持续关注人效，优化资源配置。 | U10: ≥76.6 | V10: 90 | W10: 固定90分（满分） | X10: 人均服务网点数处于同类经销商中的领先水平，单兵服务密度极高，人员负荷处于满载状态。建议关注人效，防止服务质量下降。 | Z10: 超特|300W-1000W|人均服务网点数
A11: 超特 | B11: 300W-1000W | C11: 增长层 | D11: 分销 | E11: 自有人员数量 | F11: 个 | G11: 0.024 | H11: 3个 | I11: 1 | J11: 30 | K11: 固定30分 | L11: 自有人员数量处于同类经销商中的末位水平，自有销售人员严重不足，业务开拓与网络维护能力严重受限。建议制定招聘计划，快速补充人员。 | M11: 2 | N11: 50 | O11: 固定50分 | P11: 自有人员数量处于同类经销商中的中等偏下水平，自有人员力量薄弱，覆盖与服务能力不足。建议结合人效和渠道需求，制定人员招聘计划，补充团队力量。 | Q11: 3 | R11: 70 | S11: 固定70分 | T11: 自有人员数量处于同类经销商中的中等偏上水平，具备基础的覆盖保障能力。建议聚焦重点渠道，优化人员配置。 | U11: ≥3 | V11: 90 | W11: 固定90分（满分） | X11: 自有人员数量处于同类经销商中的领先水平，具备深耕市场的团队基础。建议结合渠道发展合理分工，加强人员专业技能培训，提升团队整体素质；建立人员梯队建设计划，保障团队可持续发展。 | Z11: 超特|300W-1000W|自有人员数量
A12: 超特 | B12: 300W-1000W | C12: 增长层 | D12: 分销 | E12: 人效 | F12: 万元/人 | G12: 0.072 | H12: 511.8万/人 | I12: 277.2 | J12: 30 | K12: 固定30分 | L12: 人效处于同类经销商中的末位水平，可能存在经营亏损风险。建议关注如何提升销售额或考虑人员调整，建立明确的绩效考核和激励机制；同时加强人员培训，提升专业技能和工作效率。 | M12: 427.5 | N12: 50 | O12: 固定50分 | P12: 人效处于同类经销商中的中等偏下水平，人均产出不足，无法满足当前生意规模的需求。建议优化工作流程，消除无效劳动；建立绩效考核机制，激发人员工作积极性。 | Q12: 511.8 | R12: 70 | S12: 固定70分 | T12: 人效处于同类经销商中的中等偏上水平，基本满足当前生意规模的需求。建议分析高绩效人员工作方法，在团队内推广，持续优化人员产出，提升盈利能力。 | U12: ≥511.8 | V12: 90 | W12: 固定90分（满分） | X12: 人效处于同类经销商中的领先水平，人力资源利用充分，人均创造价值高。建议关注销售额整体构成，提升净利润水平。 | Z12: 超特|300W-1000W|人效
A13: 超特 | B13: 300W-1000W | C13: 增长层 | D13: 分销 | E13: 乡镇覆盖率 | F13: % | G13: 0.01 | H13: 1 | I13: 0.818 | J13: 30 | K13: 固定30分 | L13: 乡镇覆盖率处于同类经销商中的末位水平，乡镇覆盖极少，下沉市场开拓严重不足。建议制定乡镇市场专项开拓计划，快速布局；简化乡镇市场进入流程，降低开拓难度；建立乡镇市场开拓激励机制，加快开拓进度。 | M13: 0.909 | N13: 50 | O13: 固定50分 | P13: 乡镇覆盖率处于同类经销商中的中等水平，乡镇覆盖良好，布局较为均衡。建议建议制定乡镇开拓计划，筛选空白重点乡镇，逐步扩大乡镇覆盖范围，持续完善乡镇网络。 | Q13: 1 | R13: 70 | S13: 固定70分（本指标最高档，无第四档） | T13: 乡镇覆盖率处于同类经销商中的领先水平，乡镇市场渗透充分。建议关注乡镇网点的产值表现，制定差异化运营方案，优化产品和服务策略。 | U13: — | X13: 乡镇覆盖率处于同类经销商中的领先水平，乡镇市场渗透充分。建议关注乡镇网点的产值表现，制定差异化运营方案，优化产品和服务策略。 | Y13: 仅三档，满分系数70（非90） | Z13: 超特|300W-1000W|乡镇覆盖率
A14: 超特 | B14: 300W-1000W | C14: 增长层 | D14: 分销 | E14: 单店产出 | F14: 万元 | G14: 0.095 | H14: 8.4万 | I14: 2.8 | J14: 30 | K14: 固定30分 | L14: 单店产值处于同类经销商中的末位水平，门店产出普遍偏低。建议全面诊断门店运营问题，制定系统性提升方案；加强门店陈列、促销和服务管理，提升单店产出；建立门店运营督导机制，确保改进措施执行到位。 | M14: 3.7 | N14: 50 | O14: 固定50分 | P14: 单店产值处于同类经销商中的中等偏下水平，门店之间产值差异较大，整体水平偏低，单店运营效率有待提升。建议提升铺货率和拜访频次，激活低效门店。 | Q14: 8.4 | R14: 70 | S14: 固定70分 | T14: 单店产值处于同类经销商中的中等偏上水平，网络基础较好。大部分门店运营正常，少数门店产值偏低，建议聚焦低产值网点，提升铺货率和销售能力。 | U14: ≥8.4 | V14: 90 | W14: 固定90分（满分） | X14: 单店产值处于同类经销商中的领先水平，头部门店表现突出。建议分析头部门店成功经验，复制推广至其他门店，防范因过度依赖少数头部门店而导致的结构性风险。 | Y14: 权重由9.6%修正为9.5%，修正权重合计为100% | Z14: 超特|300W-1000W|单店产出
A15: 超特 | B15: 300W-1000W | C15: 增长层 | D15: 零售 | E15: 会员数量 | F15: 人 | G15: 0.035 | H15: 54人 | I15: 25 | J15: 30 | K15: 固定30分 | L15: 会员数量处于同类经销商中的末位水平，客户数量严重缺失，市场影响力弱。建议制定会员快速发展计划，通过多种渠道吸纳会员；建立会员入门优惠机制，降低会员加入门槛；加强会员服务基础建设，提升会员留存率。 | M15: 38 | N15: 50 | O15: 固定50分 | P15: 会员数量处于同类经销商中的中等偏下水平，客户基础薄弱，尚未形成规模。建议制定会员发展计划，通过工人会和小区推广等形式，扩大会员规模；建立会员服务体系，提升会员满意度和忠诚度。 | Q15: 54 | R15: 70 | S15: 固定70分 | T15: 会员数量处于同类经销商中的中等偏上水平，客户基础较好，具备零售业务基础。建议持续挖掘会员价值，提升转化率。 | U15: ≥54 | V15: 90 | W15: 固定90分（满分） | X15: 会员数量处于同类经销商中的领先水平，市场影响力强，客户资源丰富。建议建立会员分级管理体系，提升高价值会员服务质量；制定会员活跃度提升计划，增强会员粘性。 | Z15: 超特|300W-1000W|会员数量
A16: 超特 | B16: 300W-1000W | C16: 增长层 | D16: 零售 | E16: 会员人均产出 | F16: 万元/人 | G16: 0.015 | H16: 0.59万/人 | I16: 0.222 | J16: 30 | K16: 固定30分 | L16: 会员人均产出处于同类经销商中的末位水平，客户价值低，消费转化困难。建议安排专人负责，勤沟通，多开展培训会、订货会等，制定会员消费激励计划，提高会员消费频次和客单价。 | M16: 0.354 | N16: 50 | O16: 固定50分 | P16: 会员人均产出处于同类经销商中的中等偏下水平，价值转化不足，会员消费频次低。建议多开展培训会、订货会等，建立会员激励机制，提高会员消费积极性。 | Q16: 0.594 | R16: 70 | S16: 固定70分 | T16: 会员人均产出处于同类经销商中的中等偏上水平，会员产出良好，贡献稳定，高价值会员占比有待提升。建议建立会员价值提升机制，持续挖掘会员潜在价值；识别高潜力会员，制定专项服务计划。 | U16: ≥0.594 | V16: 90 | W16: 固定90分（满分） | X16: 会员人均产出处于同类经销商中的领先水平，核心会员粘性强、贡献大。建议与核心会员签订协议，建立长期合作关系，保证稳定性。 | Z16: 超特|300W-1000W|会员人均产出
A17: 超特 | B17: 300W-1000W | C17: 增长层 | D17: 渠道均衡发展 | E17: 渠道数量 | F17: 个 | G17: 0.06 | H17: 4个 | I17: 2 | J17: 20 | K17: 固定20分 | L17: 渠道数量处于同类经销商中的末位水平，业务结构单一，渠道建设严重不足。抗风险能力弱。建议拓展多元化渠道，丰富渠道结构；加强与现有渠道的深度合作，提升渠道效益。 | M17: 3 | N17: 70 | O17: 固定70分 | P17: 渠道数量处于同类经销商中的中等偏下水平，渠道类型少，抗风险能力不足。建议拓展多元化渠道，丰富渠道结构。 | Q17: 4 | R17: 90 | S17: 固定90分 | T17: 渠道数量处于同类经销商中的中等偏上水平，具备一定的抗风险能力。建议结合当地及自身情况，评估是否拓展新渠道；同时评估低效渠道改进空间，优化渠道结构。 | U17: ≧4 | V17: 90 | W17: 固定90分 | X17: 渠道数量处于同类经销商中的领先水平，业务结构健康多元，具备一定盈利能力和发展潜力，抗风险能力强。建议针对低产出渠道进行资源倾斜。 | Y17: 四档，得分跨度较大（20/70/90），区间③和区间④分值均为90分。 | Z17: 超特|300W-1000W|渠道数量
A18: 超特 | B18: 300W-1000W | C18: 增长层 | D18: 品类均衡发展 | E18: 品类数量 | F18: 个 | G18: 0.06 | H18: 4个 | I18: 2 | J18: 20 | K18: 固定20分（品类数<2个） | L18: 品类数量处于同类经销商中的末位水平，品类结构单一，客单价和盈利能力可能陷入瓶颈。建议结合当地市场需求，增加新品，提升品类丰富度和盈利能力。 | M18: 3 | N18: 50 | O18: 固定50分（2≤品类数<3个） | P18: 品类数量处于同类经销商中的中等偏下水平，品类偏少，综合服务能力不足。建议适当增加新品类，丰富产品结构，提升竞争力。 | Q18: 4 | R18: 70 | S18: 固定70分（3≤品类数<4个） | T18: 品类数量处于同类经销商中的中等偏上水平，具备基础的综合服务能力，建议结合产品销售增长情况，评估是否增加新品。 | U18: — | V18: 90 | W18: 固定90分（品类数≥4个） | X18: 品类数量处于同类经销商中的领先水平，品类结构丰富，具备一站式综合服务基础，市场竞争力强。建议分级管理品类，明确利润品与销量品，保持品类活力。 | Y18: 四档，20/50/70/90 | Z18: 超特|300W-1000W|品类数量
A19: 超特 | B19: 300W-1000W | C19: 支撑层 | D19: 会议场次 | E19: 分销会次数 | F19: 次 | G19: 0.015 | H19: 2次 | I19: 1 | J19: 30 | K19: 固定30分 | L19: 分销会场次处于同类经销商中的末位水平，与分销渠道的互动极度缺乏，渠道可能存在失联风险。建议结合门店拜访计划，制定最低会议频次标准，确保基本沟通；同时建立渠道反馈机制，及时了解渠道需求。 | M19: 2 | N19: 50 | O19: 固定50分 | P19: 分销会场次处于同类经销商中的中等偏下水平，渠道沟通不足，难以维系渠道粘性。建议结合销售节奏，制定分销会议计划，增加会议频次。 | Q19: 4 | R19: 70 | S19: 固定70分 | T19: 分销会场次处于同类经销商中的中等偏上水平，渠道粘性较强。建议聚焦核心店和有效门店，提升会议质量。 | U19: ≥4 | V19: 90 | W19: 固定90分（满分） | X19: 分销会场次处于同类经销商中的领先水平，在激活分销网络上具备主动性，渠道维护积极。建议提升会议质量和针对性，增强会议效果，关注分销单店产值。 | Z19: 超特|300W-1000W|分销会次数
A20: 超特 | B20: 300W-1000W | C20: 支撑层 | D20: 会议场次 | E20: 专业人士会议次数 | F20: 次 | G20: 0.035 | H20: 14次 | I20: 5 | J20: 30 | K20: 固定30分 | L20: 专业人士会议场次处于同类经销商中的末位水平，客情维护严重缺失，会员关系薄弱。建议制定专业人士会议计划，定期开展会议，加强会员沟通。 | M20: 8 | N20: 50 | O20: 固定50分 | P20: 专业人士会议场次处于同类经销商中的中等偏下水平，客情维护不足。建议聚焦新会员和低黏度会员，增强互动。 | Q20: 14 | R20: 70 | S20: 固定70分 | T20: 专业人士会议场次处于同类经销商中的中等偏上水平，会议开展良好，会员关系稳定。建议关注会员人均产出，提升低产出会员。 | U20: ≥14 | V20: 90 | W20: 固定90分（14~40次区间满分） | X20: 专业人士会议场次处于同类经销商中的领先水平，会议开展积极，客情维护到位。 建议关注会员人均产出，防范资源浪费。 | Y20: ⚠️ 特殊规则：次数>40次视为数据异常，得分回退至50分，函数中需单独处理 | Z20: 超特|300W-1000W|专业人士会议次数
A21: 超特 | B21: 300W-1000W | C21: 支撑层 | D21: 仓储效率 | E21: 坪效 | F21: 万元/㎡ | G21: 0.03 | H21: 1.25万/平方米 | I21: 0.61 | J21: 30 | K21: 固定30分 | L21: 坪效处于同类经销商中的末位水平，运营成本高，仓储可能已成为高成本负担。建议优化库存管理，调整产品结构；关注坪效指标，持续提升空间利用效率。 | M21: 0.94 | N21: 50 | O21: 固定50分 | P21: 坪效处于同类经销商中的中等偏下水平，仓储运营管理粗放，表明成本控制能力不足。建议调整产品结构，提升仓储效率。 | Q21: 1.25 | R21: 70 | S21: 固定70分 | T21: 坪效处于同类经销商中的中等偏上水平，仓储利用与成本控制良好。建议根据产品周转率优化仓储布局，聚焦低周转率产品，提升空间效率。 | U21: ≥1.25 | V21: 90 | W21: 固定90分（满分） | X21: 坪效处于同类经销商中的领先水平，仓储运营的精细化管理程度高，成本控制好。建议根据毛利润调整产品组合，持续优化。 | Z21: 超特|300W-1000W|坪效
A22: 超特 | B22: 300W-1000W | C22: 支撑层 | D22: 数字化水平 | E22: 数字化水平 | F22: a/b/c/d档 | G22: 0.02 | H22: a档 | I22: d | J22: 0 | K22: 未采用数字化系统，0分 | L22: 数字化水平处于同类经销商中的末位水平，无系统，管理方式原始，数据资产缺失，管理风险高，数据价值被浪费。建议引入基础数字化管理工具，加强人员数字化技能培训，快速推动数字化转型。 | M22: a | N22: 30 | O22: 固定30分（进销存系统） | P22: 数字化水平处于同类经销商中的中等偏下水平，数字化应用停留在记账层面，仍以传统管理方式为主，数据价值可能被浪费。建议引入数字化管理工具，提升管理效率和风险控制能力。 | Q22: b | R22: 70 | S22: 固定70分（数据分析能力） | T22: 数字化水平处于同类经销商中的中等偏上水平，已开始利用数据进行管理。建议建立数据资产体系，提升数据价值。 | U22: c | V22: 90 | W22: 固定90分（c档，指标洞察能力，满分） | X22: 数字化水平处于同类经销商中的领先水平，具备数据驱动决策能力。建议加强数据分析能力建设，用数据指导经营，提升决策效率。 | Y22: 字母档位评级，非数值区间；c最高（指标洞察），d最低 | Z22: 超特|300W-1000W|数字化水平
A23: 超特 | B23: 300W-1000W | C23: 意愿层 | D23: — | E23: 活动参与度 | F23: a/b/c档 | G23: 0.015 | H23: A档 | I23: c | J23: 20 | K23: 固定20分（基本不参与） | L23: 活动参与度处于同类经销商中的末位水平，活动参与积极性低，意愿差。建议与经销商勤沟通，提前沟通活动重要性和利益点；建立活动参与考核和激励机制，提升参与积极性。 | M23: b | N23: 60 | O23: 固定60分（一般参与） | P23: 活动参与度处于同类经销商中的中等偏下水平，参与积极性不足。建议与经销商勤沟通，找出活动参与度低的原因，提升活动参与意愿。 | Q23: a | R23: 90 | S23: 固定90分（积极参与，最高档） | T23: 活动参与度处于同类经销商中的中等偏上水平，参与意愿较强。建议建立活动总结机制，持续优化活动参与质量。 | U23: — | X23: 活动参与度处于同类经销商中的领先水平，活动配合积极，市场响应及时。建议关注活动执行效果，提升活动价值。 | Z23: 超特|300W-1000W|活动参与度
A24: 超特 | B24: 300W-1000W | C24: 意愿层 | D24: — | E24: 经营意愿 | F24: a/b/c档 | G24: 0.02 | H24: a档 | I24: c | J24: 20 | K24: 固定20分（计划放弃） | L24: 经营意愿处于同类经销商中的末位水平，对品牌信息不足，合作稳定性低。建议加强深度沟通，了解顾虑并提供解决方案，逐步建立信心。 | M24: b | N24: 60 | O24: 固定60分（一般配合） | P24: 经营意愿处于同类经销商中的中等偏下水平，经营积极性不足。建议与经销商勤沟通，找出经营意愿低的原因，寻找提升意愿的突破口。 | Q24: a | R24: 90 | S24: 固定90分（强烈经营意愿，最高档） | T24: 经营意愿处于同类经销商中的中等偏上水平，合作意愿较强。建议与经销商勤沟通，关注经营动态，及时响应需求。 | U24: — | X24: 经营意愿处于同类经销商中的领先水平，对于品牌经营信心充足，愿意配合公司积极开展市场活动，并投入人力物力等资源开展经营。建议保持沟通，深化合作关系。 | Z24: 超特|300W-1000W|经营意愿
A25: 超特 | B25: 300W-1000W | C25: 意愿层 | D25: — | E25: 文化认知度 | F25: a/b/c档 | G25: 0.015 | H25: A档 | I25: c | J25: 20 | K25: 固定20分（不认同） | L25: 文化认知度处于同类经销商中的末位水平，文化认知度薄弱，文化认同感低。建议与经销商勤沟通，建立文化沟通机制，及时传递文化理念；通过文化践行活动，促进文化认同。 | M25: b | N25: 60 | O25: 固定60分（了解认同） | P25: 文化认知度处于同类经销商中的中等偏下水平，文化理解不深，认同不足。建议加强企业文化宣导，提升文化认知度。 | Q25: a | R25: 90 | S25: 固定90分（高度认同品牌文化，最高档） | T25: 文化认知度处于同类经销商中的中等偏上水平，文化认同情况良好。建议加强企业文化培训，深化文化理解。 | U25: — | X25: 文化认知度处于同类经销商中的领先水平，对企业文化清晰认知和认同，价值观一致，合作基础稳固，并在日常市场经营活动中积极践行。建议积极传播企业文化，发挥示范作用。 | Z25: 超特|300W-1000W|文化认知度
A26: 超特 | B26: 1000W-2000W | C26: 增长层 | D26: 生意总体 | E26: 合同达成率 | F26: % | G26: 0.1 | H26: 1 | I26: 0.85 | J26: 0.1 | K26: 实际值×0.1（得分随实际值浮动） | L26: 合同达成率低于85%，履约情况需重点改善，严重影响合作稳定性。建议深入复盘分析未达成原因，制定详细改进计划并跟踪落实，确保合同履约执行到位。 | M26: 0.9 | N26: 0.11 | O26: 实际值×0.11 | P26: 合同达成率低于90%，合同履约不足，存在较大改善空间。建议重点关注低达成率品类，分析原因并制定改善计划。 | Q26: 1 | R26: 0.12 | S26: 实际值×0.12 | T26: 全年合同尚未达百，但整体达成情况较好，可能存在部分合同履约不足。建议关注单份合同达成差异，制定针对性改进措施。 | U26: — | V26: 0.144 | W26: 固定封顶，最高14.4分 | X26: 全年合同达百，整体表现优异。建议深入分析单份合同达成差异，防范个别合同达成不力带来的风险。 | Y26: 比例计分，区间上限即为各档临界值 | Z26: 超特|1000W-2000W|合同达成率
A27: 超特 | B27: 1000W-2000W | C27: 增长层 | D27: 生意总体 | E27: 销售增长率 | F27: % | G27: 0.1 | H27: 0.259 | I27: -1e-17 | J27: 0 | K27: 负增长超过阈值，得0分 | L27: 销售呈现负增长，市场竞争力弱。建议深入分析市场环境和竞争态势，制定针对性营销策略，同时对负增长品类进行专项评估，调整产品结构。 | M27: 0.0906 | N27: 0.04 | O27: 固定系数，×100得4分 | P27: 销售增长率处于同类经销商中的中等偏下水平，增长动力有待加强。建议聚焦低增长品类，分析原因并制定提升策略。 | Q27: 0.2592 | R27: 0.07 | S27: 固定系数，×100得7分 | T27: 销售增长率处于同类经销商中的中等偏上水平，增长态势良好。建议持续关注品类增长，挖掘潜力品类，提升增长空间。 | U27: — | V27: 0.1 | W27: 固定系数，×100得10分 | X27: 销售增长率处于同类经销商中的领先水平，增长动力强劲。建议关注各品类的增长表现，识别增长引擎品类，制定可持续增长策略，避免短期波动影响长期发展。 | Z27: 超特|1000W-2000W|销售增长率
A28: 超特 | B28: 1000W-2000W | C28: 增长层 | D28: 分销 | E28: 网点数量 | F28: 个 | G28: 0.0405 | H28: 368个 | I28: 27 | J28: 30 | K28: 固定30分 | L28: 网点数量处于同类经销商中的末位水平，网点数量严重不足，网络基础薄弱。建议快速制定网点开发计划，加快拓展步伐，优先覆盖重点区域，并建立网点建设进度跟踪机制，确保计划落地。 | M28: 212 | N28: 50 | O28: 固定50分 | P28: 网点数量处于同类经销商中的中等偏下水平，网点数量少，网络覆盖不足。建议制定网点拓展计划，持续推进网点开发，填补空白区域，逐步完善网络布局。 | Q28: 368 | R28: 70 | S28: 固定70分 | T28: 网点数量处于同类经销商中的中等偏上水平，网络布局合理。建议在稳定数量的同时提升网点质量，聚焦单店产值和有效门店占比提升，优化网点结构。 | U28: ≥368 | V28: 90 | W28: 固定90分（满分） | X28: 网点数量处于同类经销商中的领先水平，网点覆盖广泛，网络基础扎实。建议重点提升单店产值和核心店占比，优化网点质量；同时建立网点分级管理体系，提高网点运营效率。 | Z28: 超特|1000W-2000W|网点数量
A29: 超特 | B29: 1000W-2000W | C29: 增长层 | D29: 分销 | E29: 核心店数量占比 | F29: % | G29: 0.045 | H29: 0.187 | I29: 0.072 | J29: 30 | K29: 固定30分 | L29: 核心店数量占比处于同类经销商中的末位水平，分销渠道结构极不稳定，核心网点建设严重不足，增长依赖低产值网点。建议分级管理，紧急选拔有潜力门店进行重点培育，打造核心店；学习优秀经销商核心店建设经验，快速复制；建立核心店建设专项考核机制，确保建设效果。 | M29: 0.108 | N29: 50 | O29: 固定50分 | P29: 核心店数量占比处于同类经销商中的中等偏下水平，分销渠道结构不稳定，核心网点建设不足，市场支撑能力弱。建议持续提升网点质量，建立核心店运营标准，培育更多核心店。 | Q29: 0.187 | R29: 70 | S29: 固定70分 | T29: 核心店数量占比处于同类经销商中的中等偏上水平，分销渠道结构稳定，核心店占比相对健康。建议关注核心店达成，建立核心店培育与退出机制，持续提升核心店质量，稳定增长基础。 | U29: ≥18.7% | V29: 90 | W29: 固定90分（满分） | X29: 核心店数量占比处于同类经销商中的领先水平，核心资源集中，分销渠道增长由核心店驱动，市场竞争力强。建议持续关注核心店达成情况，保持增长动力。 | Z29: 超特|1000W-2000W|核心店数量占比
A30: 超特 | B30: 1000W-2000W | C30: 增长层 | D30: 分销 | E30: 有效门店占比 | F30: % | G30: 0.09 | H30: 0.942 | I30: 0.889 | J30: 30 | K30: 固定30分 | L30: 有效门店占比处于同类经销商中的末位水平，建议安排专人定时进行拜访，完善分销管理流程；对低效门店进行全面评估，制定关停并转计划，集中资源提升保留门店的运营效率。 | M30: 0.915 | N30: 50 | O30: 固定50分 | P30: 有效门店占比处于同类经销商中的中等偏下水平，存在部分“沉睡”门店。建议提升拜访率，激活沉睡门店，避免分销资源浪费；同时对低效门店进行评估，制定整改或淘汰计划。 | Q30: 0.942 | R30: 70 | S30: 固定70分 | T30: 有效门店占比处于同类经销商中的中等偏上水平，网点拜访率及陈列合格率较高，大部分门店运营有效，存在少量低效门店。建议对低效门店进行整改或优化，提升整体有效性。 | U30: ≥94.2% | V30: 90 | W30: 固定90分（满分） | X30: 有效门店占比处于同类经销商中的领先水平，网点拜访率及陈列合格率高，资源利用效率高。建议关注高拜访率门店的产值表现。 | Z30: 超特|1000W-2000W|有效门店占比
A31: 超特 | B31: 1000W-2000W | C31: 增长层 | D31: 分销 | E31: 人均服务网点数 | F31: 个 | G31: 0.045 | H31: 85个 | I31: 46 | J31: 30 | K31: 固定30分 | L31: 人均服务网点数处于同类经销商中的末位水平，人员服务密度严重不足，单点人力服务成本高。建议重新设定人员服务网点考核指标，提升人员利用效率。 | M31: 62 | N31: 50 | O31: 固定50分 | P31: 人均服务网点数处于同类经销商中的中等偏下水平，单兵服务半径较小，人力资源利用不充分。建议提升网点数量，释放人员效能。 | Q31: 85 | R31: 70 | S31: 固定70分 | T31: 人均服务网点数处于同类经销商中的中等偏上水平，管理半径相对合理。建议持续关注人效，优化资源配置。 | U31: ≥85 | V31: 90 | W31: 固定90分（满分） | X31: 人均服务网点数处于同类经销商中的领先水平，单兵服务密度极高，人员负荷处于满载状态。建议关注人效，防止服务质量下降。 | Z31: 超特|1000W-2000W|人均服务网点数
A32: 超特 | B32: 1000W-2000W | C32: 增长层 | D32: 分销 | E32: 自有人员数量 | F32: 个 | G32: 0.0225 | H32: 3人 | I32: 1 | J32: 30 | K32: 固定30分 | L32: 自有人员数量处于同类经销商中的末位水平，自有销售人员严重不足，业务开拓与网络维护能力严重受限。建议制定招聘计划，快速补充人员。 | M32: 2 | N32: 50 | O32: 固定50分 | P32: 自有人员数量处于同类经销商中的中等偏下水平，自有人员力量薄弱，覆盖与服务能力不足。建议结合人效和渠道需求，制定人员招聘计划，补充团队力量。 | Q32: 3 | R32: 70 | S32: 固定70分 | T32: 自有人员数量处于同类经销商中的中等偏上水平，具备基础的覆盖保障能力。建议聚焦重点渠道，优化人员配置。 | U32: ≥3 | V32: 90 | W32: 固定90分（满分） | X32: 自有人员数量处于同类经销商中的领先水平，具备深耕市场的团队基础。建议结合渠道发展合理分工，加强人员专业技能培训，提升团队整体素质；建立人员梯队建设计划，保障团队可持续发展。 | Z32: 超特|1000W-2000W|自有人员数量
A33: 超特 | B33: 1000W-2000W | C33: 增长层 | D33: 分销 | E33: 人效 | F33: 万元/人 | G33: 0.09 | H33: 874.8万/人 | I33: 425 | J33: 30 | K33: 固定30分 | L33: 人效处于同类经销商中的末位水平，可能存在经营亏损风险。建议关注如何提升销售额或考虑人员调整，建立明确的绩效考核和激励机制；同时加强人员培训，提升专业技能和工作效率。 | M33: 592 | N33: 50 | O33: 固定50分 | P33: 人效处于同类经销商中的中等偏下水平，人均产出不足，无法满足当前生意规模的需求。建议优化工作流程，消除无效劳动；建立绩效考核机制，激发人员工作积极性。 | Q33: 875 | R33: 70 | S33: 固定70分 | T33: 人效处于同类经销商中的中等偏上水平，基本满足当前生意规模的需求。建议分析高绩效人员工作方法，在团队内推广，持续优化人员产出，提升盈利能力。 | U33: ≥875 | V33: 90 | W33: 固定90分（满分） | X33: 人效处于同类经销商中的领先水平，人力资源利用充分，人均创造价值高。建议关注销售额整体构成，提升净利润水平。 | Z33: 超特|1000W-2000W|人效
A34: 超特 | B34: 1000W-2000W | C34: 增长层 | D34: 分销 | E34: 乡镇覆盖率 | F34: % | G34: 0.0045 | H34: 1 | I34: 0.785 | J34: 30 | K34: 固定30分 | L34: 乡镇覆盖率处于同类经销商中的末位水平，乡镇覆盖极少，下沉市场开拓严重不足。建议制定乡镇市场专项开拓计划，快速布局；简化乡镇市场进入流程，降低开拓难度；建立乡镇市场开拓激励机制，加快开拓进度。 | M34: 0.8925 | N34: 50 | O34: 固定50分 | P34: 乡镇覆盖率处于同类经销商中的中等水平，乡镇覆盖良好，布局较为均衡。建议建议制定乡镇开拓计划，筛选空白重点乡镇，逐步扩大乡镇覆盖范围，持续完善乡镇网络。 | Q34: 1 | R34: 70 | S34: 固定70分（本指标最高档，无第四档） | T34: 乡镇覆盖率处于同类经销商中的领先水平，乡镇市场渗透充分。建议关注乡镇网点的产值表现，制定差异化运营方案，优化产品和服务策略。 | U34: — | X34: 乡镇覆盖率处于同类经销商中的领先水平，乡镇市场渗透充分。建议关注乡镇网点的产值表现，制定差异化运营方案，优化产品和服务策略。 | Y34: 仅三档，满分系数70（非90） | Z34: 超特|1000W-2000W|乡镇覆盖率
A35: 超特 | B35: 1000W-2000W | C35: 增长层 | D35: 分销 | E35: 单店产出 | F35: 万元 | G35: 0.1115 | H35: 8.6万 | I35: 3.6 | J35: 30 | K35: 固定30分 | L35: 单店产值处于同类经销商中的末位水平，门店产出普遍偏低。建议全面诊断门店运营问题，制定系统性提升方案；加强门店陈列、促销和服务管理，提升单店产出；建立门店运营督导机制，确保改进措施执行到位。 | M35: 4.4 | N35: 50 | O35: 固定50分 | P35: 单店产值处于同类经销商中的中等偏下水平，门店之间产值差异较大，整体水平偏低，单店运营效率有待提升。建议提升铺货率和拜访频次，激活低效门店。 | Q35: 8.6 | R35: 70 | S35: 固定70分 | T35: 单店产值处于同类经销商中的中等偏上水平，网络基础较好。大部分门店运营正常，少数门店产值偏低，建议聚焦低产值网点，提升铺货率和销售能力。 | U35: ≥8.6 | V35: 90 | W35: 固定90分（满分） | X35: 单店产值处于同类经销商中的领先水平，头部门店表现突出。建议分析头部门店成功经验，复制推广至其他门店，防范因过度依赖少数头部门店而导致的结构性风险。 | Z35: 超特|1000W-2000W|单店产出
A36: 超特 | B36: 1000W-2000W | C36: 增长层 | D36: 零售 | E36: 会员数量 | F36: 人 | G36: 0.025 | H36: 76人 | I36: 29 | J36: 30 | K36: 固定30分 | L36: 会员数量处于同类经销商中的末位水平，客户数量严重缺失，市场影响力弱。建议制定会员快速发展计划，通过多种渠道吸纳会员；建立会员入门优惠机制，降低会员加入门槛；加强会员服务基础建设，提升会员留存率。 | M36: 51 | N36: 50 | O36: 固定50分 | P36: 会员数量处于同类经销商中的中等偏下水平，客户基础薄弱，尚未形成规模。建议制定会员发展计划，通过工人会和小区推广等形式，扩大会员规模；建立会员服务体系，提升会员满意度和忠诚度。 | Q36: 76 | R36: 70 | S36: 固定70分 | T36: 会员数量处于同类经销商中的中等偏上水平，客户基础较好，具备零售业务基础。建议持续挖掘会员价值，提升转化率。 | U36: ≥76 | V36: 90 | W36: 固定90分（满分） | X36: 会员数量处于同类经销商中的领先水平，市场影响力强，客户资源丰富。建议建立会员分级管理体系，提升高价值会员服务质量；制定会员活跃度提升计划，增强会员粘性。 | Z36: 超特|1000W-2000W|会员数量
A37: 超特 | B37: 1000W-2000W | C37: 增长层 | D37: 零售 | E37: 会员人均产出 | F37: 万元/人 | G37: 0.025 | H37: 0.45万/人 | I37: 0.249 | J37: 30 | K37: 固定30分 | L37: 会员人均产出处于同类经销商中的末位水平，客户价值低，消费转化困难。建议安排专人负责，勤沟通，多开展培训会、订货会等，制定会员消费激励计划，提高会员消费频次和客单价。 | M37: 0.343 | N37: 50 | O37: 固定50分 | P37: 会员人均产出处于同类经销商中的中等偏下水平，价值转化不足，会员消费频次低。建议多开展培训会、订货会等，建立会员激励机制，提高会员消费积极性。 | Q37: 0.451 | R37: 70 | S37: 固定70分 | T37: 会员人均产出处于同类经销商中的中等偏上水平，会员产出良好，贡献稳定，高价值会员占比有待提升。建议建立会员价值提升机制，持续挖掘会员潜在价值；识别高潜力会员，制定专项服务计划。 | U37: ≥0.451 | V37: 90 | W37: 固定90分（满分） | X37: 会员人均产出处于同类经销商中的领先水平，核心会员粘性强、贡献大。建议与核心会员签订协议，建立长期合作关系，保证稳定性。 | Z37: 超特|1000W-2000W|会员人均产出
A38: 超特 | B38: 1000W-2000W | C38: 增长层 | D38: 渠道均衡发展 | E38: 渠道数量 | F38: 个 | G38: 0.06 | H38: 4个 | I38: 2 | J38: 20 | K38: 固定20分 | L38: 渠道数量处于同类经销商中的末位水平，业务结构单一，渠道建设严重不足。抗风险能力弱。建议拓展多元化渠道，丰富渠道结构；加强与现有渠道的深度合作，提升渠道效益。 | M38: 3 | N38: 70 | O38: 固定70分 | P38: 渠道数量处于同类经销商中的中等偏下水平，渠道类型少，抗风险能力不足。建议拓展多元化渠道，丰富渠道结构。 | Q38: 4 | R38: 90 | S38: 固定90分 | T38: 渠道数量处于同类经销商中的中等偏上水平，具备一定的抗风险能力。建议结合当地及自身情况，评估是否拓展新渠道；同时评估低效渠道改进空间，优化渠道结构。 | U38: ≧4 | V38: 90 | W38: 固定90分 | X38: 渠道数量处于同类经销商中的领先水平，业务结构健康多元，具备一定盈利能力和发展潜力，抗风险能力强。建议针对低产出渠道进行资源倾斜。 | Y38: 四档，得分跨度较大（20/70/90），区间③和区间④分值均为90分。 | Z38: 超特|1000W-2000W|渠道数量
A39: 超特 | B39: 1000W-2000W | C39: 增长层 | D39: 品类均衡发展 | E39: 品类数量 | F39: 个 | G39: 0.06 | H39: 4个 | I39: 2 | J39: 20 | K39: 固定20分（品类数<2个） | L39: 品类数量处于同类经销商中的末位水平，品类结构单一，客单价和盈利能力可能陷入瓶颈。建议结合当地市场需求，增加新品，提升品类丰富度和盈利能力。 | M39: 3 | N39: 50 | O39: 固定50分（2≤品类数<3个） | P39: 品类数量处于同类经销商中的中等偏下水平，品类偏少，综合服务能力不足。建议适当增加新品类，丰富产品结构，提升竞争力。 | Q39: 4 | R39: 70 | S39: 固定70分（3≤品类数<4个） | T39: 品类数量处于同类经销商中的中等偏上水平，具备基础的综合服务能力，建议结合产品销售增长情况，评估是否增加新品。 | U39: — | V39: 90 | W39: 固定90分（品类数≥4个） | X39: 品类数量处于同类经销商中的领先水平，品类结构丰富，具备一站式综合服务基础，市场竞争力强。建议分级管理品类，明确利润品与销量品，保持品类活力。 | Y39: 四档，20/50/70/90 | Z39: 超特|1000W-2000W|品类数量
A40: 超特 | B40: 1000W-2000W | C40: 支撑层 | D40: 会议场次 | E40: 分销会次数 | F40: 次 | G40: 0.03 | H40: 7次 | I40: 1 | J40: 30 | K40: 固定30分 | L40: 分销会场次处于同类经销商中的末位水平，与分销渠道的互动极度缺乏，渠道可能存在失联风险。建议结合门店拜访计划，制定最低会议频次标准，确保基本沟通；同时建立渠道反馈机制，及时了解渠道需求。 | M40: 3 | N40: 50 | O40: 固定50分 | P40: 分销会场次处于同类经销商中的中等偏下水平，渠道沟通不足，难以维系渠道粘性。建议结合销售节奏，制定分销会议计划，增加会议频次。 | Q40: 7 | R40: 70 | S40: 固定70分 | T40: 分销会场次处于同类经销商中的中等偏上水平，渠道粘性较强。建议聚焦核心店和有效门店，提升会议质量。 | U40: ≥7 | V40: 90 | W40: 固定90分（满分） | X40: 分销会场次处于同类经销商中的领先水平，在激活分销网络上具备主动性，渠道维护积极。建议提升会议质量和针对性，增强会议效果，关注分销单店产值。 | Z40: 超特|1000W-2000W|分销会次数
A41: 超特 | B41: 1000W-2000W | C41: 支撑层 | D41: 会议场次 | E41: 专业人士会议次数 | F41: 次 | G41: 0.029 | H41: 24次 | I41: 6 | J41: 30 | K41: 固定30分 | L41: 专业人士会议场次处于同类经销商中的末位水平，客情维护严重缺失，会员关系薄弱。建议制定专业人士会议计划，定期开展会议，加强会员沟通。 | M41: 15 | N41: 50 | O41: 固定50分 | P41: 专业人士会议场次处于同类经销商中的中等偏下水平，客情维护不足。建议聚焦新会员和低黏度会员，增强互动。 | Q41: 24 | R41: 70 | S41: 固定70分 | T41: 专业人士会议场次处于同类经销商中的中等偏上水平，会议开展良好，会员关系稳定。建议关注会员人均产出，提升低产出会员。 | U41: ≥24 | V41: 90 | W41: 固定90分（14~40次区间满分） | X41: 专业人士会议场次处于同类经销商中的领先水平，会议开展积极，客情维护到位。 建议关注会员人均产出，防范资源浪费。 | Y41: ⚠️ 特殊规则：次数>40次视为数据异常，得分回退至50分，函数中需单独处理 | Z41: 超特|1000W-2000W|专业人士会议次数
A42: 超特 | B42: 1000W-2000W | C42: 支撑层 | D42: 仓储效率 | E42: 坪效 | F42: 万元/㎡ | G42: 0.039 | H42: 2.16万/平方米 | I42: 1.1 | J42: 30 | K42: 固定30分 | L42: 坪效处于同类经销商中的末位水平，运营成本高，仓储可能已成为高成本负担。建议优化库存管理，调整产品结构；关注坪效指标，持续提升空间利用效率。 | M42: 1.42 | N42: 50 | O42: 固定50分 | P42: 坪效处于同类经销商中的中等偏下水平，仓储运营管理粗放，表明成本控制能力不足。建议调整产品结构，提升仓储效率。 | Q42: 2.16 | R42: 70 | S42: 固定70分 | T42: 坪效处于同类经销商中的中等偏上水平，仓储利用与成本控制良好。建议根据产品周转率优化仓储布局，聚焦低周转率产品，提升空间效率。 | U42: ≥2.16 | V42: 90 | W42: 固定90分（满分） | X42: 坪效处于同类经销商中的领先水平，仓储运营的精细化管理程度高，成本控制好。建议根据毛利润调整产品组合，持续优化。 | Z42: 超特|1000W-2000W|坪效
A43: 超特 | B43: 1000W-2000W | C43: 支撑层 | D43: 数字化水平 | E43: 数字化水平 | F43: a/b/c/d档 | G43: 0.033 | H43: b档 | I43: d | J43: 0 | K43: 未采用数字化系统，0分 | L43: 数字化水平处于同类经销商中的末位水平，无系统，管理方式原始，数据资产缺失，管理风险高，数据价值被浪费。建议引入基础数字化管理工具，加强人员数字化技能培训，快速推动数字化转型。 | M43: a | N43: 30 | O43: 固定30分（进销存系统） | P43: 数字化水平处于同类经销商中的中等偏下水平，数字化应用停留在记账层面，仍以传统管理方式为主，数据价值可能被浪费。建议引入数字化管理工具，提升管理效率和风险控制能力。 | Q43: b | R43: 70 | S43: 固定70分（数据分析能力） | T43: 数字化水平处于同类经销商中的中等偏上水平，已开始利用数据进行管理。建议建立数据资产体系，提升数据价值。 | U43: c | V43: 90 | W43: 固定90分（a档，指标洞察能力，满分） | X43: 数字化水平处于同类经销商中的领先水平，具备数据驱动决策能力。建议加强数据分析能力建设，用数据指导经营，提升决策效率。 | Y43: 字母档位评级，非数值区间；c最高（指标洞察），d最低 | Z43: 超特|1000W-2000W|数字化水平
A44: 超特 | B44: 1000W-2000W | C44: 意愿层 | D44: — | E44: 活动参与度 | F44: a/b/c档 | G44: 0.015 | H44: A档 | I44: c | J44: 20 | K44: 固定20分（基本不参与） | L44: 活动参与度处于同类经销商中的末位水平，活动参与积极性低，意愿差。建议与经销商勤沟通，提前沟通活动重要性和利益点；建立活动参与考核和激励机制，提升参与积极性。 | M44: b | N44: 60 | O44: 固定60分（一般参与） | P44: 活动参与度处于同类经销商中的中等偏下水平，参与积极性不足。建议与经销商勤沟通，找出活动参与度低的原因，提升活动参与意愿。 | Q44: a | R44: 90 | S44: 固定90分（积极参与，最高档） | T44: 活动参与度处于同类经销商中的中等偏上水平，参与意愿较强。建议建立活动总结机制，持续优化活动参与质量。 | U44: — | X44: 活动参与度处于同类经销商中的领先水平，活动配合积极，市场响应及时。建议关注活动执行效果，提升活动价值。 | Z44: 超特|1000W-2000W|活动参与度
A45: 超特 | B45: 1000W-2000W | C45: 意愿层 | D45: — | E45: 经营意愿 | F45: a/b/c档 | G45: 0.02 | H45: a档 | I45: c | J45: 20 | K45: 固定20分（计划放弃） | L45: 经营意愿处于同类经销商中的末位水平，对品牌信息不足，合作稳定性低。建议加强深度沟通，了解顾虑并提供解决方案，逐步建立信心。 | M45: b | N45: 60 | O45: 固定60分（一般配合） | P45: 经营意愿处于同类经销商中的中等偏下水平，经营积极性不足。建议与经销商勤沟通，找出经营意愿低的原因，寻找提升意愿的突破口。 | Q45: a | R45: 90 | S45: 固定90分（强烈经营意愿，最高档） | T45: 经营意愿处于同类经销商中的中等偏上水平，合作意愿较强。建议与经销商勤沟通，关注经营动态，及时响应需求。 | U45: — | X45: 经营意愿处于同类经销商中的领先水平，对于品牌经营信心充足，愿意配合公司积极开展市场活动，并投入人力物力等资源开展经营。建议保持沟通，深化合作关系。 | Z45: 超特|1000W-2000W|经营意愿
A46: 超特 | B46: 1000W-2000W | C46: 意愿层 | D46: — | E46: 文化认知度 | F46: a/b/c档 | G46: 0.015 | H46: A档 | I46: c | J46: 20 | K46: 固定20分（不认同） | L46: 文化认知度处于同类经销商中的末位水平，文化认知度薄弱，文化认同感低。建议与经销商勤沟通，建立文化沟通机制，及时传递文化理念；通过文化践行活动，促进文化认同。 | M46: b | N46: 60 | O46: 固定60分（了解认同） | P46: 文化认知度处于同类经销商中的中等偏下水平，文化理解不深，认同不足。建议加强企业文化宣导，提升文化认知度。 | Q46: a | R46: 90 | S46: 固定90分（高度认同品牌文化，最高档） | T46: 文化认知度处于同类经销商中的中等偏上水平，文化认同情况良好。建议加强企业文化培训，深化文化理解。 | U46: — | X46: 文化认知度处于同类经销商中的领先水平，对企业文化清晰认知和认同，价值观一致，合作基础稳固，并在日常市场经营活动中积极践行。建议积极传播企业文化，发挥示范作用。 | Z46: 超特|1000W-2000W|文化认知度
A47: 超特 | B47: 2000W+ | C47: 增长层 | D47: 生意总体 | E47: 合同达成率 | F47: % | G47: 0.1 | H47: 1 | I47: 0.85 | J47: 0.1 | K47: 实际值×0.1（得分随实际值浮动） | L47: 合同达成率低于85%，履约情况需重点改善，严重影响合作稳定性。建议深入复盘分析未达成原因，制定详细改进计划并跟踪落实，确保合同履约执行到位。 | M47: 0.9 | N47: 0.11 | O47: 实际值×0.11 | P47: 合同达成率低于90%，合同履约不足，存在较大改善空间。建议重点关注低达成率品类，分析原因并制定改善计划。 | Q47: 1 | R47: 0.12 | S47: 实际值×0.12 | T47: 全年合同尚未达百，但整体达成情况较好，可能存在部分合同履约不足。建议关注单份合同达成差异，制定针对性改进措施。 | U47: — | V47: 0.144 | W47: 固定封顶，最高14.4分 | X47: 全年合同达百，整体表现优异。建议深入分析单份合同达成差异，防范个别合同达成不力带来的风险。 | Y47: 比例计分，区间上限即为各档临界值 | Z47: 超特|2000W+|合同达成率
A48: 超特 | B48: 2000W+ | C48: 增长层 | D48: 生意总体 | E48: 销售增长率 | F48: % | G48: 0.1 | H48: 0.1359 | I48: -1e-17 | J48: 0 | K48: 负增长超过阈值，得0分 | L48: 销售呈现负增长，市场竞争力弱。建议深入分析市场环境和竞争态势，制定针对性营销策略，同时对负增长品类进行专项评估，调整产品结构。 | M48: 0.0532 | N48: 0.04 | O48: 固定系数，×100得4分 | P48: 销售增长率处于同类经销商中的中等偏下水平，增长动力有待加强。建议聚焦低增长品类，分析原因并制定提升策略。 | Q48: 0.1359 | R48: 0.07 | S48: 固定系数，×100得7分 | T48: 销售增长率处于同类经销商中的中等偏上水平，增长态势良好。建议持续关注品类增长，挖掘潜力品类，提升增长空间。 | U48: — | V48: 0.1 | W48: 固定系数，×100得10分 | X48: 销售增长率处于同类经销商中的领先水平，增长动力强劲。建议关注各品类的增长表现，识别增长引擎品类，制定可持续增长策略，避免短期波动影响长期发展。 | Z48: 超特|2000W+|销售增长率
A49: 超特 | B49: 2000W+ | C49: 增长层 | D49: 分销 | E49: 网点数量 | F49: 个 | G49: 0.058 | H49: 658个 | I49: 155 | J49: 30 | K49: 固定30分 | L49: 网点数量处于同类经销商中的末位水平，网点数量严重不足，网络基础薄弱。建议快速制定网点开发计划，加快拓展步伐，优先覆盖重点区域，并建立网点建设进度跟踪机制，确保计划落地。 | M49: 439 | N49: 50 | O49: 固定50分 | P49: 网点数量处于同类经销商中的中等偏下水平，网点数量少，网络覆盖不足。建议制定网点拓展计划，持续推进网点开发，填补空白区域，逐步完善网络布局。 | Q49: 660 | R49: 70 | S49: 固定70分 | T49: 网点数量处于同类经销商中的中等偏上水平，网络布局合理。建议在稳定数量的同时提升网点质量，聚焦单店产值和有效门店占比提升，优化网点结构。 | U49: ≥660 | V49: 90 | W49: 固定90分（满分） | X49: 网点数量处于同类经销商中的领先水平，网点覆盖广泛，网络基础扎实。建议重点提升单店产值和核心店占比，优化网点质量；同时建立网点分级管理体系，提高网点运营效率。 | Z49: 超特|2000W+|网点数量
A50: 超特 | B50: 2000W+ | C50: 增长层 | D50: 分销 | E50: 核心店数量占比 | F50: % | G50: 0.043 | H50: 0.131 | I50: 0.05 | J50: 30 | K50: 固定30分 | L50: 核心店数量占比处于同类经销商中的末位水平，分销渠道结构极不稳定，核心网点建设严重不足，增长依赖低产值网点。建议分级管理，紧急选拔有潜力门店进行重点培育，打造核心店；学习优秀经销商核心店建设经验，快速复制；建立核心店建设专项考核机制，确保建设效果。 | M50: 0.077 | N50: 50 | O50: 固定50分 | P50: 核心店数量占比处于同类经销商中的中等偏下水平，分销渠道结构不稳定，核心网点建设不足，市场支撑能力弱。建议持续提升网点质量，建立核心店运营标准，培育更多核心店。 | Q50: 0.131 | R50: 70 | S50: 固定70分 | T50: 核心店数量占比处于同类经销商中的中等偏上水平，分销渠道结构稳定，核心店占比相对健康。建议关注核心店达成，建立核心店培育与退出机制，持续提升核心店质量，稳定增长基础。 | U50: ≥13.1% | V50: 90 | W50: 固定90分（满分） | X50: 核心店数量占比处于同类经销商中的领先水平，核心资源集中，分销渠道增长由核心店驱动，市场竞争力强。建议持续关注核心店达成情况，保持增长动力。 | Z50: 超特|2000W+|核心店数量占比
A51: 超特 | B51: 2000W+ | C51: 增长层 | D51: 分销 | E51: 有效门店占比 | F51: % | G51: 0.13 | H51: 0.941 | I51: 0.855 | J51: 30 | K51: 固定30分 | L51: 有效门店占比处于同类经销商中的末位水平，建议安排专人定时进行拜访，完善分销管理流程；对低效门店进行全面评估，制定关停并转计划，集中资源提升保留门店的运营效率。 | M51: 0.915 | N51: 50 | O51: 固定50分 | P51: 有效门店占比处于同类经销商中的中等偏下水平，存在部分“沉睡”门店。建议提升拜访率，激活沉睡门店，避免分销资源浪费；同时对低效门店进行评估，制定整改或淘汰计划。 | Q51: 0.941 | R51: 70 | S51: 固定70分 | T51: 有效门店占比处于同类经销商中的中等偏上水平，网点拜访率及陈列合格率较高，大部分门店运营有效，存在少量低效门店。建议对低效门店进行整改或优化，提升整体有效性。 | U51: ≥94.1% | V51: 90 | W51: 固定90分（满分） | X51: 有效门店占比处于同类经销商中的领先水平，网点拜访率及陈列合格率高，资源利用效率高。建议关注高拜访率门店的产值表现。 | Z51: 超特|2000W+|有效门店占比
A52: 超特 | B52: 2000W+ | C52: 增长层 | D52: 分销 | E52: 人均服务网点数 | F52: 个 | G52: 0.048 | H52: 108个 | I52: 59.3 | J52: 30 | K52: 固定30分 | L52: 人均服务网点数处于同类经销商中的末位水平，人员服务密度严重不足，单点人力服务成本高。建议重新设定人员服务网点考核指标，提升人员利用效率。 | M52: 84.1 | N52: 50 | O52: 固定50分 | P52: 人均服务网点数处于同类经销商中的中等偏下水平，单兵服务半径较小，人力资源利用不充分。建议提升网点数量，释放人员效能。 | Q52: 108 | R52: 70 | S52: 固定70分 | T52: 人均服务网点数处于同类经销商中的中等偏上水平，管理半径相对合理。建议持续关注人效，优化资源配置。 | U52: ≥108 | V52: 90 | W52: 固定90分（满分） | X52: 人均服务网点数处于同类经销商中的领先水平，单兵服务密度极高，人员负荷处于满载状态。建议关注人效，防止服务质量下降。 | Z52: 超特|2000W+|人均服务网点数
A53: 超特 | B53: 2000W+ | C53: 增长层 | D53: 分销 | E53: 自有人员数量 | F53: 个 | G53: 0.024 | H53: 4人 | I53: 2 | J53: 30 | K53: 固定30分 | L53: 自有人员数量处于同类经销商中的末位水平，自有销售人员严重不足，业务开拓与网络维护能力严重受限。建议制定招聘计划，快速补充人员。 | M53: 3 | N53: 50 | O53: 固定50分 | P53: 自有人员数量处于同类经销商中的中等偏下水平，自有人员力量薄弱，覆盖与服务能力不足。建议结合人效和渠道需求，制定人员招聘计划，补充团队力量。 | Q53: 4 | R53: 70 | S53: 固定70分 | T53: 自有人员数量处于同类经销商中的中等偏上水平，具备基础的覆盖保障能力。建议聚焦重点渠道，优化人员配置。 | U53: ≥4 | V53: 90 | W53: 固定90分（满分） | X53: 自有人员数量处于同类经销商中的领先水平，具备深耕市场的团队基础。建议结合渠道发展合理分工，加强人员专业技能培训，提升团队整体素质；建立人员梯队建设计划，保障团队可持续发展。 | Z53: 超特|2000W+|自有人员数量
A54: 超特 | B54: 2000W+ | C54: 增长层 | D54: 分销 | E54: 人效 | F54: 万元/人 | G54: 0.072 | H54: 857.1万/人 | I54: 610.2 | J54: 30 | K54: 固定30分 | L54: 人效处于同类经销商中的末位水平，可能存在经营亏损风险。建议关注如何提升销售额或考虑人员调整，建立明确的绩效考核和激励机制；同时加强人员培训，提升专业技能和工作效率。 | M54: 712.4 | N54: 50 | O54: 固定50分 | P54: 人效处于同类经销商中的中等偏下水平，人均产出不足，无法满足当前生意规模的需求。建议优化工作流程，消除无效劳动；建立绩效考核机制，激发人员工作积极性。 | Q54: 857.1 | R54: 70 | S54: 固定70分 | T54: 人效处于同类经销商中的中等偏上水平，基本满足当前生意规模的需求。建议分析高绩效人员工作方法，在团队内推广，持续优化人员产出，提升盈利能力。 | U54: ≥857.1 | V54: 90 | W54: 固定90分（满分） | X54: 人效处于同类经销商中的领先水平，人力资源利用充分，人均创造价值高。建议关注销售额整体构成，提升净利润水平。 | Z54: 超特|2000W+|人效
A55: 超特 | B55: 2000W+ | C55: 增长层 | D55: 分销 | E55: 乡镇覆盖率 | F55: % | G55: 0.01 | H55: 1 | I55: 0.74 | J55: 30 | K55: 固定30分 | L55: 乡镇覆盖率处于同类经销商中的末位水平，乡镇覆盖极少，下沉市场开拓严重不足。建议制定乡镇市场专项开拓计划，快速布局；简化乡镇市场进入流程，降低开拓难度；建立乡镇市场开拓激励机制，加快开拓进度。 | M55: 0.87 | N55: 50 | O55: 固定50分 | P55: 乡镇覆盖率处于同类经销商中的中等水平，乡镇覆盖良好，布局较为均衡。建议建议制定乡镇开拓计划，筛选空白重点乡镇，逐步扩大乡镇覆盖范围，持续完善乡镇网络。 | Q55: 1 | R55: 70 | S55: 固定70分（本指标最高档，无第四档） | T55: 乡镇覆盖率处于同类经销商中的领先水平，乡镇市场渗透充分。建议关注乡镇网点的产值表现，制定差异化运营方案，优化产品和服务策略。 | U55: — | X55: 乡镇覆盖率处于同类经销商中的领先水平，乡镇市场渗透充分。建议关注乡镇网点的产值表现，制定差异化运营方案，优化产品和服务策略。 | Y55: 仅三档，满分系数70（非90） | Z55: 超特|2000W+|乡镇覆盖率
A56: 超特 | B56: 2000W+ | C56: 增长层 | D56: 分销 | E56: 单店产出 | F56: 万元 | G56: 0.095 | H56: 8.7万 | I56: 3.4 | J56: 30 | K56: 固定30分 | L56: 单店产值处于同类经销商中的末位水平，门店产出普遍偏低。建议全面诊断门店运营问题，制定系统性提升方案；加强门店陈列、促销和服务管理，提升单店产出；建立门店运营督导机制，确保改进措施执行到位。 | M56: 5.3 | N56: 50 | O56: 固定50分 | P56: 单店产值处于同类经销商中的中等偏下水平，门店之间产值差异较大，整体水平偏低，单店运营效率有待提升。建议提升铺货率和拜访频次，激活低效门店。 | Q56: 8.7 | R56: 70 | S56: 固定70分 | T56: 单店产值处于同类经销商中的中等偏上水平，网络基础较好。大部分门店运营正常，少数门店产值偏低，建议聚焦低产值网点，提升铺货率和销售能力。 | U56: ≥8.7 | V56: 90 | W56: 固定90分（满分） | X56: 单店产值处于同类经销商中的领先水平，头部门店表现突出。建议分析头部门店成功经验，复制推广至其他门店，防范因过度依赖少数头部门店而导致的结构性风险。 | Z56: 超特|2000W+|单店产出
A57: 超特 | B57: 2000W+ | C57: 增长层 | D57: 零售 | E57: 会员数量 | F57: 人 | G57: 0.035 | H57: 32人 | I57: 12 | J57: 30 | K57: 固定30分 | L57: 会员数量处于同类经销商中的末位水平，客户数量严重缺失，市场影响力弱。建议制定会员快速发展计划，通过多种渠道吸纳会员；建立会员入门优惠机制，降低会员加入门槛；加强会员服务基础建设，提升会员留存率。 | M57: 20 | N57: 50 | O57: 固定50分 | P57: 会员数量处于同类经销商中的中等偏下水平，客户基础薄弱，尚未形成规模。建议制定会员发展计划，通过工人会和小区推广等形式，扩大会员规模；建立会员服务体系，提升会员满意度和忠诚度。 | Q57: 32 | R57: 70 | S57: 固定70分 | T57: 会员数量处于同类经销商中的中等偏上水平，客户基础较好，具备零售业务基础。建议持续挖掘会员价值，提升转化率。 | U57: ≥32 | V57: 90 | W57: 固定90分（满分） | X57: 会员数量处于同类经销商中的领先水平，市场影响力强，客户资源丰富。建议建立会员分级管理体系，提升高价值会员服务质量；制定会员活跃度提升计划，增强会员粘性。 | Z57: 超特|2000W+|会员数量
A58: 超特 | B58: 2000W+ | C58: 增长层 | D58: 零售 | E58: 会员人均产出 | F58: 万元/人 | G58: 0.015 | H58: 0.98万/人 | I58: 0.292 | J58: 30 | K58: 固定30分 | L58: 会员人均产出处于同类经销商中的末位水平，客户价值低，消费转化困难。建议安排专人负责，勤沟通，多开展培训会、订货会等，制定会员消费激励计划，提高会员消费频次和客单价。 | M58: 0.486 | N58: 50 | O58: 固定50分 | P58: 会员人均产出处于同类经销商中的中等偏下水平，价值转化不足，会员消费频次低。建议多开展培训会、订货会等，建立会员激励机制，提高会员消费积极性。 | Q58: 0.98 | R58: 70 | S58: 固定70分 | T58: 会员人均产出处于同类经销商中的中等偏上水平，会员产出良好，贡献稳定，高价值会员占比有待提升。建议建立会员价值提升机制，持续挖掘会员潜在价值；识别高潜力会员，制定专项服务计划。 | U58: ≥0.98 | V58: 90 | W58: 固定90分（满分） | X58: 会员人均产出处于同类经销商中的领先水平，核心会员粘性强、贡献大。建议与核心会员签订协议，建立长期合作关系，保证稳定性。 | Z58: 超特|2000W+|会员人均产出
A59: 超特 | B59: 2000W+ | C59: 增长层 | D59: 渠道均衡发展 | E59: 渠道数量 | F59: 个 | G59: 0.06 | H59: 4个 | I59: 2 | J59: 20 | K59: 固定20分 | L59: 渠道数量处于同类经销商中的末位水平，业务结构单一，渠道建设严重不足。抗风险能力弱。建议拓展多元化渠道，丰富渠道结构；加强与现有渠道的深度合作，提升渠道效益。 | M59: 3 | N59: 70 | O59: 固定70分 | P59: 渠道数量处于同类经销商中的中等偏下水平，渠道类型少，抗风险能力不足。建议拓展多元化渠道，丰富渠道结构。 | Q59: 4 | R59: 90 | S59: 固定90分 | T59: 渠道数量处于同类经销商中的中等偏上水平，具备一定的抗风险能力。建议结合当地及自身情况，评估是否拓展新渠道；同时评估低效渠道改进空间，优化渠道结构。 | U59: ≧4 | V59: 90 | W59: 固定90分 | X59: 渠道数量处于同类经销商中的领先水平，业务结构健康多元，具备一定盈利能力和发展潜力，抗风险能力强。建议针对低产出渠道进行资源倾斜。 | Y59: 四档，得分跨度较大（20/70/90），区间③和区间④分值均为90分。 | Z59: 超特|2000W+|渠道数量
A60: 超特 | B60: 2000W+ | C60: 增长层 | D60: 品类均衡发展 | E60: 品类数量 | F60: 个 | G60: 0.06 | H60: 5个 | I60: 3 | J60: 20 | K60: 固定20分（品类数<3个） | L60: 品类数量处于同类经销商中的末位水平，品类结构单一，客单价和盈利能力可能陷入瓶颈。建议结合当地市场需求，增加新品，提升品类丰富度和盈利能力。 | M60: 4 | N60: 50 | O60: 固定50分（3≤品类数<4个） | P60: 品类数量处于同类经销商中的中等偏下水平，品类偏少，综合服务能力不足。建议适当增加新品类，丰富产品结构，提升竞争力。 | Q60: 5 | R60: 70 | S60: 固定70分（4≤品类数<5个） | T60: 品类数量处于同类经销商中的中等偏上水平，具备基础的综合服务能力，建议结合产品销售增长情况，评估是否增加新品。 | U60: — | V60: 90 | W60: 固定90分（品类数≥5个） | X60: 品类数量处于同类经销商中的领先水平，品类结构丰富，具备一站式综合服务基础，市场竞争力强。建议分级管理品类，明确利润品与销量品，保持品类活力。 | Y60: 四档，20/50/70/90 | Z60: 超特|2000W+|品类数量
A61: 超特 | B61: 2000W+ | C61: 支撑层 | D61: 会议场次 | E61: 分销会次数 | F61: 次 | G61: 0.015 | H61: 6次 | I61: 1 | J61: 30 | K61: 固定30分 | L61: 分销会场次处于同类经销商中的末位水平，与分销渠道的互动极度缺乏，渠道可能存在失联风险。建议结合门店拜访计划，制定最低会议频次标准，确保基本沟通；同时建立渠道反馈机制，及时了解渠道需求。 | M61: 3 | N61: 50 | O61: 固定50分 | P61: 分销会场次处于同类经销商中的中等偏下水平，渠道沟通不足，难以维系渠道粘性。建议结合销售节奏，制定分销会议计划，增加会议频次。 | Q61: 6 | R61: 70 | S61: 固定70分 | T61: 分销会场次处于同类经销商中的中等偏上水平，渠道粘性较强。建议聚焦核心店和有效门店，提升会议质量。 | U61: ≥6 | V61: 90 | W61: 固定90分（满分） | X61: 分销会场次处于同类经销商中的领先水平，在激活分销网络上具备主动性，渠道维护积极。建议提升会议质量和针对性，增强会议效果，关注分销单店产值。 | Z61: 超特|2000W+|分销会次数
A62: 超特 | B62: 2000W+ | C62: 支撑层 | D62: 会议场次 | E62: 专业人士会议次数 | F62: 次 | G62: 0.035 | H62: 30次 | I62: 13 | J62: 30 | K62: 固定30分 | L62: 专业人士会议场次处于同类经销商中的末位水平，客情维护严重缺失，会员关系薄弱。建议制定专业人士会议计划，定期开展会议，加强会员沟通。 | M62: 20 | N62: 50 | O62: 固定50分 | P62: 专业人士会议场次处于同类经销商中的中等偏下水平，客情维护不足。建议聚焦新会员和低黏度会员，增强互动。 | Q62: 30 | R62: 70 | S62: 固定70分 | T62: 专业人士会议场次处于同类经销商中的中等偏上水平，会议开展良好，会员关系稳定。建议关注会员人均产出，提升低产出会员。 | U62: ≥30 | V62: 90 | W62: 固定90分（14~40次区间满分） | X62: 专业人士会议场次处于同类经销商中的领先水平，会议开展积极，客情维护到位。 建议关注会员人均产出，防范资源浪费。 | Y62: ⚠️ 特殊规则：次数>40次视为数据异常，得分回退至50分，函数中需单独处理 | Z62: 超特|2000W+|专业人士会议次数
A63: 超特 | B63: 2000W+ | C63: 支撑层 | D63: 仓储效率 | E63: 坪效 | F63: 万元/㎡ | G63: 0.03 | H63: 2.01万/平方米 | I63: 1.06 | J63: 30 | K63: 固定30分 | L63: 坪效处于同类经销商中的末位水平，运营成本高，仓储可能已成为高成本负担。建议优化库存管理，调整产品结构；关注坪效指标，持续提升空间利用效率。 | M63: 1.65 | N63: 50 | O63: 固定50分 | P63: 坪效处于同类经销商中的中等偏下水平，仓储运营管理粗放，表明成本控制能力不足。建议调整产品结构，提升仓储效率。 | Q63: 2.01 | R63: 70 | S63: 固定70分 | T63: 坪效处于同类经销商中的中等偏上水平，仓储利用与成本控制良好。建议根据产品周转率优化仓储布局，聚焦低周转率产品，提升空间效率。 | U63: ≥2.01 | V63: 90 | W63: 固定90分（满分） | X63: 坪效处于同类经销商中的领先水平，仓储运营的精细化管理程度高，成本控制好。建议根据毛利润调整产品组合，持续优化。 | Z63: 超特|2000W+|坪效
A64: 超特 | B64: 2000W+ | C64: 支撑层 | D64: 数字化水平 | E64: 数字化水平 | F64: a/b/c/d档 | G64: 0.02 | H64: c档 | I64: d | J64: 0 | K64: 未采用数字化系统，0分 | L64: 数字化水平处于同类经销商中的末位水平，无系统，管理方式原始，数据资产缺失，管理风险高，数据价值被浪费。建议引入基础数字化管理工具，加强人员数字化技能培训，快速推动数字化转型。 | M64: a | N64: 30 | O64: 固定30分（进销存系统） | P64: 数字化水平处于同类经销商中的中等偏下水平，数字化应用停留在记账层面，仍以传统管理方式为主，数据价值可能被浪费。建议引入数字化管理工具，提升管理效率和风险控制能力。 | Q64: b | R64: 70 | S64: 固定70分（数据分析能力） | T64: 数字化水平处于同类经销商中的中等偏上水平，已开始利用数据进行管理。建议建立数据资产体系，提升数据价值。 | U64: c | V64: 90 | W64: 固定90分（a档，指标洞察能力，满分） | X64: 数字化水平处于同类经销商中的领先水平，具备数据驱动决策能力。建议加强数据分析能力建设，用数据指导经营，提升决策效率。 | Y64: 字母档位评级，非数值区间；c最高（指标洞察），d最低 | Z64: 超特|2000W+|数字化水平
A65: 超特 | B65: 2000W+ | C65: 意愿层 | D65: — | E65: 活动参与度 | F65: a/b/c档 | G65: 0.015 | H65: A档 | I65: c | J65: 20 | K65: 固定20分（基本不参与） | L65: 活动参与度处于同类经销商中的末位水平，活动参与积极性低，意愿差。建议与经销商勤沟通，提前沟通活动重要性和利益点；建立活动参与考核和激励机制，提升参与积极性。 | M65: b | N65: 60 | O65: 固定60分（一般参与） | P65: 活动参与度处于同类经销商中的中等偏下水平，参与积极性不足。建议与经销商勤沟通，找出活动参与度低的原因，提升活动参与意愿。 | Q65: a | R65: 90 | S65: 固定90分（积极参与，最高档） | T65: 活动参与度处于同类经销商中的中等偏上水平，参与意愿较强。建议建立活动总结机制，持续优化活动参与质量。 | U65: — | X65: 活动参与度处于同类经销商中的领先水平，活动配合积极，市场响应及时。建议关注活动执行效果，提升活动价值。 | Z65: 超特|2000W+|活动参与度
A66: 超特 | B66: 2000W+ | C66: 意愿层 | D66: — | E66: 经营意愿 | F66: a/b/c档 | G66: 0.02 | H66: a档 | I66: c | J66: 20 | K66: 固定20分（计划放弃） | L66: 经营意愿处于同类经销商中的末位水平，对品牌信息不足，合作稳定性低。建议加强深度沟通，了解顾虑并提供解决方案，逐步建立信心。 | M66: b | N66: 60 | O66: 固定60分（一般配合） | P66: 经营意愿处于同类经销商中的中等偏下水平，经营积极性不足。建议与经销商勤沟通，找出经营意愿低的原因，寻找提升意愿的突破口。 | Q66: a | R66: 90 | S66: 固定90分（强烈经营意愿，最高档） | T66: 经营意愿处于同类经销商中的中等偏上水平，合作意愿较强。建议与经销商勤沟通，关注经营动态，及时响应需求。 | U66: — | X66: 经营意愿处于同类经销商中的领先水平，对于品牌经营信心充足，愿意配合公司积极开展市场活动，并投入人力物力等资源开展经营。建议保持沟通，深化合作关系。 | Z66: 超特|2000W+|经营意愿
A67: 超特 | B67: 2000W+ | C67: 意愿层 | D67: — | E67: 文化认知度 | F67: a/b/c档 | G67: 0.015 | H67: A档 | I67: c | J67: 20 | K67: 固定20分（不认同） | L67: 文化认知度处于同类经销商中的末位水平，文化认知度薄弱，文化认同感低。建议与经销商勤沟通，建立文化沟通机制，及时传递文化理念；通过文化践行活动，促进文化认同。 | M67: b | N67: 60 | O67: 固定60分（了解认同） | P67: 文化认知度处于同类经销商中的中等偏下水平，文化理解不深，认同不足。建议加强企业文化宣导，提升文化认知度。 | Q67: a | R67: 90 | S67: 固定90分（高度认同品牌文化，最高档） | T67: 文化认知度处于同类经销商中的中等偏上水平，文化认同情况良好。建议加强企业文化培训，深化文化理解。 | U67: — | X67: 文化认知度处于同类经销商中的领先水平，对企业文化清晰认知和认同，价值观一致，合作基础稳固，并在日常市场经营活动中积极践行。建议积极传播企业文化，发挥示范作用。 | Z67: 超特|2000W+|文化认知度
A68: 一二级 | B68: 300W-1000W | C68: 增长层 | D68: 生意总体 | E68: 合同达成率 | F68: % | G68: 0.1 | H68: 1 | I68: 0.85 | J68: 0.1 | K68: 实际值×0.1（得分随实际值浮动） | L68: 合同达成率低于85%，履约情况需重点改善，严重影响合作稳定性。建议深入复盘分析未达成原因，制定详细改进计划并跟踪落实，确保合同履约执行到位。 | M68: 0.9 | N68: 0.11 | O68: 实际值×0.11 | P68: 合同达成率低于90%，合同履约不足，存在较大改善空间。建议重点关注低达成率品类，分析原因并制定改善计划。 | Q68: 1 | R68: 0.12 | S68: 实际值×0.12 | T68: 全年合同尚未达百，但整体达成情况较好，可能存在部分合同履约不足。建议关注单份合同达成差异，制定针对性改进措施。 | U68: — | V68: 0.144 | W68: 固定封顶，最高14.4分 | X68: 全年合同达百，整体表现优异。建议深入分析单份合同达成差异，防范个别合同达成不力带来的风险。 | Y68: 比例计分，区间上限即为各档临界值 | Z68: 一二级|300W-1000W|合同达成率
A69: 一二级 | B69: 300W-1000W | C69: 增长层 | D69: 生意总体 | E69: 销售增长率 | F69: % | G69: 0.1 | H69: 0.386 | I69: -1e-17 | J69: 0 | K69: 负增长超过阈值，得0分 | L69: 销售呈现负增长，市场竞争力弱。建议深入分析市场环境和竞争态势，制定针对性营销策略，同时对负增长品类进行专项评估，调整产品结构。 | M69: 0.1267 | N69: 0.04 | O69: 固定系数，×100得4分 | P69: 销售增长率处于同类经销商中的中等偏下水平，增长动力有待加强。建议聚焦低增长品类，分析原因并制定提升策略。 | Q69: 0.3857 | R69: 0.07 | S69: 固定系数，×100得7分 | T69: 销售增长率处于同类经销商中的中等偏上水平，增长态势良好。建议持续关注品类增长，挖掘潜力品类，提升增长空间。 | U69: — | V69: 0.1 | W69: 固定系数，×100得10分 | X69: 销售增长率处于同类经销商中的领先水平，增长动力强劲。建议关注各品类的增长表现，识别增长引擎品类，制定可持续增长策略，避免短期波动影响长期发展。 | Z69: 一二级|300W-1000W|销售增长率
A70: 一二级 | B70: 300W-1000W | C70: 增长层 | D70: 分销 | E70: 网点数量 | F70: 个 | G70: 0.058 | H70: 334个 | I70: 177 | J70: 30 | K70: 固定30分 | L70: 网点数量处于同类经销商中的末位水平，网点数量严重不足，网络基础薄弱。建议快速制定网点开发计划，加快拓展步伐，优先覆盖重点区域，并建立网点建设进度跟踪机制，确保计划落地。 | M70: 267 | N70: 50 | O70: 固定50分 | P70: 网点数量处于同类经销商中的中等偏下水平，网点数量少，网络覆盖不足。建议制定网点拓展计划，持续推进网点开发，填补空白区域，逐步完善网络布局。 | Q70: 334 | R70: 70 | S70: 固定70分 | T70: 网点数量处于同类经销商中的中等偏上水平，网络布局合理。建议在稳定数量的同时提升网点质量，聚焦单店产值和有效门店占比提升，优化网点结构。 | U70: ≥334 | V70: 90 | W70: 固定90分（满分） | X70: 网点数量处于同类经销商中的领先水平，网点覆盖广泛，网络基础扎实。建议重点提升单店产值和核心店占比，优化网点质量；同时建立网点分级管理体系，提高网点运营效率。 | Z70: 一二级|300W-1000W|网点数量
A71: 一二级 | B71: 300W-1000W | C71: 增长层 | D71: 分销 | E71: 核心店数量占比 | F71: % | G71: 0.043 | H71: 0.202 | I71: 0.105 | J71: 30 | K71: 固定30分 | L71: 核心店数量占比处于同类经销商中的末位水平，分销渠道结构极不稳定，核心网点建设严重不足，增长依赖低产值网点。建议分级管理，紧急选拔有潜力门店进行重点培育，打造核心店；学习优秀经销商核心店建设经验，快速复制；建立核心店建设专项考核机制，确保建设效果。 | M71: 0.152 | N71: 50 | O71: 固定50分 | P71: 核心店数量占比处于同类经销商中的中等偏下水平，分销渠道结构不稳定，核心网点建设不足，市场支撑能力弱。建议持续提升网点质量，建立核心店运营标准，培育更多核心店。 | Q71: 0.202 | R71: 70 | S71: 固定70分 | T71: 核心店数量占比处于同类经销商中的中等偏上水平，分销渠道结构稳定，核心店占比相对健康。建议关注核心店达成，建立核心店培育与退出机制，持续提升核心店质量，稳定增长基础。 | U71: ≥20.2% | V71: 90 | W71: 固定90分（满分） | X71: 核心店数量占比处于同类经销商中的领先水平，核心资源集中，分销渠道增长由核心店驱动，市场竞争力强。建议持续关注核心店达成情况，保持增长动力。 | Z71: 一二级|300W-1000W|核心店数量占比
A72: 一二级 | B72: 300W-1000W | C72: 增长层 | D72: 分销 | E72: 有效门店占比 | F72: % | G72: 0.13 | H72: 0.949 | I72: 0.853 | J72: 30 | K72: 固定30分 | L72: 有效门店占比处于同类经销商中的末位水平，建议安排专人定时进行拜访，完善分销管理流程；对低效门店进行全面评估，制定关停并转计划，集中资源提升保留门店的运营效率。 | M72: 0.92 | N72: 50 | O72: 固定50分 | P72: 有效门店占比处于同类经销商中的中等偏下水平，存在部分“沉睡”门店。建议提升拜访率，激活沉睡门店，避免分销资源浪费；同时对低效门店进行评估，制定整改或淘汰计划。 | Q72: 0.949 | R72: 70 | S72: 固定70分 | T72: 有效门店占比处于同类经销商中的中等偏上水平，网点拜访率及陈列合格率较高，大部分门店运营有效，存在少量低效门店。建议对低效门店进行整改或优化，提升整体有效性。 | U72: ≥94.9% | V72: 90 | W72: 固定90分（满分） | X72: 有效门店占比处于同类经销商中的领先水平，网点拜访率及陈列合格率高，资源利用效率高。建议关注高拜访率门店的产值表现。 | Z72: 一二级|300W-1000W|有效门店占比
A73: 一二级 | B73: 300W-1000W | C73: 增长层 | D73: 分销 | E73: 人均服务网点数 | F73: 个 | G73: 0.048 | H73: 79个 | I73: 47.5 | J73: 30 | K73: 固定30分 | L73: 人均服务网点数处于同类经销商中的末位水平，人员服务密度严重不足，单点人力服务成本高。建议重新设定人员服务网点考核指标，提升人员利用效率。 | M73: 60.3 | N73: 50 | O73: 固定50分 | P73: 人均服务网点数处于同类经销商中的中等偏下水平，单兵服务半径较小，人力资源利用不充分。建议提升网点数量，释放人员效能。 | Q73: 79 | R73: 70 | S73: 固定70分 | T73: 人均服务网点数处于同类经销商中的中等偏上水平，管理半径相对合理。建议持续关注人效，优化资源配置。 | U73: ≥79 | V73: 90 | W73: 固定90分（满分） | X73: 人均服务网点数处于同类经销商中的领先水平，单兵服务密度极高，人员负荷处于满载状态。建议关注人效，防止服务质量下降。 | Z73: 一二级|300W-1000W|人均服务网点数
A74: 一二级 | B74: 300W-1000W | C74: 增长层 | D74: 分销 | E74: 自有人员数量 | F74: 个 | G74: 0.024 | H74: 3人 | I74: 1 | J74: 30 | K74: 固定30分 | L74: 自有人员数量处于同类经销商中的末位水平，自有销售人员严重不足，业务开拓与网络维护能力严重受限。建议制定招聘计划，快速补充人员。 | M74: 2 | N74: 50 | O74: 固定50分 | P74: 自有人员数量处于同类经销商中的中等偏下水平，自有人员力量薄弱，覆盖与服务能力不足。建议结合人效和渠道需求，制定人员招聘计划，补充团队力量。 | Q74: 3 | R74: 70 | S74: 固定70分 | T74: 自有人员数量处于同类经销商中的中等偏上水平，具备基础的覆盖保障能力。建议聚焦重点渠道，优化人员配置。 | U74: ≥3 | V74: 90 | W74: 固定90分（满分） | X74: 自有人员数量处于同类经销商中的领先水平，具备深耕市场的团队基础。建议结合渠道发展合理分工，加强人员专业技能培训，提升团队整体素质；建立人员梯队建设计划，保障团队可持续发展。 | Z74: 一二级|300W-1000W|自有人员数量
A75: 一二级 | B75: 300W-1000W | C75: 增长层 | D75: 分销 | E75: 人效 | F75: 万元/人 | G75: 0.067 | H75: 310.7万/人 | I75: 204.8 | J75: 30 | K75: 固定30分 | L75: 人效处于同类经销商中的末位水平，可能存在经营亏损风险。建议关注如何提升销售额或考虑人员调整，建立明确的绩效考核和激励机制；同时加强人员培训，提升专业技能和工作效率。 | M75: 260.2 | N75: 50 | O75: 固定50分 | P75: 人效处于同类经销商中的中等偏下水平，人均产出不足，无法满足当前生意规模的需求。建议优化工作流程，消除无效劳动；建立绩效考核机制，激发人员工作积极性。 | Q75: 310.7 | R75: 70 | S75: 固定70分 | T75: 人效处于同类经销商中的中等偏上水平，基本满足当前生意规模的需求。建议分析高绩效人员工作方法，在团队内推广，持续优化人员产出，提升盈利能力。 | U75: ≥310.7 | V75: 90 | W75: 固定90分（满分） | X75: 人效处于同类经销商中的领先水平，人力资源利用充分，人均创造价值高。建议关注销售额整体构成，提升净利润水平。 | Z75: 一二级|300W-1000W|人效
A76: 一二级 | B76: 300W-1000W | C76: 增长层 | D76: 分销 | E76: 乡镇覆盖率 | F76: % | G76: 0.014 | H76: 1 | I76: 0.647 | J76: 30 | K76: 固定30分 | L76: 乡镇覆盖率处于同类经销商中的末位水平，乡镇覆盖极少，下沉市场开拓严重不足。建议制定乡镇市场专项开拓计划，快速布局；简化乡镇市场进入流程，降低开拓难度；建立乡镇市场开拓激励机制，加快开拓进度。 | M76: 0.8235 | N76: 50 | O76: 固定50分 | P76: 乡镇覆盖率处于同类经销商中的中等水平，乡镇覆盖良好，布局较为均衡。建议建议制定乡镇开拓计划，筛选空白重点乡镇，逐步扩大乡镇覆盖范围，持续完善乡镇网络。 | Q76: 1 | R76: 70 | S76: 固定70分（本指标最高档，无第四档） | T76: 乡镇覆盖率处于同类经销商中的领先水平，乡镇市场渗透充分。建议关注乡镇网点的产值表现，制定差异化运营方案，优化产品和服务策略。 | U76: — | X76: 乡镇覆盖率处于同类经销商中的领先水平，乡镇市场渗透充分。建议关注乡镇网点的产值表现，制定差异化运营方案，优化产品和服务策略。 | Y76: 仅三档，满分系数70（非90） | Z76: 一二级|300W-1000W|乡镇覆盖率
A77: 一二级 | B77: 300W-1000W | C77: 增长层 | D77: 分销 | E77: 单店产出 | F77: 万元 | G77: 0.096 | H77: 3.0万 | I77: 1.8 | J77: 30 | K77: 固定30分 | L77: 单店产值处于同类经销商中的末位水平，门店产出普遍偏低。建议全面诊断门店运营问题，制定系统性提升方案；加强门店陈列、促销和服务管理，提升单店产出；建立门店运营督导机制，确保改进措施执行到位。 | M77: 2.2 | N77: 50 | O77: 固定50分 | P77: 单店产值处于同类经销商中的中等偏下水平，门店之间产值差异较大，整体水平偏低，单店运营效率有待提升。建议提升铺货率和拜访频次，激活低效门店。 | Q77: 3 | R77: 70 | S77: 固定70分 | T77: 单店产值处于同类经销商中的中等偏上水平，网络基础较好。大部分门店运营正常，少数门店产值偏低，建议聚焦低产值网点，提升铺货率和销售能力。 | U77: ≥3 | V77: 90 | W77: 固定90分（满分） | X77: 单店产值处于同类经销商中的领先水平，头部门店表现突出。建议分析头部门店成功经验，复制推广至其他门店，防范因过度依赖少数头部门店而导致的结构性风险。 | Z77: 一二级|300W-1000W|单店产出
A78: 一二级 | B78: 300W-1000W | C78: 增长层 | D78: 零售 | E78: 会员数量 | F78: 人 | G78: 0.035 | H78: 95人 | I78: 28 | J78: 30 | K78: 固定30分 | L78: 会员数量处于同类经销商中的末位水平，客户数量严重缺失，市场影响力弱。建议制定会员快速发展计划，通过多种渠道吸纳会员；建立会员入门优惠机制，降低会员加入门槛；加强会员服务基础建设，提升会员留存率。 | M78: 47 | N78: 50 | O78: 固定50分 | P78: 会员数量处于同类经销商中的中等偏下水平，客户基础薄弱，尚未形成规模。建议制定会员发展计划，通过工人会和小区推广等形式，扩大会员规模；建立会员服务体系，提升会员满意度和忠诚度。 | Q78: 95 | R78: 70 | S78: 固定70分 | T78: 会员数量处于同类经销商中的中等偏上水平，客户基础较好，具备零售业务基础。建议持续挖掘会员价值，提升转化率。 | U78: ≥95 | V78: 90 | W78: 固定90分（满分） | X78: 会员数量处于同类经销商中的领先水平，市场影响力强，客户资源丰富。建议建立会员分级管理体系，提升高价值会员服务质量；制定会员活跃度提升计划，增强会员粘性。 | Z78: 一二级|300W-1000W|会员数量
A79: 一二级 | B79: 300W-1000W | C79: 增长层 | D79: 零售 | E79: 会员人均产出 | F79: 万元/人 | G79: 0.015 | H79: 0.50万/人 | I79: 0.269 | J79: 30 | K79: 固定30分 | L79: 会员人均产出处于同类经销商中的末位水平，客户价值低，消费转化困难。建议安排专人负责，勤沟通，多开展培训会、订货会等，制定会员消费激励计划，提高会员消费频次和客单价。 | M79: 0.335 | N79: 50 | O79: 固定50分 | P79: 会员人均产出处于同类经销商中的中等偏下水平，价值转化不足，会员消费频次低。建议多开展培训会、订货会等，建立会员激励机制，提高会员消费积极性。 | Q79: 0.502 | R79: 70 | S79: 固定70分 | T79: 会员人均产出处于同类经销商中的中等偏上水平，会员产出良好，贡献稳定，高价值会员占比有待提升。建议建立会员价值提升机制，持续挖掘会员潜在价值；识别高潜力会员，制定专项服务计划。 | U79: ≥0.502 | V79: 90 | W79: 固定90分（满分） | X79: 会员人均产出处于同类经销商中的领先水平，核心会员粘性强、贡献大。建议与核心会员签订协议，建立长期合作关系，保证稳定性。 | Z79: 一二级|300W-1000W|会员人均产出
A80: 一二级 | B80: 300W-1000W | C80: 增长层 | D80: 渠道均衡发展 | E80: 渠道数量 | F80: 个 | G80: 0.06 | H80: 4个 | I80: 2 | J80: 20 | K80: 固定20分 | L80: 渠道数量处于同类经销商中的末位水平，业务结构单一，渠道建设严重不足。抗风险能力弱。建议拓展多元化渠道，丰富渠道结构；加强与现有渠道的深度合作，提升渠道效益。 | M80: 3 | N80: 70 | O80: 固定70分 | P80: 渠道数量处于同类经销商中的中等偏下水平，渠道类型少，抗风险能力不足。建议拓展多元化渠道，丰富渠道结构。 | Q80: 4 | R80: 90 | S80: 固定90分 | T80: 渠道数量处于同类经销商中的中等偏上水平，具备一定的抗风险能力。建议结合当地及自身情况，评估是否拓展新渠道；同时评估低效渠道改进空间，优化渠道结构。 | U80: ≧4 | V80: 90 | W80: 固定90分 | X80: 渠道数量处于同类经销商中的领先水平，业务结构健康多元，具备一定盈利能力和发展潜力，抗风险能力强。建议针对低产出渠道进行资源倾斜。 | Y80: 四档，得分跨度较大（20/70/90），区间③和区间④分值均为90分。 | Z80: 一二级|300W-1000W|渠道数量
A81: 一二级 | B81: 300W-1000W | C81: 增长层 | D81: 品类均衡发展 | E81: 品类数量 | F81: 个 | G81: 0.06 | H81: 4个 | I81: 2 | J81: 20 | K81: 固定20分（品类数<2个） | L81: 品类数量处于同类经销商中的末位水平，品类结构单一，客单价和盈利能力可能陷入瓶颈。建议结合当地市场需求，增加新品，提升品类丰富度和盈利能力。 | M81: 3 | N81: 50 | O81: 固定50分（2≤品类数<3个） | P81: 品类数量处于同类经销商中的中等偏下水平，品类偏少，综合服务能力不足。建议适当增加新品类，丰富产品结构，提升竞争力。 | Q81: 4 | R81: 70 | S81: 固定70分（3≤品类数<4个） | T81: 品类数量处于同类经销商中的中等偏上水平，具备基础的综合服务能力，建议结合产品销售增长情况，评估是否增加新品。 | U81: — | V81: 90 | W81: 固定90分（品类数≥4个） | X81: 品类数量处于同类经销商中的领先水平，品类结构丰富，具备一站式综合服务基础，市场竞争力强。建议分级管理品类，明确利润品与销量品，保持品类活力。 | Y81: 四档，20/50/70/90 | Z81: 一二级|300W-1000W|品类数量
A82: 一二级 | B82: 300W-1000W | C82: 支撑层 | D82: 会议场次 | E82: 分销会次数 | F82: 次 | G82: 0.025 | H82: 5次 | I82: 1 | J82: 30 | K82: 固定30分 | L82: 分销会场次处于同类经销商中的末位水平，与分销渠道的互动极度缺乏，渠道可能存在失联风险。建议结合门店拜访计划，制定最低会议频次标准，确保基本沟通；同时建立渠道反馈机制，及时了解渠道需求。 | M82: 2 | N82: 50 | O82: 固定50分 | P82: 分销会场次处于同类经销商中的中等偏下水平，渠道沟通不足，难以维系渠道粘性。建议结合销售节奏，制定分销会议计划，增加会议频次。 | Q82: 5 | R82: 70 | S82: 固定70分 | T82: 分销会场次处于同类经销商中的中等偏上水平，渠道粘性较强。建议聚焦核心店和有效门店，提升会议质量。 | U82: ≥5 | V82: 90 | W82: 固定90分（满分） | X82: 分销会场次处于同类经销商中的领先水平，在激活分销网络上具备主动性，渠道维护积极。建议提升会议质量和针对性，增强会议效果，关注分销单店产值。 | Z82: 一二级|300W-1000W|分销会次数
A83: 一二级 | B83: 300W-1000W | C83: 支撑层 | D83: 会议场次 | E83: 专业人士会议次数 | F83: 次 | G83: 0.035 | H83: 29次 | I83: 11 | J83: 30 | K83: 固定30分 | L83: 专业人士会议场次处于同类经销商中的末位水平，客情维护严重缺失，会员关系薄弱。建议制定专业人士会议计划，定期开展会议，加强会员沟通。 | M83: 17 | N83: 50 | O83: 固定50分 | P83: 专业人士会议场次处于同类经销商中的中等偏下水平，客情维护不足。建议聚焦新会员和低黏度会员，增强互动。 | Q83: 29 | R83: 70 | S83: 固定70分 | T83: 专业人士会议场次处于同类经销商中的中等偏上水平，会议开展良好，会员关系稳定。建议关注会员人均产出，提升低产出会员。 | U83: ≥29 | V83: 90 | W83: 固定90分（14~40次区间满分） | X83: 专业人士会议场次处于同类经销商中的领先水平，会议开展积极，客情维护到位。 建议关注会员人均产出，防范资源浪费。 | Y83: ⚠️ 特殊规则：次数>40次视为数据异常，得分回退至50分，函数中需单独处理 | Z83: 一二级|300W-1000W|专业人士会议次数
A84: 一二级 | B84: 300W-1000W | C84: 支撑层 | D84: 仓储效率 | E84: 坪效 | F84: 万元/㎡ | G84: 0.02 | H84: 0.94万/平方米 | I84: 0.6 | J84: 30 | K84: 固定30分 | L84: 坪效处于同类经销商中的末位水平，运营成本高，仓储可能已成为高成本负担。建议优化库存管理，调整产品结构；关注坪效指标，持续提升空间利用效率。 | M84: 0.75 | N84: 50 | O84: 固定50分 | P84: 坪效处于同类经销商中的中等偏下水平，仓储运营管理粗放，表明成本控制能力不足。建议调整产品结构，提升仓储效率。 | Q84: 0.94 | R84: 70 | S84: 固定70分 | T84: 坪效处于同类经销商中的中等偏上水平，仓储利用与成本控制良好。建议根据产品周转率优化仓储布局，聚焦低周转率产品，提升空间效率。 | U84: ≥0.94 | V84: 90 | W84: 固定90分（满分） | X84: 坪效处于同类经销商中的领先水平，仓储运营的精细化管理程度高，成本控制好。建议根据毛利润调整产品组合，持续优化。 | Z84: 一二级|300W-1000W|坪效
A85: 一二级 | B85: 300W-1000W | C85: 支撑层 | D85: 数字化水平 | E85: 数字化水平 | F85: a/b/c/d档 | G85: 0.02 | H85: a档 | I85: d | J85: 0 | K85: 未采用数字化系统，0分 | L85: 数字化水平处于同类经销商中的末位水平，无系统，管理方式原始，数据资产缺失，管理风险高，数据价值被浪费。建议引入基础数字化管理工具，加强人员数字化技能培训，快速推动数字化转型。 | M85: a | N85: 30 | O85: 固定30分（进销存系统） | P85: 数字化水平处于同类经销商中的中等偏下水平，数字化应用停留在记账层面，仍以传统管理方式为主，数据价值可能被浪费。建议引入数字化管理工具，提升管理效率和风险控制能力。 | Q85: b | R85: 70 | S85: 固定70分（数据分析能力） | T85: 数字化水平处于同类经销商中的中等偏上水平，已开始利用数据进行管理。建议建立数据资产体系，提升数据价值。 | U85: c | V85: 90 | W85: 固定90分（a档，指标洞察能力，满分） | X85: 数字化水平处于同类经销商中的领先水平，具备数据驱动决策能力。建议加强数据分析能力建设，用数据指导经营，提升决策效率。 | Y85: 字母档位评级，非数值区间；c最高（指标洞察），d最低 | Z85: 一二级|300W-1000W|数字化水平
A86: 一二级 | B86: 300W-1000W | C86: 意愿层 | D86: — | E86: 活动参与度 | F86: a/b/c档 | G86: 0.015 | H86: A档 | I86: c | J86: 20 | K86: 固定20分（基本不参与） | L86: 活动参与度处于同类经销商中的末位水平，活动参与积极性低，意愿差。建议与经销商勤沟通，提前沟通活动重要性和利益点；建立活动参与考核和激励机制，提升参与积极性。 | M86: b | N86: 60 | O86: 固定60分（一般参与） | P86: 活动参与度处于同类经销商中的中等偏下水平，参与积极性不足。建议与经销商勤沟通，找出活动参与度低的原因，提升活动参与意愿。 | Q86: a | R86: 90 | S86: 固定90分（积极参与，最高档） | T86: 活动参与度处于同类经销商中的中等偏上水平，参与意愿较强。建议建立活动总结机制，持续优化活动参与质量。 | U86: — | X86: 活动参与度处于同类经销商中的领先水平，活动配合积极，市场响应及时。建议关注活动执行效果，提升活动价值。 | Z86: 一二级|300W-1000W|活动参与度
A87: 一二级 | B87: 300W-1000W | C87: 意愿层 | D87: — | E87: 经营意愿 | F87: a/b/c档 | G87: 0.02 | H87: a档 | I87: c | J87: 20 | K87: 固定20分（计划放弃） | L87: 经营意愿处于同类经销商中的末位水平，对品牌信息不足，合作稳定性低。建议加强深度沟通，了解顾虑并提供解决方案，逐步建立信心。 | M87: b | N87: 60 | O87: 固定60分（一般配合） | P87: 经营意愿处于同类经销商中的中等偏下水平，经营积极性不足。建议与经销商勤沟通，找出经营意愿低的原因，寻找提升意愿的突破口。 | Q87: a | R87: 90 | S87: 固定90分（强烈经营意愿，最高档） | T87: 经营意愿处于同类经销商中的中等偏上水平，合作意愿较强。建议与经销商勤沟通，关注经营动态，及时响应需求。 | U87: — | X87: 经营意愿处于同类经销商中的领先水平，对于品牌经营信心充足，愿意配合公司积极开展市场活动，并投入人力物力等资源开展经营。建议保持沟通，深化合作关系。 | Z87: 一二级|300W-1000W|经营意愿
A88: 一二级 | B88: 300W-1000W | C88: 意愿层 | D88: — | E88: 文化认知度 | F88: a/b/c档 | G88: 0.015 | H88: A档 | I88: c | J88: 20 | K88: 固定20分（不认同） | L88: 文化认知度处于同类经销商中的末位水平，文化认知度薄弱，文化认同感低。建议与经销商勤沟通，建立文化沟通机制，及时传递文化理念；通过文化践行活动，促进文化认同。 | M88: b | N88: 60 | O88: 固定60分（了解认同） | P88: 文化认知度处于同类经销商中的中等偏下水平，文化理解不深，认同不足。建议加强企业文化宣导，提升文化认知度。 | Q88: a | R88: 90 | S88: 固定90分（高度认同品牌文化，最高档） | T88: 文化认知度处于同类经销商中的中等偏上水平，文化认同情况良好。建议加强企业文化培训，深化文化理解。 | U88: — | X88: 文化认知度处于同类经销商中的领先水平，对企业文化清晰认知和认同，价值观一致，合作基础稳固，并在日常市场经营活动中积极践行。建议积极传播企业文化，发挥示范作用。 | Z88: 一二级|300W-1000W|文化认知度
A89: 一二级 | B89: 1000W-2000W | C89: 增长层 | D89: 生意总体 | E89: 合同达成率 | F89: % | G89: 0.1 | H89: 1 | I89: 0.85 | J89: 0.1 | K89: 实际值×0.1（得分随实际值浮动） | L89: 合同达成率低于85%，履约情况需重点改善，严重影响合作稳定性。建议深入复盘分析未达成原因，制定详细改进计划并跟踪落实，确保合同履约执行到位。 | M89: 0.9 | N89: 0.11 | O89: 实际值×0.11 | P89: 合同达成率低于90%，合同履约不足，存在较大改善空间。建议重点关注低达成率品类，分析原因并制定改善计划。 | Q89: 1 | R89: 0.12 | S89: 实际值×0.12 | T89: 全年合同尚未达百，但整体达成情况较好，可能存在部分合同履约不足。建议关注单份合同达成差异，制定针对性改进措施。 | U89: — | V89: 0.144 | W89: 固定封顶，最高14.4分 | X89: 全年合同达百，整体表现优异。建议深入分析单份合同达成差异，防范个别合同达成不力带来的风险。 | Y89: 比例计分，区间上限即为各档临界值 | Z89: 一二级|1000W-2000W|合同达成率
A90: 一二级 | B90: 1000W-2000W | C90: 增长层 | D90: 生意总体 | E90: 销售增长率 | F90: % | G90: 0.1 | H90: 0.158 | I90: -1e-17 | J90: 0 | K90: 负增长超过阈值，得0分 | L90: 销售呈现负增长，市场竞争力弱。建议深入分析市场环境和竞争态势，制定针对性营销策略，同时对负增长品类进行专项评估，调整产品结构。 | M90: 0.0274 | N90: 0.04 | O90: 固定系数，×100得4分 | P90: 销售增长率处于同类经销商中的中等偏下水平，增长动力有待加强。建议聚焦低增长品类，分析原因并制定提升策略。 | Q90: 0.1582 | R90: 0.07 | S90: 固定系数，×100得7分 | T90: 销售增长率处于同类经销商中的中等偏上水平，增长态势良好。建议持续关注品类增长，挖掘潜力品类，提升增长空间。 | U90: — | V90: 0.1 | W90: 固定系数，×100得10分 | X90: 销售增长率处于同类经销商中的领先水平，增长动力强劲。建议关注各品类的增长表现，识别增长引擎品类，制定可持续增长策略，避免短期波动影响长期发展。 | Z90: 一二级|1000W-2000W|销售增长率
A91: 一二级 | B91: 1000W-2000W | C91: 增长层 | D91: 分销 | E91: 网点数量 | F91: 个 | G91: 0.0405 | H91: 489个 | I91: 321 | J91: 30 | K91: 固定30分 | L91: 网点数量处于同类经销商中的末位水平，网点数量严重不足，网络基础薄弱。建议快速制定网点开发计划，加快拓展步伐，优先覆盖重点区域，并建立网点建设进度跟踪机制，确保计划落地。 | M91: 369 | N91: 50 | O91: 固定50分 | P91: 网点数量处于同类经销商中的中等偏下水平，网点数量少，网络覆盖不足。建议制定网点拓展计划，持续推进网点开发，填补空白区域，逐步完善网络布局。 | Q91: 489 | R91: 70 | S91: 固定70分 | T91: 网点数量处于同类经销商中的中等偏上水平，网络布局合理。建议在稳定数量的同时提升网点质量，聚焦单店产值和有效门店占比提升，优化网点结构。 | U91: ≥489 | V91: 90 | W91: 固定90分（满分） | X91: 网点数量处于同类经销商中的领先水平，网点覆盖广泛，网络基础扎实。建议重点提升单店产值和核心店占比，优化网点质量；同时建立网点分级管理体系，提高网点运营效率。 | Z91: 一二级|1000W-2000W|网点数量
A92: 一二级 | B92: 1000W-2000W | C92: 增长层 | D92: 分销 | E92: 核心店数量占比 | F92: % | G92: 0.0405 | H92: 0.234 | I92: 0.103 | J92: 30 | K92: 固定30分 | L92: 核心店数量占比处于同类经销商中的末位水平，分销渠道结构极不稳定，核心网点建设严重不足，增长依赖低产值网点。建议分级管理，紧急选拔有潜力门店进行重点培育，打造核心店；学习优秀经销商核心店建设经验，快速复制；建立核心店建设专项考核机制，确保建设效果。 | M92: 0.168 | N92: 50 | O92: 固定50分 | P92: 核心店数量占比处于同类经销商中的中等偏下水平，分销渠道结构不稳定，核心网点建设不足，市场支撑能力弱。建议持续提升网点质量，建立核心店运营标准，培育更多核心店。 | Q92: 0.234 | R92: 70 | S92: 固定70分 | T92: 核心店数量占比处于同类经销商中的中等偏上水平，分销渠道结构稳定，核心店占比相对健康。建议关注核心店达成，建立核心店培育与退出机制，持续提升核心店质量，稳定增长基础。 | U92: ≥23.4% | V92: 90 | W92: 固定90分（满分） | X92: 核心店数量占比处于同类经销商中的领先水平，核心资源集中，分销渠道增长由核心店驱动，市场竞争力强。建议持续关注核心店达成情况，保持增长动力。 | Z92: 一二级|1000W-2000W|核心店数量占比
A93: 一二级 | B93: 1000W-2000W | C93: 增长层 | D93: 分销 | E93: 有效门店占比 | F93: % | G93: 0.09 | H93: 0.955 | I93: 0.843 | J93: 30 | K93: 固定30分 | L93: 有效门店占比处于同类经销商中的末位水平，建议安排专人定时进行拜访，完善分销管理流程；对低效门店进行全面评估，制定关停并转计划，集中资源提升保留门店的运营效率。 | M93: 0.923 | N93: 50 | O93: 固定50分 | P93: 有效门店占比处于同类经销商中的中等偏下水平，存在部分“沉睡”门店。建议提升拜访率，激活沉睡门店，避免分销资源浪费；同时对低效门店进行评估，制定整改或淘汰计划。 | Q93: 0.955 | R93: 70 | S93: 固定70分 | T93: 有效门店占比处于同类经销商中的中等偏上水平，网点拜访率及陈列合格率较高，大部分门店运营有效，存在少量低效门店。建议对低效门店进行整改或优化，提升整体有效性。 | U93: ≥95.5% | V93: 90 | W93: 固定90分（满分） | X93: 有效门店占比处于同类经销商中的领先水平，网点拜访率及陈列合格率高，资源利用效率高。建议关注高拜访率门店的产值表现。 | Z93: 一二级|1000W-2000W|有效门店占比
A94: 一二级 | B94: 1000W-2000W | C94: 增长层 | D94: 分销 | E94: 人均服务网点数 | F94: 个 | G94: 0.045 | H94: 80个 | I94: 51.6 | J94: 30 | K94: 固定30分 | L94: 人均服务网点数处于同类经销商中的末位水平，人员服务密度严重不足，单点人力服务成本高。建议重新设定人员服务网点考核指标，提升人员利用效率。 | M94: 62.6 | N94: 50 | O94: 固定50分 | P94: 人均服务网点数处于同类经销商中的中等偏下水平，单兵服务半径较小，人力资源利用不充分。建议提升网点数量，释放人员效能。 | Q94: 80.3 | R94: 70 | S94: 固定70分 | T94: 人均服务网点数处于同类经销商中的中等偏上水平，管理半径相对合理。建议持续关注人效，优化资源配置。 | U94: ≥80.3 | V94: 90 | W94: 固定90分（满分） | X94: 人均服务网点数处于同类经销商中的领先水平，单兵服务密度极高，人员负荷处于满载状态。建议关注人效，防止服务质量下降。 | Z94: 一二级|1000W-2000W|人均服务网点数
A95: 一二级 | B95: 1000W-2000W | C95: 增长层 | D95: 分销 | E95: 自有人员数量 | F95: 个 | G95: 0.0225 | H95: 4人 | I95: 2 | J95: 30 | K95: 固定30分 | L95: 自有人员数量处于同类经销商中的末位水平，自有销售人员严重不足，业务开拓与网络维护能力严重受限。建议制定招聘计划，快速补充人员。 | M95: 3 | N95: 50 | O95: 固定50分 | P95: 自有人员数量处于同类经销商中的中等偏下水平，自有人员力量薄弱，覆盖与服务能力不足。建议结合人效和渠道需求，制定人员招聘计划，补充团队力量。 | Q95: 4 | R95: 70 | S95: 固定70分 | T95: 自有人员数量处于同类经销商中的中等偏上水平，具备基础的覆盖保障能力。建议聚焦重点渠道，优化人员配置。 | U95: ≥4 | V95: 90 | W95: 固定90分（满分） | X95: 自有人员数量处于同类经销商中的领先水平，具备深耕市场的团队基础。建议结合渠道发展合理分工，加强人员专业技能培训，提升团队整体素质；建立人员梯队建设计划，保障团队可持续发展。 | Z95: 一二级|1000W-2000W|自有人员数量
A96: 一二级 | B96: 1000W-2000W | C96: 增长层 | D96: 分销 | E96: 人效 | F96: 万元/人 | G96: 0.09 | H96: 478.2万/人 | I96: 291.8 | J96: 30 | K96: 固定30分 | L96: 人效处于同类经销商中的末位水平，可能存在经营亏损风险。建议关注如何提升销售额或考虑人员调整，建立明确的绩效考核和激励机制；同时加强人员培训，提升专业技能和工作效率。 | M96: 350.8 | N96: 50 | O96: 固定50分 | P96: 人效处于同类经销商中的中等偏下水平，人均产出不足，无法满足当前生意规模的需求。建议优化工作流程，消除无效劳动；建立绩效考核机制，激发人员工作积极性。 | Q96: 478.2 | R96: 70 | S96: 固定70分 | T96: 人效处于同类经销商中的中等偏上水平，基本满足当前生意规模的需求。建议分析高绩效人员工作方法，在团队内推广，持续优化人员产出，提升盈利能力。 | U96: ≥478.2 | V96: 90 | W96: 固定90分（满分） | X96: 人效处于同类经销商中的领先水平，人力资源利用充分，人均创造价值高。建议关注销售额整体构成，提升净利润水平。 | Z96: 一二级|1000W-2000W|人效
A97: 一二级 | B97: 1000W-2000W | C97: 增长层 | D97: 分销 | E97: 乡镇覆盖率 | F97: % | G97: 0.009 | H97: 1 | I97: 0.778 | J97: 30 | K97: 固定30分 | L97: 乡镇覆盖率处于同类经销商中的末位水平，乡镇覆盖极少，下沉市场开拓严重不足。建议制定乡镇市场专项开拓计划，快速布局；简化乡镇市场进入流程，降低开拓难度；建立乡镇市场开拓激励机制，加快开拓进度。 | M97: 0.889 | N97: 50 | O97: 固定50分 | P97: 乡镇覆盖率处于同类经销商中的中等水平，乡镇覆盖良好，布局较为均衡。建议建议制定乡镇开拓计划，筛选空白重点乡镇，逐步扩大乡镇覆盖范围，持续完善乡镇网络。 | Q97: 1 | R97: 70 | S97: 固定70分（本指标最高档，无第四档） | T97: 乡镇覆盖率处于同类经销商中的领先水平，乡镇市场渗透充分。建议关注乡镇网点的产值表现，制定差异化运营方案，优化产品和服务策略。 | U97: — | X97: 乡镇覆盖率处于同类经销商中的领先水平，乡镇市场渗透充分。建议关注乡镇网点的产值表现，制定差异化运营方案，优化产品和服务策略。 | Y97: 仅三档，满分系数70（非90） | Z97: 一二级|1000W-2000W|乡镇覆盖率
A98: 一二级 | B98: 1000W-2000W | C98: 增长层 | D98: 分销 | E98: 单店产出 | F98: 万元 | G98: 0.1125 | H98: 3.9万 | I98: 2.5 | J98: 30 | K98: 固定30分 | L98: 单店产值处于同类经销商中的末位水平，门店产出普遍偏低。建议全面诊断门店运营问题，制定系统性提升方案；加强门店陈列、促销和服务管理，提升单店产出；建立门店运营督导机制，确保改进措施执行到位。 | M98: 3.1 | N98: 50 | O98: 固定50分 | P98: 单店产值处于同类经销商中的中等偏下水平，门店之间产值差异较大，整体水平偏低，单店运营效率有待提升。建议提升铺货率和拜访频次，激活低效门店。 | Q98: 3.9 | R98: 70 | S98: 固定70分 | T98: 单店产值处于同类经销商中的中等偏上水平，网络基础较好。大部分门店运营正常，少数门店产值偏低，建议聚焦低产值网点，提升铺货率和销售能力。 | U98: ≥3.9 | V98: 90 | W98: 固定90分（满分） | X98: 单店产值处于同类经销商中的领先水平，头部门店表现突出。建议分析头部门店成功经验，复制推广至其他门店，防范因过度依赖少数头部门店而导致的结构性风险。 | Z98: 一二级|1000W-2000W|单店产出
A99: 一二级 | B99: 1000W-2000W | C99: 增长层 | D99: 零售 | E99: 会员数量 | F99: 人 | G99: 0.025 | H99: 126人 | I99: 29 | J99: 30 | K99: 固定30分 | L99: 会员数量处于同类经销商中的末位水平，客户数量严重缺失，市场影响力弱。建议制定会员快速发展计划，通过多种渠道吸纳会员；建立会员入门优惠机制，降低会员加入门槛；加强会员服务基础建设，提升会员留存率。 | M99: 74 | N99: 50 | O99: 固定50分 | P99: 会员数量处于同类经销商中的中等偏下水平，客户基础薄弱，尚未形成规模。建议制定会员发展计划，通过工人会和小区推广等形式，扩大会员规模；建立会员服务体系，提升会员满意度和忠诚度。 | Q99: 126 | R99: 70 | S99: 固定70分 | T99: 会员数量处于同类经销商中的中等偏上水平，客户基础较好，具备零售业务基础。建议持续挖掘会员价值，提升转化率。 | U99: ≥126 | V99: 90 | W99: 固定90分（满分） | X99: 会员数量处于同类经销商中的领先水平，市场影响力强，客户资源丰富。建议建立会员分级管理体系，提升高价值会员服务质量；制定会员活跃度提升计划，增强会员粘性。 | Z99: 一二级|1000W-2000W|会员数量
A100: 一二级 | B100: 1000W-2000W | C100: 增长层 | D100: 零售 | E100: 会员人均产出 | F100: 万元/人 | G100: 0.025 | H100: 0.65万/人 | I100: 0.341 | J100: 30 | K100: 固定30分 | L100: 会员人均产出处于同类经销商中的末位水平，客户价值低，消费转化困难。建议安排专人负责，勤沟通，多开展培训会、订货会等，制定会员消费激励计划，提高会员消费频次和客单价。 | M100: 0.52 | N100: 50 | O100: 固定50分 | P100: 会员人均产出处于同类经销商中的中等偏下水平，价值转化不足，会员消费频次低。建议多开展培训会、订货会等，建立会员激励机制，提高会员消费积极性。 | Q100: 0.65 | R100: 70 | S100: 固定70分 | T100: 会员人均产出处于同类经销商中的中等偏上水平，会员产出良好，贡献稳定，高价值会员占比有待提升。建议建立会员价值提升机制，持续挖掘会员潜在价值；识别高潜力会员，制定专项服务计划。 | U100: ≥0.65 | V100: 90 | W100: 固定90分（满分） | X100: 会员人均产出处于同类经销商中的领先水平，核心会员粘性强、贡献大。建议与核心会员签订协议，建立长期合作关系，保证稳定性。 | Z100: 一二级|1000W-2000W|会员人均产出
...

Sheet 数据底稿2
A1: 附加分指标参考值 & 评语底稿
A2: ▌ 一、可打分指标 — 参考值（P70 / P50 / P30）
A3: 指标 | B3: 档位 | C3: 超特300W-1000W | D3: 超特1000W-2000W | E3: 超特2000W+ | F3: 一二级300W-1000W | G3: 一二级1000W-2000W | H3: 一二级2000W+ | I3: 三四级300W-1000W | J3: 三四级1000W-2000W | K3: 三四级2000W+
A4: 会员活跃率 | B4: P70 | C4: 0.1318 | D4: 0.1318 | E4: 0.1318 | F4: 0.1432 | G4: 0.1075 | H4: 0.1075 | I4: 0.1406 | J4: 0.1318 | K4: 0.1318
B5: P50 | C5: 0.0858 | D5: 0.0858 | E5: 0.0858 | F5: 0.0696 | G5: 0.0678 | H5: 0.0678 | I5: 0.0931 | J5: 0.0858 | K5: 0.0858
B6: P30 | C6: 0.051 | D6: 0.051 | E6: 0.051 | F6: 0.0492 | G6: 0.037 | H6: 0.037 | I6: 0.0578 | J6: 0.051 | K6: 0.051
A7: 家装销售占比 | B7: P70 | C7: 0.038 | D7: 0.038 | E7: 0.038 | F7: 0.038 | G7: 0.038 | H7: 0.038 | I7: 0.038 | J7: 0.038 | K7: 0.038
B8: P50 | C8: 0.0228 | D8: 0.0228 | E8: 0.0228 | F8: 0.0228 | G8: 0.0228 | H8: 0.0228 | I8: 0.0228 | J8: 0.0228 | K8: 0.0228
B9: P30 | C9: 0.0136 | D9: 0.0136 | E9: 0.0136 | F9: 0.0136 | G9: 0.0136 | H9: 0.0136 | I9: 0.0136 | J9: 0.0136 | K9: 0.0136
A10: 家装公司产出/月 | B10: P70 | C10: 2741 | D10: 2741 | E10: 2741 | F10: 2832 | G10: 2832 | H10: 2832 | I10: 2864 | J10: 2864 | K10: 2864
B11: P50 | C11: 1523 | D11: 1523 | E11: 1523 | F11: 1804 | G11: 1804 | H11: 1804 | I11: 1512 | J11: 1512 | K11: 1512
B12: P30 | C12: 1188 | D12: 1188 | E12: 1188 | F12: 765 | G12: 765 | H12: 765 | I12: 863 | J12: 863 | K12: 863
A13: 月均工单数量 | B13: P80(优秀线) | C13: 38 | D13: 38 | E13: 38 | F13: 38 | G13: 38 | H13: 38 | I13: 38 | J13: 38 | K13: 38
B14: P50 | C14: 16 | D14: 16 | E14: 16 | F14: 16 | G14: 16 | H14: 16 | I14: 16 | J14: 16 | K14: 16
B15: P30 | C15: 10 | D15: 10 | E15: 10 | F15: 10 | G15: 10 | H15: 10 | I15: 10 | J15: 10 | K15: 10
A16: 工单转化率 | B16: P70 | C16: 0.274 | D16: 0.274 | E16: 0.274 | F16: 0.274 | G16: 0.274 | H16: 0.274 | I16: 0.274 | J16: 0.274 | K16: 0.274
B17: P50 | C17: 0.2334 | D17: 0.2334 | E17: 0.2334 | F17: 0.2334 | G17: 0.2334 | H17: 0.2334 | I17: 0.2334 | J17: 0.2334 | K17: 0.2334
B18: P30 | C18: 0.2061 | D18: 0.2061 | E18: 0.2061 | F18: 0.2061 | G18: 0.2061 | H18: 0.2061 | I18: 0.2061 | J18: 0.2061 | K18: 0.2061
A20: ▌ 二、可打分指标 — 附加分评语（四档：≥P70 / P50~P70 / P30~P50 / <P30）
A21: 指标 | B21: ≥P70 评语 | C21: P50~P70 评语 | D21: P30~P50 评语 | E21: <P30 评语
A22: 会员活跃率 | B22: 零售会员活跃度已达参考值。 | C22: 会员活跃率接近参考值，仍有提升空间 | D22: 会员活跃率偏低，会员价值未能有效转化 | E22: 会员活跃率显著低于参考值，需重点突破
A23: 家装销售占比 | B23: 家装销售占比已达参考值。 | C23: 家装销售占比接近参考值，可继续优化销售结构 | D23: 家装销售占比未达参考值，需结合生意状态调整销售结构 | E23: 家装销售占比显著偏低，亟需开发家装渠道，如油工、设计带动等
A24: 家装公司产出/月 | B24: 单家装公司产出达标。 | C24: 单家装公司产出接近参考值，可持续挖掘单客价值 | D24: 单家装公司产出未达参考值，建议关注B端客户单客价值挖掘 | E24: 单家装公司产出显著偏低，需重点突破家装渠道
A25: 工单转化率 | B25: 工单转化率已达参考值，在维持转化率的同时关注工单质量 | C25: 工单转化率接近参考值，可根据生意状态调整服务推广策略 | D25: 工单转化率偏低，建议加强服务推广力度 | E25: 工单转化率显著偏低，需重点优化服务流程
A26: 月均工单数量 | B26: 月均工单数量已达参考值。 | C26: 月均工单数量接近参考值，可进一步优化服务流程 | D26: 月均工单数量偏低，建议优化服务流程，提升月均工单处理量 | E26: 月均工单数量显著偏低，需重点突破服务承接能力，提升月均工单规模
A42: ▌ 三、区域竞争格局评语
A43: 条件（倍率） | B43: 竞争格局评语
A44: >1.5 | B44: 竞争格局：区域领先，占据优势
A45: 0.8~1.5 | B45: 竞争格局：势均力敌，激烈胶着
A46: 0.5~0.8 | B46: 竞争格局：差距明显，需加大投入力度
A47: <0.5 | B47: 竞争格局：敌强我弱，面临压制
A49: ▌ 四、品类及渠道参考值
A50: 组合键 | B50: 防水 | C50: 砂浆 | D50: 美缝 | E50: 卷材 | F50: 墙辅 | G50: 胶业 | H50: 管业 | I50: 分销 | J50: 零售 | K50: 家装 | L50: 服务 | M50: 品类结构（优秀值） | N50: 渠道结构（优秀值）
A51: 超特300W-1000W | B51: 245.5万 | C51: 274万 | D51: 33.1万 | E51: 505.9万 | F51: 54.1万 | G51: 448.1万 | H51: / | I51: 649.2万 | J51: 22.1万 | K51: 25.7万 | L51: 12.4万 | M51: 30 : 23 : 3 : 41 : 4 : 0 | N51: 47 : 1 : 2
A52: 超特1000W-2000W | B52: 800.7万 | C52: 563.8万 | D52: 115万 | E52: 1072万 | F52: 61.4万 | G52: 8.4万 | H52: / | I52: 1485万 | J52: 22.4万 | K52: 60.7万 | L52: 9.6万 | M52: 37 : 25 : 5 : 32 : 1 : 1 | N52: 76 : 1 : 4
A53: 超特2000W+ | B53: 1334万 | C53: 1403万 | D53: 435.1万 | E53: 341.3万 | F53: 115.1万 | G53: 10.3万 | H53: / | I53: 2510万 | J53: 4.5万 | K53: 35.9万 | L53: 30万 | M53: 399 : 356 : 79 : 143 : 22 : 2 | N53: 93 : 1 : 6
A54: 一二级300W-1000W | B54: 275.4万 | C54: 291.1万 | D54: 62.8万 | E54: 341万 | F54: 40.6万 | G54: 63.7万 | H54: 35.5万 | I54: 646.3万 | J54: 30万 | K54: 21.7万 | L54: 5.1万 | M54: 36 : 35 : 6 : 18 : 4 : 1 | N54: 92 : 3 : 5
A55: 一二级1000W-2000W | B55: 596.1万 | C55: 664.9万 | D55: 108.4万 | E55: 413.7万 | F55: 99.8万 | G55: 13.3万 | H55: 33.2万 | I55: 1454万 | J55: 67.7万 | K55: 47.2万 | L55: 11.5万 | M55: 44 : 42 : 10 : 23 : 2 : 5 | N55: 91 : 4 : 5
A56: 一二级2000W+ | B56: 1238.6万 | C56: 1370.1万 | D56: 330.9万 | E56: 352.3万 | F56: 24.8万 | G56: 87.4万 | H56: / | I56: 2703.2万 | J56: 82.9万 | K56: 81.9万 | L56: 6.8万 | M56: 40 : 39 : 8 : 9 : 1 : 2 | N56: 92 : 3 : 5
A57: 三四级300W-1000W | B57: 200.8万 | C57: 228.8万 | D57: 43.8万 | E57: 121.6万 | F57: 35.6万 | G57: 29.3万 | H57: 24.6万 | I57: 507.8万 | J57: 28.4万 | K57: 15.7万 | L57: 4.9万 | M57: 34 : 39 : 7 : 12 : 4 : 4 | N57: 95 : 5 : 3
A58: 三四级1000W-2000W | B58: 458.8万 | C58: 754.2万 | D58: 112.7万 | E58: 189.2万 | F58: 52.7万 | G58: 20.2万 | H58: 21.3万 | I58: 1250.5万 | J58: 71.3万 | K58: 28.7万 | L58: 3.9万 | M58: 33 : 44 : 7 : 10 : 2 : 4 | N58: 93：04：03
A59: 三四级2000W+ | B59: 1462.9万 | C59: 2294.6万 | D59: 318.2万 | E59: / | F59: / | G59: / | H59: / | I59: 3103.6万 | J59: 26.1万 | K59: / | L59: / | M59: 37 : 50 : 5 : 5 : 2 : 1 | N59: 95 : 3 : 3
A61: ▌ 五、分品类数据（区域经理填写）
A62: 品类 | B62: 品类单价(元/m²) | C62: 雨虹实际销售额(万元)
A63: 防水 | B63: 5 | C63: 0
A64: 砂浆 | B64: 10 | C64: 0
A65: 美缝 | B65: 6 | C65: 0
A66: 卷材 | B66: 10 | C66: 0
A67: 墙辅 | B67: 10 | C67: 100
A68: 胶业 | B68: 2 | C68: 0
A69: 管业 | B69: 10 | C69: 0
A70: 合计 | B70: =SUM(B63:B69) -> 53 | C70: =SUM(C63:C69) -> 100
A73: ▌ 六、数据备注
A74: 分位值直接从原始数据（商评估项目-数据补充-解密.xlsx）重新计算。清洗规则：坎级＜300W剔除、活跃率=0剔除、家装公司数量=0剔除、工单量=0剔除。
A75: 1. 会员活跃率 超特1000W+: n=28<30, 用总体中位数替代 (P70=0.1318)
A76: 2. 会员活跃率 三四级1000W+: n=28<30, 用总体中位数替代 (P70=0.1318)
A77: 3. 会员活跃率 超特300W-1000W: n=19<30, 用总体中位数替代 (P70=0.1318)
A78: 4. 家装销售占比: 全局分位值，排除零值样本后计算（n=346/632，零值占比45.3%）
A79: 5. 月均工单数量: ①按服务商名称合并维修+防铺美25年工单（去重55家），总服务商826家；②剔除月均≤5单的微小服务商473家（占57.3%，月均不到1单的有253家），保留353家；③以P80替代P70作为优秀线（P80=38>原P70=10），分位值取整。原因：原始数据极度右偏，32.9%服务商月均<1单，P70仅9.75单/月不具备优秀线参考意义
A80: 6. 工单转化率: 全局样本（不分九宫格），n=168。维修-转单率 线上渠道

Sheet 数据底稿3
A1: 最终得分权重配置
A2: 指标类别 | B2: 权重
A3: 定量指标 | B3: 0.8
A4: 附加分 | B4: 0.2
A5: 合计 | B5: =SUM(B3:B4) -> 1
A7: 说明：修改权重值后，动态诊断表的最终得分将自动更新。两项权重之和应为100%。
